Workbook
Name _5面遮水: #REF!
Name _5面遮水: #REF!
Name _5面遮水: #REF!
Name _5面遮水: #REF!
Name _5面遮水: '債務負担行為積算 (数式)'!#REF!
Name _5面遮水: '債務負担行為積算 (全部盛り) '!#REF!
Name _5面遮水: #REF!
Name _6面遮水: #REF!
Name _6面遮水: #REF!
Name _6面遮水: #REF!
Name _6面遮水: #REF!
Name _6面遮水: '債務負担行為積算 (数式)'!#REF!
Name _6面遮水: '債務負担行為積算 (全部盛り) '!#REF!
Name _6面遮水: #REF!
Name _シート無: #REF!
Name _シート無: #REF!
Name _シート無: #REF!
Name _シート無: #REF!
Name _シート無: '債務負担行為積算 (数式)'!#REF!
Name _シート無: '債務負担行為積算 (全部盛り) '!#REF!
Name _シート無: #REF!
Name ・・・: #REF!
Name ・・・: #REF!
Name a: #REF!
Name a: [1]会場形態!$A$2:$A$6
Name a: [1]会場形態!$A$2:$A$6
Name a: #REF!
Name a: #REF!
Name a: #REF!
Name a: '債務負担行為積算 (数式)'!#REF!
Name a: '債務負担行為積算 (全部盛り) '!#REF!
Name a: #REF!
Name AAM: #REF!
Name AAM: #REF!
Name AAM: #REF!
Name AAM: '債務負担行為積算 (数式)'!#REF!
Name AAM: '債務負担行為積算 (全部盛り) '!#REF!
Name AAM: #REF!
Name ah: #REF!
Name ah: #REF!
Name ah: #REF!
Name ah: '債務負担行為積算 (数式)'!#REF!
Name ah: '債務負担行為積算 (全部盛り) '!#REF!
Name ah: #REF!
Name AIX: #REF!
Name AIX: #REF!
Name AIX: #REF!
Name AIX: '債務負担行為積算 (数式)'!#REF!
Name AIX: '債務負担行為積算 (全部盛り) '!#REF!
Name AIX: #REF!
Name AJC: #REF!
Name AJC: #REF!
Name AJC: #REF!
Name AJC: '債務負担行為積算 (数式)'!#REF!
Name AJC: '債務負担行為積算 (全部盛り) '!#REF!
Name AJC: #REF!
Name AJG: #REF!
Name AJG: #REF!
Name AJG: #REF!
Name AJG: '債務負担行為積算 (数式)'!#REF!

Sheet Sheet1
B1: 施設番号 | C1: 施設名 | D1: 住所 | E1: 市町村
B2: 4 | C2: =VLOOKUP(B2,#REF!,2,FALSE) -> #REF! | D2: =VLOOKUP(B2,#REF!,3,FALSE) -> #REF! | E2: 一宮市
B3: 8 | C3: =VLOOKUP(B3,#REF!,2,FALSE) -> #REF! | D3: =VLOOKUP(B3,#REF!,3,FALSE) -> #REF! | E3: 春日井市
B4: 12 | C4: =VLOOKUP(B4,#REF!,2,FALSE) -> #REF! | D4: =VLOOKUP(B4,#REF!,3,FALSE) -> #REF! | E4: 小牧市
B5: 15 | C5: =VLOOKUP(B5,#REF!,2,FALSE) -> #REF! | D5: =VLOOKUP(B5,#REF!,3,FALSE) -> #REF! | E5: 小牧市
B6: 21 | C6: =VLOOKUP(B6,#REF!,2,FALSE) -> #REF! | D6: =VLOOKUP(B6,#REF!,3,FALSE) -> #REF! | E6: 名古屋市
B7: 22 | C7: =VLOOKUP(B7,#REF!,2,FALSE) -> #REF! | D7: =VLOOKUP(B7,#REF!,3,FALSE) -> #REF! | E7: 名古屋市
B8: 23 | C8: =VLOOKUP(B8,#REF!,2,FALSE) -> #REF! | D8: =VLOOKUP(B8,#REF!,3,FALSE) -> #REF! | E8: 名古屋市
B9: 24 | C9: =VLOOKUP(B9,#REF!,2,FALSE) -> #REF! | D9: =VLOOKUP(B9,#REF!,3,FALSE) -> #REF! | E9: 名古屋市
B10: 28 | C10: =VLOOKUP(B10,#REF!,2,FALSE) -> #REF! | D10: =VLOOKUP(B10,#REF!,3,FALSE) -> #REF! | E10: 名古屋市
B11: 34 | C11: =VLOOKUP(B11,#REF!,2,FALSE) -> #REF! | D11: =VLOOKUP(B11,#REF!,3,FALSE) -> #REF! | E11: 名古屋市
B12: 39 | C12: =VLOOKUP(B12,#REF!,2,FALSE) -> #REF! | D12: =VLOOKUP(B12,#REF!,3,FALSE) -> #REF! | E12: 名古屋市
B13: 40 | C13: =VLOOKUP(B13,#REF!,2,FALSE) -> #REF! | D13: =VLOOKUP(B13,#REF!,3,FALSE) -> #REF! | E13: 名古屋市
... B123: 3025 | C123: =VLOOKUP(B123,#REF!,2,FALSE) -> #REF! | D123: =VLOOKUP(B123,#REF!,3,FALSE) -> #REF! | E123: 豊田市
B124: 3027 | C124: =VLOOKUP(B124,#REF!,2,FALSE) -> #REF! | D124: 大阪府大阪市住之江区南港北1丁目13-11 · | E124: 大阪府大阪市
B125: 3028 | C125: =VLOOKUP(B125,#REF!,2,FALSE) -> #REF! | D125: =VLOOKUP(B125,#REF!,3,FALSE) -> #REF! | E125: 静岡県伊豆市
B126: 3029 | C126: =VLOOKUP(B126,#REF!,2,FALSE) -> #REF! | D126: =VLOOKUP(B126,#REF!,3,FALSE) -> #REF! | E126: 大阪府大阪市
B127: 3030 | C127: =VLOOKUP(B127,#REF!,2,FALSE) -> #REF! | D127: =VLOOKUP(B127,#REF!,3,FALSE) -> #REF! | E127: 東京都江東区
B128: 3031 | C128: =VLOOKUP(B128,#REF!,2,FALSE) -> #REF! | D128: =VLOOKUP(B128,#REF!,3,FALSE) -> #REF! | E128: 岡崎市
B129: 3032 | C129: =VLOOKUP(B129,#REF!,2,FALSE) -> #REF! | D129: =VLOOKUP(B129,#REF!,3,FALSE) -> #REF! | E129: 新城市
B130: 3033 | C130: =VLOOKUP(B130,#REF!,2,FALSE) -> #REF! | D130: =VLOOKUP(B130,#REF!,3,FALSE) -> #REF! | E130: 岐阜県多治見市
B131: 3034 | C131: =VLOOKUP(B131,#REF!,2,FALSE) -> #REF! | D131: =VLOOKUP(B131,#REF!,3,FALSE) -> #REF! | E131: 静岡県浜松市

Sheet 予算管理比較積算 (VIL移管前)
A1: 24/10時点 | B1: 全体予算 | D1: アジア | H1: 一旦計算（非表示） | J1: パラ | N1: 一旦計算（非表示） | P1: 全体
B2: 予算項目 | C2: 予算金額（VIL移管分含む） | D2: 項目 | E2: 単価 | F2: 人数 | G2: 泊数 | I2: 小計 | J2: 項目 | K2: 単価 | L2: 人数 | M2: 泊数 | O2: 小計 | P2: 合計
B3: 客室確保費（朝食付） | C3: 15457292778 | D3: ホテル（選手団） | E3: 3042691395 | F3: 1 | G3: 1 | I3: =E3*F3*G3 -> 3042691395 | J3: ホテル（選手団） | K3: 2596055904 | L3: 1 | M3: 1 | O3: =K3*L3*M3 -> 2596055904 | P3: =I3+O3 -> 5638747299
D4: ホテル（選手団以外） | E4: 7718814575 | F4: 1 | G4: 1 | I4: =E4*F4*G4 -> 7718814575 | J4: ホテル（選手団以外） | K4: 2099730904 | L4: 1 | M4: 1 | O4: =K4*L4*M4 -> 2099730904 | P4: =I4+O4 -> 9818545479
D5: （ファミリーAINAGOC負担） | E5: 2004704909 | F5: 1 | G5: 1 | I5: =E5*F5*G5 -> 2004704909 | J5: （ファミリーAINAGOC負担） | K5: 197828150 | L5: 1 | M5: 1 | O5: =K5*L5*M5 -> 197828150 | P5: =I5+O5 -> 2202533059
D6: （ファミリー利用者負担） | E6: 881565432 | F6: 1 | G6: 1 | I6: =E6*F6*G6 -> 881565432 | J6: （ファミリー利用者負担） | K6: 449927739 | L6: 1 | M6: 1 | O6: =K6*L6*M6 -> 449927739 | P6: =I6+O6 -> 1331493171
D7: （技術役員） | E7: 723774664 | F7: 1 | G7: 1 | I7: =E7*F7*G7 -> 723774664 | J7: （技術役員） | K7: 217404288 | L7: 1 | M7: 1 | O7: =K7*L7*M7 -> 217404288 | P7: =I7+O7 -> 941178952
D8: （スポンサー利用者負担） | E8: =SUM('財政見通し積算 (全SH全項目統合版）'!AD29) -> 2342187094 | F8: 1 | G8: 1 | I8: =E8*F8*G8 -> 2342187094 | J8: （スポンサー利用者負担） | K8: 783186617 | L8: 1 | M8: 1 | O8: =K8*L8*M8 -> 783186617 | P8: =I8+O8 -> 3125373711
D9: （メディア利用者負担） | E9: =SUM('財政見通し積算 (全SH全項目統合版）'!AD30) -> 1766582476 | F9: 1 | G9: 1 | I9: =E9*F9*G9 -> 1766582476 | J9: （メディア利用者負担） | K9: =SUM('財政見通し積算 (全SH全項目統合版）'!AD35) -> 451384110 | L9: 1 | M9: 1 | O9: =K9*L9*M9 -> 451384110 | P9: =I9+O9 -> 2217966586
B10: 飲食費（昼食及び夕食） | C10: 2004611332 | D10: ホテル（選手団） | E10: 16900 | F10: 3546 | G10: 11 | H10: =F10*G10 -> 39006 | I10: =E10*F10*G10 -> 659201400 | J10: ホテル（選手団） | K10: 16900 | L10: =3305*0.6 -> 1983 | M10: 13 | N10: =L10*M10 -> 25779 | O10: =K10*L10*M10 -> 435665100 | P10: =I10+O10 -> 1094866500
D11: ホテル（選手団以外） | E11: =SUM(E12:E13) -> 487471732 | F11: 1 | G11: 1 | I11: =E11*F11*G11 -> 487471732 | J11: ホテル（選手団以外） | K11: =SUM(K12:K13) -> 77936100 | L11: 1 | M11: 1 | O11: =K11*L11*M11 -> 77936100 | P11: =I11+O11 -> 565407832
D12: （ファミリーAINAGOC負担） | E12: 324285720 | F12: 1 | G12: 1 | I12: =E12*F12*G12 -> 324285720 | J12: （ファミリーAINAGOC負担） | K12: 23802106 | L12: 1 | M12: 1 | O12: =K12*L12*M12 -> 23802106 | P12: =I12+O12 -> 348087826
D13: （ファミリー利用者負担） | E13: 163186012 | F13: 1 | G13: 1 | I13: =E13*F13*G13 -> 163186012 | J13: （ファミリー利用者負担） | K13: 54133994 | L13: 1 | M13: 1 | O13: =K13*L13*M13 -> 54133994 | P13: =I13+O13 -> 217320006
D14: コンテナ | E14: 21000 | F14: 725 | G14: 11 | H14: =F14*G14 -> 7975 | I14: 167496000 | J14: コンテナ（選手団） | K14: 21000 | L14: =695*0.6 -> 417 | M14: 13 | N14: =L14*M14 -> 5421 | O14: =K14*L14*M14 -> 113841000 | P14: =I14+O14 -> 281337000
I15: =E15*F15*G15 -> 0 | J15: コンテナ（NOC本部） | K15: 21000 | L15: 200 | M15: 15 | N15: =L15*M15 -> 3000 | O15: =K15*L15*M15 -> 63000000 | P15: =I15+O15 -> 63000000
B16: 飲食費（ハラル・ヴィーガン対応） | C16: 1354510000 | D16: ホテル | E16: 19000 | F16: 4189 | G16: 11 | H16: =F16*G16 -> 46079 | I16: =E16*F16*G16 -> 875501000 | J16: ホテル | K16: 19000 | L16: =3305*0.4 -> 1322 | M16: 13 | N16: =L16*M16 -> 17186 | O16: =K16*L16*M16 -> 326534000 | P16: =I16+O16 -> 1202035000 | Q16: =P16/2 -> 601017500
D17: コンテナ | E17: 19000 | F17: 401 | G17: 11 | H17: =F17*G17 -> 4411 | I17: =E17*F17*G17 -> 83809000 | J17: コンテナ | K17: 19000 | L17: =695*0.4 -> 278 | M17: 13 | N17: =L17*M17 -> 3614 | O17: =K17*L17*M17 -> 68666000 | P17: =I17+O17 -> 152475000 | Q17: =P17/2 -> 76237500
B18: 飲食費（グラブアンドゴー） | C18: 183440400 | D18: ホテル | E18: 880 | F18: 9235 | G18: 11 | H18: =F18*G18 -> 101585 | I18: =E18*F18*G18 -> 89394800 | J18: ホテル | K18: 880 | L18: 3305 | M18: 13 | N18: =L18*M18 -> 42965 | O18: =K18*L18*M18 -> 37809200 | P18: =I18+O18 -> 127204000
D19: コンテナ | E19: 880 | F19: 1002 | G19: 11 | H19: =F19*G19 -> 11022 | I19: =E19*F19*G19 -> 9699360 | J19: コンテナ | K19: 880 | L19: 695 | M19: 13 | N19: =L19*M19 -> 9035 | O19: =K19*L19*M19 -> 7950800 | P19: =I19+O19 -> 17650160
D20: 船 | E20: 880 | F20: 2436 | G20: 18 | H20: =F20*G20 -> 43848 | I20: =E20*F20*G20 -> 38586240 | O20: =K20*L20*M20 -> 0 | P20: =I20+O20 -> 38586240
B21: 飲食費（アスリートミール：船） | C21: 920808000 | D21: 船 | E21: 21000 | F21: 2436 | G21: 18 | H21: =F21*G21 -> 43848 | I21: =E21*F21*G21 -> 920808000 | O21: =K21*L21*M21 -> 0 | P21: =I21+O21 -> 920808000
B22: 飲食費（空港島運営及びガーデンふ頭運営及び仮設厨房）内容については別紙参照 | C22: 2411358140 | D22: 空港島運営経費 | E22: 1336000000 | F22: 1 | G22: 1 | I22: =E22*F22*G22 -> 1336000000 | P22: =I22+O22 -> 1336000000
D23: 空港島仮設厨房経費 | E23: 101358140 | F23: 1 | G23: 1 | I23: =E23*F23*G23 -> 101358140 | O23: =K23*L23*M23 -> 0 | P23: =I23+O23 -> 101358140
D24: ガーデン運営経費 | E24: 408277000 | F24: 1 | G24: 1 | I24: =E24*F24*G24 -> 408277000 | J24: ガーデン運営経費 | K24: 360000000 | L24: 1 | M24: 1 | O24: =K24*L24*M24 -> 360000000 | P24: =I24+O24 -> 768277000
D25: ガーデン仮設厨房経費 | E25: 205723000 | F25: 1 | G25: 1 | I25: =E25*F25*G25 -> 205723000 | O25: =K25*L25*M25 -> 0 | P25: =I25+O25 -> 205723000
B26: 飲食費（その他経費（支援機器設置等）） | C26: 88652020 | D26: ホテル | E26: 6000000 | F26: 12 | G26: 1 | I26: =E26*F26*G26 -> 72000000 | J26: ホテル | K26: 2378860 | L26: 7 | M26: 1 | O26: =K26*L26*M26 -> 16652020 | P26: =I26+O26 -> 88652020
B27: 会議室等確保費 | C27: 3450377147 | D27: ホテル（選手団） | E27: 858587762 | F27: 1 | G27: 1 | I27: =E27*F27*G27 -> 858587762 | J27: ホテル（選手団） | K27: 1030634912 | L27: 1 | M27: 1 | O27: =K27*L27*M27 -> 1030634912 | P27: =I27+O27 -> 1889222674
D28: ホテル（選手団以外）（ファミリー） | E28: 1178445153 | F28: 1 | G28: 1 | I28: =E28*F28*G28 -> 1178445153 | J28: ホテル（選手団以外）（ファミリー） | K28: 382709320 | L28: 1 | M28: 1 | O28: =K28*L28*M28 -> 382709320 | P28: =I28+O28 -> 1561154473
B29: 営業補償費 | C29: 54466667 | D29: ホテル（選手団以外）（ファミリー） | E29: 34400000 | F29: 1 | G29: 1 | I29: =E29*F29*G29 -> 34400000 | J29: ホテル（選手団以外）（ファミリー） | K29: 20066667 | L29: 1 | M29: 1 | O29: =K29*L29*M29 -> 20066667 | P29: =I29+O29 -> 54466667
B30: 合計 | C30: =SUM(C3:C29) -> 25925516484 | I30: =SUM(I3:I4,I10:I11,I14,I16:I17,I18,I19:I20,I21,I22:I25,I26,I27:I28,I29) -> 18288264557 | O30: =SUM(O3:O4,O10:O11,O14:O15,O16:O17,O18,O19,O24,O26,O27:O28,O29) -> 7637251927 | P30: =SUM(P3:P4,P10:P11,P14:P15,P16:P17,P18,P19:P20,P21,P22:P25,P26,P27:P28,P29) -> 25925516484
A33: 25/6時点 | B33: 全体額 | D33: アジア | J33: パラ | P33: 全体
B34: 予算項目 | C34: 予算金額（VIL移管分含む） | D34: 項目 | E34: 単価 | F34: 人数 | G34: 泊数 | I34: 小計 | J34: 項目 | K34: 単価 | L34: 人数 | M34: 泊数 | O34: 小計 | P34: 合計 | Q34: 差し引き（項目ごと） | R34: 差し引き（項目ごと）
B35: 客室確保費（朝食付） | C35: 15457292778 | D35: ホテル（選手団） | E35: ='財政見通し積算 (全SH全項目統合版）'!C26 -> #REF! | F35: 1 | G35: 1 | I35: =E35*F35*G35 -> #REF! | J35: ホテル（選手団） | K35: ='財政見通し積算 (全SH全項目統合版）'!C31 -> #REF! | L35: 1 | M35: 1 | O35: =K35*L35*M35 -> #REF! | P35: =I35+O35 -> #REF! | Q35: =SUM(P35:P36)-C35 -> #REF! | R35: =SUM(P35:P36)-C35 -> #REF!
D36: ホテル（選手団以外） | I36: =SUM(I37:I41) -> 7.8708056e+09 | J36: ホテル（選手団以外） | O36: =SUM(O37:O41) -> 2.0563535e+09 | P36: =SUM(P37:P41) -> 9.9271591e+09
D37: （ファミリーAINAGOC負担） | E37: ='財政見通し積算 (全SH全項目統合版）'!C27 -> 2204156998 | F37: 1 | G37: 1 | I37: =E37*F37*G37 -> 2204156998 | J37: （ファミリーAINAGOC負担） | K37: ='財政見通し積算 (全SH全項目統合版）'!C32-K38 -> 177614008 | L37: 1 | M37: 1 | O37: =K37*L37*M37 -> 177614008 | P37: =I37+O37 -> 2381771006
J38: （ファミリー利用者負担） | K38: =[47]【250327】アジパラファミリー!$BV$28 -> 294503792 | L38: 1 | M38: 1 | O38: =K38*L38*M38 -> 294503792 | P38: =I38+O38 -> 294503792
D39: （技術役員） | E39: ='財政見通し積算 (全SH全項目統合版）'!C28 -> 1724607631 | F39: 1 | G39: 1 | I39: =E39*F39*G39 -> 1724607631 | J39: （技術役員） | K39: ='財政見通し積算 (全SH全項目統合版）'!C33 -> 344907436 | L39: 1 | M39: 1 | O39: =K39*L39*M39 -> 344907436 | P39: =I39+O39 -> 2069515067
D40: （スポンサー利用者負担） | E40: ='財政見通し積算 (全SH全項目統合版）'!C29 -> 1.2854877e+09 | F40: 1 | G40: 1 | I40: =E40*F40*G40 -> 1.2854877e+09 | J40: （スポンサー利用者負担） | K40: ='財政見通し積算 (全SH全項目統合版）'!C34 -> 8.3703864e+08 | L40: 1 | M40: 1 | O40: =K40*L40*M40 -> 8.3703864e+08 | P40: =I40+O40 -> 2.1225263e+09
D41: （メディア利用者負担） | E41: ='財政見通し積算 (全SH全項目統合版）'!C30 -> 2656553304 | F41: 1 | G41: 1 | I41: =E41*F41*G41 -> 2656553304 | J41: （メディア利用者負担） | K41: ='財政見通し積算 (全SH全項目統合版）'!C35 -> 4.022896e+08 | L41: 1 | M41: 1 | O41: =K41*L41*M41 -> 4.022896e+08 | P41: =I41+O41 -> 3.0588429e+09
B42: 飲食費（昼食及び夕食） | C42: 2004611332 | D42: ホテル（選手団）昼食及び夕食 | E42: 16900 | F42: 58451 | G42: 1 | I42: =E42*F42*G42 -> 987821900 | J42: ホテル（選手団）昼食及び夕食 | K42: 16900 | L42: 31699 | M42: 1 | N42: =L42*M42 -> 31699 | O42: =K42*L42*M42 -> 535713100 | P42: =I42+O42 -> 1523535000 | Q42: =SUM(P42:P44,P47)-C42 -> #REF! | R42: =SUM(P42:P47)-C42 -> #REF!
D43: ホテル（選手団）ｱｽﾘｰﾄﾐｰﾙ差額 | E43: ='財政見通し積算 (全SH全項目統合版）'!E26 -> #REF! | F43: 1 | G43: 1 | I43: =E43*F43*G43 -> #REF! | J43: ホテル（選手団）ｱｽﾘｰﾄﾐｰﾙ差額 | K43: ='財政見通し積算 (全SH全項目統合版）'!E31 -> #REF! | L43: 1 | M43: 1 | O43: =K43*L43*M43 -> #REF! | P43: =SUM(I43,O43) -> #REF!
D44: ホテル（選手団以外） | I44: =SUM(I45:I46) -> 453261666 | J44: ホテル（選手団以外） | O44: =SUM(O45:O46) -> 72406400 | P44: =SUM(P45:P46) -> 525668066
D45: （ファミリーAINAGOC負担） | E45: ='財政見通し積算 (全SH全項目統合版）'!E27 -> 453261666 | F45: 1 | G45: 1 | I45: =E45*F45*G45 -> 453261666 | J45: （ファミリーAINAGOC負担） | K45: ='財政見通し積算 (全SH全項目統合版）'!E32-K46 -> 12202608 | L45: 1 | M45: 1 | O45: =K45*L45*M45 -> 12202608 | P45: =I45+O45 -> 465464274
J46: （ファミリー利用者負担） | K46: =[47]【250327】アジパラファミリー!$BS$28 -> 60203792 | L46: 1 | M46: 1 | O46: =K46*L46*M46 -> 60203792 | P46: =I46+O46 -> 60203792
D47: コンテナ（選手団・NOC）※3食 | E47: 21000 | F47: 22972 | G47: 1 | I47: =E47*F47*G47 -> 482412000 | J47: コンテナ（選手団・NOC）※3食 | K47: 21000 | L47: 8640 | M47: 1 | N47: =L47*M47 -> 8640 | O47: =K47*L47*M47 -> 181440000 | P47: =I47+O47 -> 663852000
B48: 飲食費（ハラル・ヴィーガン対応） | C48: 1354510000 | D48: ホテル自前 | E48: 19000 | F48: 8364 | G48: 1 | I48: =E48*F48*G48 -> 158916000 | J48: ホテル自前 | K48: 19000 | L48: 5536 | M48: 1 | N48: =L48*M48 -> 5536 | O48: =K48*L48*M48 -> 105184000 | P48: =I48+O48 -> 264100000 | Q48: =SUM(P48:P50)-C48 -> 316777800 | R48: =SUM(P48:P50)-C48 -> 316777800
D49: コンテナ | E49: 19000 | F49: 14409 | G49: 1 | I49: =E49*F49*G49 -> 273771000 | J49: コンテナ | K49: 19000 | L49: 5760 | M49: 1 | O49: =K49*L49*M49 -> 109440000 | P49: =I49+O49 -> 383211000
D50: 完調品対応 | E50: 22164 | F50: 30603 | G50: 1 | I50: =E50*F50*G50 -> 678284892 | J50: 完調品対応 | K50: 22164 | L50: 15597 | M50: 1 | N50: =L50*M50 -> 15597 | O50: =K50*L50*M50 -> 345691908 | P50: =I50+O50 -> 1023976800
B51: 飲食費（グラブアンドゴー） | C51: 183440400 | D51: ホテル | E51: 880 | F51: 97418 | G51: 1 | I51: =E51*F51*G51 -> 85727840 | J51: ホテル | K51: 880 | L51: 52832 | M51: 1 | N51: =L51*M51 -> 52832 | O51: =K51*L51*M51 -> 46492160 | P51: =I51+O51 -> 132220000 | Q51: =SUM(P51:P53)-C51 -> 40619040 | R51: =SUM(P51:P53)-C51 -> 40619040
D52: コンテナ | E52: 880 | F52: 37381 | G52: 1 | I52: =E52*F52*G52 -> 32895280 | J52: コンテナ | K52: 880 | L52: 14400 | M52: 1 | N52: =L52*M52 -> 14400 | O52: =K52*L52*M52 -> 12672000 | P52: =I52+O52 -> 45567280
D53: 船 | E53: 880 | F53: 52582 | G53: 1 | I53: =E53*F53*G53 -> 46272160 | O53: =K53*L53*M53 -> 0 | P53: =I53+O53 -> 46272160
B54: 飲食費（アスリートミール：船） | C54: 920808000 | D54: 船 | E54: 21000 | F54: 52582 | G54: 1 | I54: =E54*F54*G54 -> 1104222000 | O54: =K54*L54*M54 -> 0 | P54: =I54+O54 -> 1104222000 | Q54: =SUM(P54)-C54 -> 183414000
B55: 飲食費（空港島運営及びガーデンふ頭運営及び仮設厨房） | C55: 2411358140 | D55: 空港島運営経費 | E55: 1336000000 | F55: 1 | G55: 1 | I55: =E55*F55*G55 -> 1336000000 | P55: =I55+O55 -> 1336000000 | Q55: =SUM(P55:P58)-C55 -> 860 | R55: =SUM(P55:P58)-C55 -> 860
D56: 空港島仮設厨房経費 | E56: 101359000 | F56: 1 | G56: 1 | I56: =E56*F56*G56 -> 101359000 | O56: =K56*L56*M56 -> 0 | P56: =I56+O56 -> 101359000
D57: ガーデン運営経費 | E57: 408277000 | F57: 1 | G57: 1 | I57: =E57*F57*G57 -> 408277000 | J57: ガーデン運営経費 | K57: 360000000 | L57: 1 | M57: 1 | O57: =K57*L57*M57 -> 360000000 | P57: =I57+O57 -> 768277000
D58: ガーデン仮設厨房経費 | E58: 205723000 | F58: 1 | G58: 1 | I58: =E58*F58*G58 -> 205723000 | O58: =K58*L58*M58 -> 0 | P58: =I58+O58 -> 205723000
B59: 飲食費（その他経費（支援機器設置等）） | C59: 88652020 | D59: ホテル厨房機器レンタル | E59: 6000000 | F59: 12 | G59: 1 | I59: =E59*F59*G59 -> 72000000 | J59: ホテル厨房機器レンタル | K59: 2379000 | L59: 7 | M59: 1 | O59: =K59*L59*M59 -> 16653000 | P59: =I59+O59 -> 88653000 | Q59: =SUM(P59:P60,P61)-C59 -> 10458980 | R59: =SUM(P59:P60,P61)-C59 -> 10458980
D60: シップグラブ＆ゴー設備レンタル | E60: 9351000 | F60: 1 | G60: 1 | I60: =E60*F60*G60 -> 9351000 | P60: =I60+O60 -> 9351000
D61: シップグラブ＆ゴー備品レンタル | E61: 1107000 | F61: 1 | G61: 1 | I61: =E61*F61*G61 -> 1107000 | P61: =I61+O61 -> 1107000
B62: 会議室等確保費 | C62: 3450377147 | D62: ホテル（選手団） | E62: ='財政見通し積算 (全SH全項目統合版）'!D26 -> #REF! | F62: 1 | G62: 1 | I62: =E62*F62*G62 -> #REF! | J62: ホテル（選手団） | K62: ='財政見通し積算 (全SH全項目統合版）'!D31 -> #REF! | L62: 1 | M62: 1 | O62: =K62*L62*M62 -> #REF! | P62: =I62+O62 -> #REF! | Q62: =SUM(P62:P63)-C62 -> #REF! | R62: =SUM(P62:P63)-C62 -> #REF!
D63: ホテル（選手団以外） | I63: =SUM(I64:I65) -> 1.8941956e+09 | J63: ホテル（選手団以外） | O63: =SUM(O64:O65) -> 6.5639053e+08 | P63: =SUM(P64:P65) -> 2.5505861e+09
D64: （ファミリー） | E64: ='財政見通し積算 (全SH全項目統合版）'!D27 -> 1133891586 | F64: 1 | G64: 1 | I64: =E64*F64*G64 -> 1133891586 | J64: （ファミリー） | K64: ='財政見通し積算 (全SH全項目統合版）'!D32 -> 2.886576e+08 | L64: 1 | M64: 1 | O64: =K64*L64*M64 -> 2.886576e+08 | P64: =I64+O64 -> 1422549186
D65: （技術役員） | E65: ='財政見通し積算 (全SH全項目統合版）'!D28 -> 7.6030401e+08 | F65: 1 | G65: 1 | I65: =E65*F65*G65 -> 7.6030401e+08 | J65: （技術役員） | K65: ='財政見通し積算 (全SH全項目統合版）'!D33 -> 3.6773293e+08 | L65: 1 | M65: 1 | O65: =K65*L65*M65 -> 3.6773293e+08 | P65: =I65+O65 -> 1.1280369e+09
B66: 営業補償費 | C66: 54466667 | D66: ホテル | I66: =SUM(I67:I68) -> #REF! | J66: ホテル | O66: =SUM(O67:O68) -> #REF! | P66: =I66+O66 -> #REF! | Q66: =SUM(P66)-C66 -> #REF! | R66: =SUM(P66)-C66 -> #REF!
D67: （選手団） | E67: ='財政見通し積算 (全SH全項目統合版）'!F26 -> #REF! | F67: 1 | G67: 1 | I67: =E67*F67*G67 -> #REF! | J67: （選手団） | K67: ='財政見通し積算 (全SH全項目統合版）'!F31 -> #REF! | L67: 1 | M67: 1 | O67: =K67*L67*M67 -> #REF! | P67: =I67+O67 -> #REF!
D68: （ファミリー） | E68: ='財政見通し積算 (全SH全項目統合版）'!F27 -> 35875905 | F68: 1 | G68: 1 | I68: =E68*F68*G68 -> 35875905 | J68: （ファミリー） | K68: ='財政見通し積算 (全SH全項目統合版）'!F32 -> 792000 | L68: 1 | M68: 1 | O68: =K68*L68*M68 -> 792000 | P68: =I68+O68 -> 36667905
B69: ランドリーサービス費 | C69: 0 | D69: ランドリーサービス費（選手団以外） | E69: ='財政見通し積算 (全SH全項目統合版）'!I39 -> 74703200 | F69: 1 | G69: 1 | I69: =E69*F69*G69 -> 74703200 | J69: ランドリーサービス費（選手団以外） | K69: ='財政見通し積算 (全SH全項目統合版）'!I40 -> 20944000 | L69: 1 | M69: 1 | O69: =K69*L69*M69 -> 20944000 | P69: =SUM(I69,O69) -> 95647200 | Q69: =SUM(P69)-C69 -> 95647200 | R69: =SUM(P69)-C69 -> 95647200
B70: 合計 | C70: =SUM(C35:C66) -> 25925516484 | I70: =SUM(I35:I36,I42:I44,I47,I48:I50,I51:I53,I54,I55:I58,I59:I61,I62:I63,I66,I69) -> #REF! | O70: =SUM(O35:O36,O42:O44,O47,O48:O50,O51:O53,O54,O55:O58,O59:O61,O62:O63,O66,O69) -> #REF! | P70: =SUM(P35,P36,P42,P43,P44,P47,P48,P49,P50,P51,P52,P53,P54,P56,P55,P57,P58,P59,P60,P61,P62,P63,P66,P69) -> #REF! | Q70: =P70-C70 -> #REF! | R70: =SUM(I73,O73) -> #REF!
B71: ※技術役員・スポンサー・メディアのホテルについては、積算単価が2021年時点のものであるため、客室単価に1.34（宿泊料物価上昇率）を掛けている | Q71: 全体差し引き | R71: VIL移管Ver.
B72: ※技術役員の会議室費用については1.1（総合物価上昇率）を掛けている | G72: アジア差し引き | I72: =I70-I30 -> #REF! | M72: パラ差し引き | O72: =O70-O30 -> #REF!
B73: ※I列、O列で青色にしている部分がVIL移管 | G73: アジア差し引き | I73: =I70-I30 -> #REF! | M73: パラ差し引き | O73: =O70-O30 -> #REF!
G74: うち ACM積算分差し引き | I74: =SUM(I35,I36,I43,I44,I62,I63,I66,I69)-SUM(I3,I4,I11,I27,I28,I29) -> #REF! | M74: うち ACM積算分差し引き | O74: =SUM(O35,O36,O43,O44,O62,O63,O66,O69)-SUM(O3,O4,O11,O27,O28,O29) -> #REF! | Q74: 歳入減 | R74: 歳入減
G75: うち FNB積算分差し引き（ACM積算分） | I75: =SUM(I42,I47,I48:I50,I51:I53,I54,I55:I58,I59:I61)-SUM(I10,I14,I16:I17,I18:I20,I21,I22:I25,I26) -> 1016286132 | M75: うち FNB積算分差し引き（ACM積算分） | O75: =SUM(O42,O47,O48:O50,O51:O52,O57,O59)-SUM(O10,O14:O15,O16:O17,O18:O19,O24,O26) -> 283168048 | Q75: =SUM(I77,O77) -> -1.3560767e+09 | R75: =SUM(I77,O77) -> -1.3560767e+09
G76: うち FNB積算分差し引き（VIL移管分） | I76: =SUM(I47,I49,I52,I53,I54,I57,I58,I60,I61)-SUM(I14,I17,I19,I20,I21,I24,I25) -> 729631840 | M76: うち FNB積算分差し引き（VIL移管分） | O76: =SUM(O47,O49,O52,O54,O57)-SUM(O14,O15,O17,O19,O24) -> 50094200
G77: 利用者負担（歳入）差し引き | I77: =SUM(I38,I40,I41,I46)-SUM(I6,I8,I9,I13) -> -1.21148e+09 | M77: 利用者負担（歳入）差し引き | O77: =SUM(O38,O40,O41,O46)-SUM(O6,O8,O9,O13) -> -1.4459664e+08 | Q77: 実質全体差し引き | R77: 実質全体差し引き
G78: 参考 利用者負担を除いた場合の差し引き | I78: =SUM(I35,I37,I39,I42:I43,I45,I47,I48:I50,I51:I53,I54,I55:I58,I59:I61,I62:I63,I66,I69)-SUM(I3,I5,I7,I10,I12,I14,I16:I17,I18:I20,I21,I22:I25,I26,I27:I28,I29) -> #REF! | M78: 参考 利用者負担を除いた場合の差し引き | O78: =SUM(O35,O37,O39,O42:O43,O45,O47,O48:O50,O51:O53,O54,O55:O58,O59:O61,O62:O63,O66,O69)-SUM(O3,O5,O7,O10,O12,O14,O15,O16:O17,O18:O20,O21,O22:O25,O26,O27:O28,O29) -> #REF! | Q78: =I78+O78 -> #REF! | R78: =R70-R75 -> #REF!
B80: 現状積算外の費用 | D80: アジア | H80: 一旦計算（非表示） | J80: パラ | N80: 一旦計算（非表示）
D81: 項目 | E81: 単価 | F81: 人数 | G81: 泊数 | I81: 小計 | J81: 項目 | K81: 単価 | L81: 人数 | M81: 泊数 | O81: 小計
B82: 飲食費（昼食及び夕食） | D82: ホテル（選手団以外） （技術役員） | E82: ='財政見通し積算 (全SH全項目統合版）'!E28 -> 726706750 | F82: 1 | G82: 1 | I82: =E82*F82*G82 -> 726706750 | J82: ホテル（選手団以外） （技術役員） | K82: ='財政見通し積算 (全SH全項目統合版）'!E33 -> 195448750 | L82: 1 | M82: 1 | O82: =K82*L82*M82 -> 195448750 | P82: =I82+O82 -> 922155500
B83: 営業補償費 | D83: ホテル （クリーンベニュー自販機） | E83: ='財政見通し積算 (全SH全項目統合版）'!G26 -> #REF! | F83: 1 | G83: 1 | I83: =E83*F83*G83 -> #REF! | J83: ホテル （クリーンベニュー自販機） | K83: ='財政見通し積算 (全SH全項目統合版）'!G31 -> #REF! | L83: 1 | M83: 1 | O83: =K83*L83*M83 -> #REF! | P83: =I83+O83 -> #REF!
D84: ホテル （クリーンベニューテナント） | E84: ='財政見通し積算 (全SH全項目統合版）'!H26 -> #REF! | F84: 1 | G84: 1 | I84: =E84*F84*G84 -> #REF! | J84: ホテル （クリーンベニューテナント） | K84: ='財政見通し積算 (全SH全項目統合版）'!H31 -> #REF! | L84: 1 | M84: 1 | O84: =K84*L84*M84 -> #REF! | P84: =I84+O84 -> #REF!
B85: ※技術役員の昼食夕食については、参照できる単価がないためアスリートミールの単価（通常：16,900円 ハラル19,000円）を参照
B86: ※クリーンベニューの営業補償については、どこまでの範囲を行うのか、どのSHを行うのか不明のため、少なくとも選手村として運用するホテルの全てのテナントに対して行う想定で算出。
B87: ※自動販売機の補償については、1台5,000円の換算で、各施設2フロアにつき1台がある想定で仮置きし算出
B88: ※テナント営業補償について、レストランやコンビニ、ゴルフ場など補償額が高そうなものが多くあるため各施設1,800,000円/日にて計算（ヒルトンしか参照単価がないためこの金額を参考）
B89: ➡なお、500,000円/日だとしても1,200,000,000円程度になる計算。
B91: ACM内で連動する費用（宿泊管理支援業務） | C91: 予算金額 | P91: 合計 | Q91: 差し引き（項目ごと） | R91: 差し引き（項目ごと）
B92: 委託料 | C92: 1545729278 | I92: =ROUNDUP(SUM(I35,I36)*0.1,0) -> #REF! | O92: =ROUNDUP(SUM(O35,O36)*0.1,0) -> #REF! | P92: =ROUNDUP(SUM(P35,P36)*0.1,0) -> #REF! | Q92: =SUM(P92)-C92 -> #REF! | R92: =SUM(P92)-C92 -> #REF!
B93: ※うち歳入になる分 | C93: =SUM(I6,I8,I9)*0.1+SUM(O6,O8,O9)*0.1 -> 6.6748335e+08 | D93: 利用者負担分の10％ | I93: =ROUNDUP(SUM(I40,I41)*0.1,0) -> 394204099 | J93: 利用者負担分の10％ | O93: =ROUNDUP(SUM(O38,O40,O41)*0.1,0) -> 153383204 | P93: =SUM(I93,O93) -> 547587303 | Q93: =SUM(P93)-C93 -> -1.1989604e+08 | R93: =SUM(P93)-C93 -> -1.1989604e+08
B94: ※宿泊確保費のうち、客室確保費（朝食付）のアジア・パラ総額の10％の金額
B97: 増額要因（FNB積算分） | P97: 増減
B98: 飲食費（昼食及び夕食） | C98: 新選手団配宿 | D98: ホテル（選手団） | E98: 16900 | F98: 58451 | G98: 1 | I98: =E98*F98*G98 -> 987821900 | J98: ホテル（選手団） | K98: 16900 | L98: 31699 | M98: 1 | N98: =L98*M98 -> 31699 | O98: =K98*L98*M98 -> 535713100 | P98: =I98+O98-I99-O99 -> 428668500
C99: 旧選手団配宿 | D99: ホテル（選手団） | E99: 16900 | F99: =3546*11 -> 39006 | G99: 1 | H99: =F99*G99 -> 39006 | I99: =E99*F99*G99 -> 659201400 | J99: ホテル（選手団） | K99: 16900 | L99: =1983*13 -> 25779 | M99: 1 | N99: =L99*M99 -> 25779 | O99: =K99*L99*M99 -> 435665100
C100: 新選手団配宿 | D100: =D47 -> コンテナ（選手団・NOC）※3食 | E100: =E47 -> 21000 | F100: =F47 -> 22972 | G100: =G47 -> 1 | H100: =H47 -> 0 | I100: =I47 -> 482412000 | J100: =J47 -> コンテナ（選手団・NOC）※3食 | K100: =K47 -> 21000 | ... O100: =O47 -> 181440000 | P100: =I100+O100-I101-O101-O102 -> 319536000
C101: 旧選手団配宿 | D101: コンテナ | E101: 21000 | F101: =725*11 -> 7975 | G101: 1 | H101: 7975 | I101: 167475000 | J101: コンテナ（選手団） | K101: 21000 | L101: =417*13 -> 5421 | M101: 1 | N101: 5421 | O101: 113841000
J102: コンテナ（NOC本部） | K102: 21000 | L102: 3000 | M102: 1 | N102: =L102*M102 -> 3000 | O102: =K102*L102*M102 -> 63000000
B103: 飲食費（ハラル・ヴィーガン対応） | C103: 新選手団配宿 | D103: =D48 -> ホテル自前 | E103: =E48 -> 19000 | F103: =F48 -> 8364 | G103: =G48 -> 1 | H103: =H48 -> 0 | I103: =I48 -> 158916000 | J103: =J48 -> ホテル自前 | K103: =K48 -> 19000 | ... O103: =O48 -> 105184000 | P103: =I103+O103+I104+O104-I105-O105 -> -554724000
C104: 新選手団配宿 | D104: コンテナ | E104: 19000 | F104: 14409 | G104: 1 | I104: 273771000 | J104: コンテナ | K104: 19000 | L104: 5760 | M104: 1 | O104: 109440000
C105: 旧選手団配宿 | D105: ホテル | E105: 19000 | F105: =4189*11 -> 46079 | G105: 1 | H105: =F105*G105 -> 46079 | I105: =E105*F105*G105 -> 875501000 | J105: ホテル | K105: 19000 | L105: =1322*13 -> 17186 | M105: 1 | N105: =L105*M105 -> 17186 | O105: =K105*L105*M105 -> 326534000
C106: 新選手団配宿 | D106: =D50 -> 完調品対応 | E106: =E50 -> 22164 | F106: =F50 -> 30603 | G106: =G50 -> 1 | H106: =H50 -> 0 | I106: =I50 -> 678284892 | J106: =J50 -> 完調品対応 | K106: =K50 -> 22164 | ... O106: =O50 -> 345691908 | P106: =I106+O106-I107-O107 -> 871501800
...

Sheet 内示額反映積算（VIL移管反映）
A2: 24/10時点 | B2: 全体予算 | D2: アジア | H2: 一旦計算（非表示） | J2: パラ | N2: 一旦計算（非表示） | P2: 全体
B3: 予算項目 | C3: 予算金額（VIL移管分含む） | D3: 項目 | E3: 単価 | F3: 人数 | G3: 泊数 | I3: 小計 | J3: 項目 | K3: 単価 | L3: 人数 | M3: 泊数 | O3: 小計 | P3: 合計
B4: 客室確保費（朝食付） | C4: =SUM(P4,P5) -> 15457292778 | D4: ホテル（選手団） | E4: 3042691395 | F4: 1 | G4: 1 | I4: =E4*F4*G4 -> 3042691395 | J4: ホテル（選手団） | K4: 2596055904 | L4: 1 | M4: 1 | O4: =K4*L4*M4 -> 2596055904 | P4: =I4+O4 -> 5638747299
D5: ホテル（選手団以外） | E5: 7718814575 | F5: 1 | G5: 1 | I5: =E5*F5*G5 -> 7718814575 | J5: ホテル（選手団以外） | K5: 2099730904 | L5: 1 | M5: 1 | O5: =K5*L5*M5 -> 2099730904 | P5: =I5+O5 -> 9818545479
D6: （ファミリーAINAGOC負担） | E6: 2004704909 | F6: 1 | G6: 1 | I6: =E6*F6*G6 -> 2004704909 | J6: （ファミリーAINAGOC負担） | K6: 197828150 | L6: 1 | M6: 1 | O6: =K6*L6*M6 -> 197828150 | P6: =I6+O6 -> 2202533059
D7: （ファミリー利用者負担） | E7: 881565432 | F7: 1 | G7: 1 | I7: =E7*F7*G7 -> 881565432 | J7: （ファミリー利用者負担） | K7: 449927739 | L7: 1 | M7: 1 | O7: =K7*L7*M7 -> 449927739 | P7: =I7+O7 -> 1331493171
D8: （技術役員） | E8: 723774664 | F8: 1 | G8: 1 | I8: =E8*F8*G8 -> 723774664 | J8: （技術役員） | K8: 217404288 | L8: 1 | M8: 1 | O8: =K8*L8*M8 -> 217404288 | P8: =I8+O8 -> 941178952
D9: （スポンサー利用者負担） | E9: =SUM('財政見通し積算 (全SH全項目統合版）'!AD29) -> 2342187094 | F9: 1 | G9: 1 | I9: =E9*F9*G9 -> 2342187094 | J9: （スポンサー利用者負担） | K9: 783186617 | L9: 1 | M9: 1 | O9: =K9*L9*M9 -> 783186617 | P9: =I9+O9 -> 3125373711
D10: （メディア利用者負担） | E10: =SUM('財政見通し積算 (全SH全項目統合版）'!AD30) -> 1766582476 | F10: 1 | G10: 1 | I10: =E10*F10*G10 -> 1766582476 | J10: （メディア利用者負担） | K10: =SUM('財政見通し積算 (全SH全項目統合版）'!AD35) -> 451384110 | L10: 1 | M10: 1 | O10: =K10*L10*M10 -> 451384110 | P10: =I10+O10 -> 2217966586
B11: 飲食費（昼食及び夕食） | C11: =SUM(P11:P12) -> 1660274332 | D11: ホテル（選手団） | E11: 16900 | F11: 3546 | G11: 11 | H11: =F11*G11 -> 39006 | I11: =E11*F11*G11 -> 659201400 | J11: ホテル（選手団） | K11: 16900 | L11: =3305*0.6 -> 1983 | M11: 13 | N11: =L11*M11 -> 25779 | O11: =K11*L11*M11 -> 435665100 | P11: =I11+O11 -> 1094866500
D12: ホテル（選手団以外） | E12: =SUM(E13:E14) -> 487471732 | F12: 1 | G12: 1 | I12: =E12*F12*G12 -> 487471732 | J12: ホテル（選手団以外） | K12: =SUM(K13:K14) -> 77936100 | L12: 1 | M12: 1 | O12: =K12*L12*M12 -> 77936100 | P12: =I12+O12 -> 565407832
D13: （ファミリーAINAGOC負担） | E13: 324285720 | F13: 1 | G13: 1 | I13: =E13*F13*G13 -> 324285720 | J13: （ファミリーAINAGOC負担） | K13: 23802106 | L13: 1 | M13: 1 | O13: =K13*L13*M13 -> 23802106 | P13: =I13+O13 -> 348087826
D14: （ファミリー利用者負担） | E14: 163186012 | F14: 1 | G14: 1 | I14: =E14*F14*G14 -> 163186012 | J14: （ファミリー利用者負担） | K14: 54133994 | L14: 1 | M14: 1 | O14: =K14*L14*M14 -> 54133994 | P14: =I14+O14 -> 217320006
D15: コンテナ | E15: 21000 | F15: 725 | G15: 11 | H15: =F15*G15 -> 7975 | I15: 167496000 | J15: コンテナ（選手団） | K15: 21000 | L15: =695*0.6 -> 417 | M15: 13 | N15: =L15*M15 -> 5421 | O15: =K15*L15*M15 -> 113841000 | P15: =I15+O15 -> 281337000
I16: =E16*F16*G16 -> 0 | J16: コンテナ（NOC本部） | K16: 21000 | L16: 200 | M16: 15 | N16: =L16*M16 -> 3000 | O16: =K16*L16*M16 -> 63000000 | P16: =I16+O16 -> 63000000
B17: 飲食費（ハラル・ヴィーガン対応） | C17: =SUM(P17) -> 1202035000 | D17: ホテル | E17: 19000 | F17: 4189 | G17: 11 | H17: =F17*G17 -> 46079 | I17: =E17*F17*G17 -> 875501000 | J17: ホテル | K17: 19000 | L17: =3305*0.4 -> 1322 | M17: 13 | N17: =L17*M17 -> 17186 | O17: =K17*L17*M17 -> 326534000 | P17: =I17+O17 -> 1202035000
D18: コンテナ | E18: 19000 | F18: 401 | G18: 11 | H18: =F18*G18 -> 4411 | I18: =E18*F18*G18 -> 83809000 | J18: コンテナ | K18: 19000 | L18: =695*0.4 -> 278 | M18: 13 | N18: =L18*M18 -> 3614 | O18: =K18*L18*M18 -> 68666000 | P18: =I18+O18 -> 152475000
B19: 飲食費（グラブアンドゴー） | C19: =SUM(P19) -> 127204000 | D19: ホテル | E19: 880 | F19: 9235 | G19: 11 | H19: =F19*G19 -> 101585 | I19: =E19*F19*G19 -> 89394800 | J19: ホテル | K19: 880 | L19: 3305 | M19: 13 | N19: =L19*M19 -> 42965 | O19: =K19*L19*M19 -> 37809200 | P19: =I19+O19 -> 127204000
D20: コンテナ | E20: 880 | F20: 1002 | G20: 11 | H20: =F20*G20 -> 11022 | I20: =E20*F20*G20 -> 9699360 | J20: コンテナ | K20: 880 | L20: 695 | M20: 13 | N20: =L20*M20 -> 9035 | O20: =K20*L20*M20 -> 7950800 | P20: =I20+O20 -> 17650160
D21: 船 | E21: 880 | F21: 2436 | G21: 18 | H21: =F21*G21 -> 43848 | I21: =E21*F21*G21 -> 38586240 | O21: =K21*L21*M21 -> 0 | P21: =I21+O21 -> 38586240
B22: 飲食費（アスリートミール：船） | C22: 920808000 | D22: 船 | E22: 21000 | F22: 2436 | G22: 18 | H22: =F22*G22 -> 43848 | I22: =E22*F22*G22 -> 920808000 | O22: =K22*L22*M22 -> 0 | P22: =I22+O22 -> 920808000
B23: 飲食費（空港島運営及びガーデンふ頭運営及び仮設厨房） | C23: =SUM(P23:P24) -> 1437358140 | D23: 空港島運営経費 | E23: 1336000000 | F23: 1 | G23: 1 | I23: =E23*F23*G23 -> 1336000000 | P23: =I23+O23 -> 1336000000
B24: 内容については別紙参照 | D24: 空港島仮設厨房経費 | E24: 101358140 | F24: 1 | G24: 1 | I24: =E24*F24*G24 -> 101358140 | O24: =K24*L24*M24 -> 0 | P24: =I24+O24 -> 101358140
D25: ガーデン運営経費 | E25: 408277000 | F25: 1 | G25: 1 | I25: =E25*F25*G25 -> 408277000 | J25: ガーデン運営経費 | K25: 360000000 | L25: 1 | M25: 1 | O25: =K25*L25*M25 -> 360000000 | P25: =I25+O25 -> 768277000
D26: ガーデン仮設厨房経費 | E26: 205723000 | F26: 1 | G26: 1 | I26: =E26*F26*G26 -> 205723000 | O26: =K26*L26*M26 -> 0 | P26: =I26+O26 -> 205723000
B27: 飲食費（その他経費（支援機器設置等）） | C27: =SUM(P27) -> 88652020 | D27: ホテル | E27: 6000000 | F27: 12 | G27: 1 | I27: =E27*F27*G27 -> 72000000 | J27: ホテル | K27: 2378860 | L27: 7 | M27: 1 | O27: =K27*L27*M27 -> 16652020 | P27: =I27+O27 -> 88652020
B28: 会議室等確保費 | C28: =SUM(P28:P29) -> 3450377147 | D28: ホテル（選手団） | E28: 858587762 | F28: 1 | G28: 1 | I28: =E28*F28*G28 -> 858587762 | J28: ホテル（選手団） | K28: 1030634912 | L28: 1 | M28: 1 | O28: =K28*L28*M28 -> 1030634912 | P28: =I28+O28 -> 1889222674
D29: ホテル（選手団以外）（ファミリー） | E29: 1178445153 | F29: 1 | G29: 1 | I29: =E29*F29*G29 -> 1178445153 | J29: ホテル（選手団以外）（ファミリー） | K29: 382709320 | L29: 1 | M29: 1 | O29: =K29*L29*M29 -> 382709320 | P29: =I29+O29 -> 1561154473
B30: 営業補償費 | C30: =SUM(P30) -> 54466667 | D30: ホテル（選手団以外）（ファミリー） | E30: 34400000 | F30: 1 | G30: 1 | I30: =E30*F30*G30 -> 34400000 | J30: ホテル（選手団以外）（ファミリー） | K30: 20066667 | L30: 1 | M30: 1 | O30: =K30*L30*M30 -> 20066667 | P30: =I30+O30 -> 54466667
B31: 合計 | C31: =SUM(C4,C11,C17,C19,C23,C27,C28,C30) -> 23477660084 | I31: =SUM(I4:I5,I11:I12,I17,I19,I23:I24,I27,I28:I29,I30) -> 16453865957 | O31: =SUM(O4:O5,O11:O12,O17,O19,O27,O28:O29,O30) -> 7023794127 | P31: =SUM(P4:P5,P11:Q12,P17,P19,P23:P24,P27,P28:P29,P30) -> 23477660084
A34: 25/6時点 | B34: 全体額 | D34: アジア | J34: パラ | P34: 全体
B35: 予算項目 | C35: 予算金額（VIL移管分含む） | D35: 項目 | E35: 単価 | F35: 人数 | G35: 泊数 | I35: 小計 | J35: 項目 | K35: 単価 | L35: 人数 | M35: 泊数 | O35: 小計 | P35: 合計 | Q35: 差し引き（項目ごと） | R35: 差し引き（項目ごと）
B36: 客室確保費（朝食付） | C36: =C4 -> 15457292778 | D36: ホテル（選手団） | E36: 3364680671 | F36: 1 | G36: 1 | I36: =E36*F36*G36 -> 3364680671 | J36: ホテル（選手団） | K36: 2615539538 | L36: 1 | M36: 1 | O36: =K36*L36*M36 -> 2615539538 | P36: =I36+O36 -> 5980220209 | Q36: =SUM(P36:P37)-C36 -> 7.7311319e+08 | R36: =SUM(P36:P37)-C36 -> 7.7311319e+08
D37: ホテル（選手団以外） | I37: =SUM(I38:I42) -> 7.8714323e+09 | J37: ホテル（選手団以外） | O37: =SUM(O38:O42) -> 2.3787535e+09 | P37: =SUM(P38:P42) -> 1.0250186e+10
D38: （ファミリーAINAGOC負担） | E38: 2334813782 | F38: 1 | G38: 1 | I38: =E38*F38*G38 -> 2334813782 | J38: （ファミリーAINAGOC負担） | K38: 237817800 | L38: 1 | M38: 1 | O38: =K38*L38*M38 -> 237817800 | P38: =I38+O38 -> 2572631582
J39: （ファミリー利用者負担） | K39: 234300000 | L39: 1 | M39: 1 | O39: =K39*L39*M39 -> 234300000 | P39: =I39+O39 -> 234300000
D40: （技術役員） | E40: 1.7067982e+09 | F40: 1 | G40: 1 | I40: =E40*F40*G40 -> 1.7067982e+09 | J40: （技術役員） | K40: 412159612 | L40: 1 | M40: 1 | O40: =K40*L40*M40 -> 412159612 | P40: =I40+O40 -> 2.1189579e+09
D41: （スポンサー利用者負担） | E41: 1.4860979e+09 | F41: 1 | G41: 1 | I41: =E41*F41*G41 -> 1.4860979e+09 | J41: （スポンサー利用者負担） | K41: 7.99788e+08 | L41: 1 | M41: 1 | O41: =K41*L41*M41 -> 7.99788e+08 | P41: =I41+O41 -> 2.2858859e+09
D42: （メディア利用者負担） | E42: 2.3437223e+09 | F42: 1 | G42: 1 | I42: =E42*F42*G42 -> 2.3437223e+09 | J42: （メディア利用者負担） | K42: 6.9468807e+08 | L42: 1 | M42: 1 | O42: =K42*L42*M42 -> 6.9468807e+08 | P42: =I42+O42 -> 3.0384104e+09
B43: 飲食費（昼食及び夕食） | C43: =C11 -> 1660274332 | D43: ホテル（選手団）昼食及び夕食 | E43: 16900 | F43: 58451 | G43: 1 | I43: =E43*F43*G43 -> 987821900 | J43: ホテル（選手団）昼食及び夕食 | K43: 16900 | L43: 31699 | M43: 1 | N43: =L43*M43 -> 31699 | O43: =K43*L43*M43 -> 535713100 | P43: =I43+O43 -> 1523535000 | Q43: =SUM(P43:P49)-C43 -> 3552291218 | R43: =SUM(P43:P45)-C43 -> 1430946248
D44: ホテル（選手団）ｱｽﾘｰﾄﾐｰﾙ差額 | E44: 79313574 | F44: 1 | G44: 1 | I44: =E44*F44*G44 -> 79313574 | J44: ホテル（選手団）ｱｽﾘｰﾄﾐｰﾙ差額 | K44: 30879036 | L44: 1 | M44: 1 | O44: =K44*L44*M44 -> 30879036 | P44: =SUM(I44,O44) -> 110192610
D45: ホテル（選手団以外） | I45: =SUM(I46,I48) -> 1181442570 | J45: ホテル（選手団以外） | O45: =SUM(O46:O48) -> 276050400 | P45: =SUM(P46:P48) -> 1457492970
D46: （ファミリーAINAGOC負担） | E46: 4.4624657e+08 | F46: 1 | G46: 1 | I46: =E46*F46*G46 -> 4.4624657e+08 | J46: （ファミリーAINAGOC負担） | K46: 12202608 | L46: 1 | M46: 1 | O46: =K46*L46*M46 -> 12202608 | P46: =I46+O46 -> 4.5844918e+08
J47: （ファミリー利用者負担） | K47: 60203792 | L47: 1 | M47: 1 | O47: =K47*L47*M47 -> 60203792 | P47: =I47+O47 -> 60203792
D48: （技術役員） | E48: 735196000 | F48: 1 | G48: 1 | I48: =E48*F48*G48 -> 735196000 | J48: （技術役員） | K48: 203644000 | L48: 1 | M48: 1 | O48: =K48*L48*M48 -> 203644000 | P48: =I48+O48 -> 938840000
D49: コンテナ（選手団・NOC）※3食 | E49: 21000 | F49: 22972 | G49: 1 | I49: =E49*F49*G49 -> 482412000 | J49: コンテナ（選手団・NOC）※3食 | K49: 21000 | L49: 8640 | M49: 1 | N49: =L49*M49 -> 8640 | O49: =K49*L49*M49 -> 181440000 | P49: =I49+O49 -> 663852000
B50: 飲食費（ハラル・ヴィーガン対応） | C50: =C17 -> 1202035000 | D50: ホテル自前 | E50: 19000 | F50: 8364 | G50: 1 | I50: =E50*F50*G50 -> 158916000 | J50: ホテル自前 | K50: 19000 | L50: 5536 | M50: 1 | N50: =L50*M50 -> 5536 | O50: =K50*L50*M50 -> 105184000 | P50: =I50+O50 -> 264100000 | Q50: =SUM(P50:P52)-C50 -> 469252800 | R50: =SUM(P50,P52)-C50 -> 86041800
D51: コンテナ | E51: 19000 | F51: 14409 | G51: 1 | I51: =E51*F51*G51 -> 273771000 | J51: コンテナ | K51: 19000 | L51: 5760 | M51: 1 | O51: =K51*L51*M51 -> 109440000 | P51: =I51+O51 -> 383211000
D52: 完調品対応 | E52: 22164 | F52: 30603 | G52: 1 | I52: =E52*F52*G52 -> 678284892 | J52: 完調品対応 | K52: 22164 | L52: 15597 | M52: 1 | N52: =L52*M52 -> 15597 | O52: =K52*L52*M52 -> 345691908 | P52: =I52+O52 -> 1023976800
B53: 飲食費（グラブアンドゴー） | C53: =C19 -> 127204000 | D53: ホテル | E53: 880 | F53: 97418 | G53: 1 | I53: =E53*F53*G53 -> 85727840 | J53: ホテル | K53: 880 | L53: 52832 | M53: 1 | N53: =L53*M53 -> 52832 | O53: =K53*L53*M53 -> 46492160 | P53: =I53+O53 -> 132220000 | Q53: =SUM(P53:P55)-C53 -> 96855440 | R53: =SUM(P53)-C53 -> 5016000
D54: コンテナ | E54: 880 | F54: 37381 | G54: 1 | I54: =E54*F54*G54 -> 32895280 | J54: コンテナ | K54: 880 | L54: 14400 | M54: 1 | N54: =L54*M54 -> 14400 | O54: =K54*L54*M54 -> 12672000 | P54: =I54+O54 -> 45567280
D55: 船 | E55: 880 | F55: 52582 | G55: 1 | I55: =E55*F55*G55 -> 46272160 | O55: =K55*L55*M55 -> 0 | P55: =I55+O55 -> 46272160
B56: 飲食費（アスリートミール：船） | C56: 920808000 | D56: 船 | E56: 21000 | F56: 52582 | G56: 1 | I56: =E56*F56*G56 -> 1104222000 | O56: =K56*L56*M56 -> 0 | P56: =I56+O56 -> 1104222000 | Q56: =SUM(P56)-C56 -> 183414000
B57: 飲食費（空港島運営及びガーデンふ頭運営及び仮設厨房） | C57: =C23 -> 1437358140 | D57: 空港島運営経費 | E57: 1336000000 | F57: 1 | G57: 1 | I57: =E57*F57*G57 -> 1336000000 | P57: =I57+O57 -> 1336000000 | Q57: =SUM(P57:P60)-C57 -> 974000860 | R57: =SUM(P57:P58)-C57 -> 860
D58: 空港島仮設厨房経費 | E58: 101359000 | F58: 1 | G58: 1 | I58: =E58*F58*G58 -> 101359000 | O58: =K58*L58*M58 -> 0 | P58: =I58+O58 -> 101359000
D59: ガーデン運営経費 | E59: 408277000 | F59: 1 | G59: 1 | I59: =E59*F59*G59 -> 408277000 | J59: ガーデン運営経費 | K59: 360000000 | L59: 1 | M59: 1 | O59: =K59*L59*M59 -> 360000000 | P59: =I59+O59 -> 768277000
D60: ガーデン仮設厨房経費 | E60: 205723000 | F60: 1 | G60: 1 | I60: =E60*F60*G60 -> 205723000 | O60: =K60*L60*M60 -> 0 | P60: =I60+O60 -> 205723000
B61: 飲食費（その他経費（支援機器設置等）） | C61: =C27 -> 88652020 | D61: ホテル厨房機器レンタル | E61: 6000000 | F61: 12 | G61: 1 | I61: =E61*F61*G61 -> 72000000 | J61: ホテル厨房機器レンタル | K61: 2379000 | L61: 7 | M61: 1 | O61: =K61*L61*M61 -> 16653000 | P61: =I61+O61 -> 88653000 | Q61: =SUM(P61:P62,P63)-C61 -> 10458980 | R61: =SUM(P61)-C61 -> 980
D62: シップグラブ＆ゴー設備レンタル | E62: 9351000 | F62: 1 | G62: 1 | I62: =E62*F62*G62 -> 9351000 | P62: =I62+O62 -> 9351000
D63: シップグラブ＆ゴー備品レンタル | E63: 1107000 | F63: 1 | G63: 1 | I63: =E63*F63*G63 -> 1107000 | P63: =I63+O63 -> 1107000
B64: 会議室等確保費 | C64: =C28 -> 3450377147 | D64: ホテル（選手団） | E64: 1.618789e+09 | F64: 1 | G64: 1 | I64: =E64*F64*G64 -> 1.618789e+09 | J64: ホテル（選手団） | K64: 1.0971813e+09 | L64: 1 | M64: 1 | O64: =K64*L64*M64 -> 1.0971813e+09 | P64: =I64+O64 -> 2.7159704e+09 | Q64: =SUM(P64:P65)-C64 -> 2.072415e+09 | R64: =SUM(P64:P65)-C64 -> 2.072415e+09
D65: ホテル（選手団以外） | I65: =SUM(I66:I67) -> 1.9880305e+09 | J65: ホテル（選手団以外） | O65: =SUM(O66:O67) -> 8.187913e+08 | P65: =SUM(P66:P67) -> 2.8068218e+09
D66: （ファミリー） | E66: 1.1408776e+09 | F66: 1 | G66: 1 | I66: =E66*F66*G66 -> 1.1408776e+09 | J66: （ファミリー） | K66: 2.886576e+08 | L66: 1 | M66: 1 | O66: =K66*L66*M66 -> 2.886576e+08 | P66: =I66+O66 -> 1.4295352e+09
D67: （技術役員） | E67: 8.4715285e+08 | F67: 1 | G67: 1 | I67: =E67*F67*G67 -> 8.4715285e+08 | J67: （技術役員） | K67: 5.301337e+08 | L67: 1 | M67: 1 | O67: =K67*L67*M67 -> 5.301337e+08 | P67: =I67+O67 -> 1.3772865e+09
B68: 営業補償費 | C68: =C30 -> 54466667 | D68: ホテル（一棟貸しによる補償） | I68: =SUM(I69:I70) -> 1.1773603e+08 | J68: ホテル（一棟貸しによる補償） | O68: =SUM(O69:O70) -> 91897355 | P68: =I68+O68 -> 2.0963338e+08 | Q68: =SUM(P68)-C68 -> 1.5516671e+08 | R68: =SUM(P68,P71)-C68 -> 4.5893617e+09
D69: （選手団） | E69: 71660120 | F69: 1 | G69: 1 | I69: =E69*F69*G69 -> 71660120 | J69: （選手団） | K69: 91105355 | L69: 1 | M69: 1 | O69: =K69*L69*M69 -> 91105355 | P69: =I69+O69 -> 1.6276548e+08
D70: （ファミリー） | E70: 46075905 | F70: 1 | G70: 1 | I70: =E70*F70*G70 -> 46075905 | J70: （ファミリー） | K70: 792000 | L70: 1 | M70: 1 | O70: =K70*L70*M70 -> 792000 | P70: =I70+O70 -> 46867905
D71: ホテル（クリーンベニューによる補償） | I71: =SUM(I72:I73) -> 2707445000 | J71: ホテル（クリーンベニューによる補償） | O71: =SUM(O72:O73) -> 1726750000 | P71: =I71+O71 -> 4434195000
D72: （選手団※自動販売機補償） | E72: 10045000 | F72: 1 | G72: 1 | I72: =E72*F72*G72 -> 10045000 | J72: （選手団※自動販売機補償） | K72: 6750000 | L72: 1 | M72: 1 | O72: =K72*L72*M72 -> 6750000 | P72: =I72+O72 -> 16795000
D73: （選手団※テナント等補償） | E73: 2697400000 | F73: 1 | G73: 1 | I73: =E73*F73*G73 -> 2697400000 | J73: （選手団※テナント等補償） | K73: 1720000000 | L73: 1 | M73: 1 | O73: =K73*L73*M73 -> 1720000000 | P73: =I73+O73 -> 4417400000
B74: ランドリーサービス費 | C74: 0 | D74: ランドリーサービス費（選手団以外） | E74: 136866942 | F74: 1 | G74: 1 | I74: =E74*F74*G74 -> 136866942 | J74: ランドリーサービス費（選手団以外） | K74: 23176780 | L74: 1 | M74: 1 | O74: =K74*L74*M74 -> 23176780 | P74: =SUM(I74,O74) -> 160043722 | R74: =SUM(P74)-C74 -> 160043722
B75: 合計 | C75: =SUM(C36,C43,C50,C53,C57,C61,C64,C68,C74) -> 23477660084 | I75: =SUM(I36:I37,I43:I45,I50,I52,I53,I57:I58,I61,I64:I65,I68,I71,I74) -> 2.2485846e+10 | O75: =SUM(O36:O37,O43:O45,O50,O52,O53,O61,O64:O65,O68,O71,O74) -> 1.0108753e+10 | P75: =SUM(P36,P37,P43,P44,P45,P50,P52,P53,P57,P58,P61,P64,P65,P68,P71,P74) -> 3.25946e+10 | Q75: =P75-C75 -> 9.1169395e+09 | R75: =SUM(R36:R74) -> 9.1169395e+09
B76: ※技術役員・スポンサー・メディアのホテルについては、積算単価が2021年時点のものであるため、客室単価に1.34（宿泊料物価上昇率）を掛けている | P76: ↑要求額 ※32,594,602千円 | Q76: 全体差し引き
B77: ※技術役員の会議室費用については1.1（総合物価上昇率）を掛けている | G77: アジア差し引き | I77: =I75-I31 -> 6.0319802e+09 | M77: パラ差し引き | O77: =O75-O31 -> 3.0849593e+09
B78: ※技術役員の昼食夕食について、延べ人数の3割に5,000円の昼食提供、10割に10,000円の夕食提供、5割に1,500円の夜食提供という前提で算出。
B79: ※クリーンベニューの営業補償については、どこまでの範囲を行うのか、どのSHを行うのか不明のため、少なくとも選手村として運用するホテルの全てのテナントに対して行う想定で算出。
B80: ※自動販売機の補償については、1台5,000円の換算で、各施設2フロアにつき1台がある想定で仮置きし算出
B81: ※テナント営業補償について、レストランやコンビニ、ゴルフ場など補償額が高そうなものが多くあるため各施設1,800,000円/日にて計算（ヒルトンしか参照単価がないためこの金額を参考）
B82: ➡なお、500,000円/日だとしても1,200,000,000円程度になる計算。
B83: ※ファミリーのランドリーサービス費については、昨年度要求時、財政見通し時にアジア86,508千円、パラ22,496千円にて積算するも予算要求資料には記載せず。ただし来年度の支払で必要になるため今回の予算要求時には積算
A86: 26/01内示額 | B86: 全体額 | D86: アジア | J86: パラ | P86: 全体
B87: 予算項目 | C87: 内示金額（7/31枠要求） | D87: 項目 | E87: 単価 | F87: 人数 | G87: 泊数 | I87: 小計 | J87: 項目 | K87: 単価 | L87: 人数 | M87: 泊数 | O87: 小計 | P87: 合計 | Q87: 差し引き（項目ごと） | R87: 差し引き（項目ごと）
B88: 客室確保費（朝食付） | C88: =SUM(P36,P37) -> 1.6230406e+10 | D88: ホテル（選手団） | E88: ='財政見通し積算 (全SH全項目統合版）'!C26 -> #REF! | F88: 1 | G88: 1 | I88: =E88*F88*G88 -> #REF! | J88: ホテル（選手団） | K88: ='財政見通し積算 (全SH全項目統合版）'!C31 -> #REF! | L88: 1 | M88: 1 | O88: =K88*L88*M88 -> #REF! | P88: =I88+O88 -> #REF! | Q88: =SUM(P88:P89)-C88 -> #REF! | R88: =SUM(P88:P89)-C88 -> #REF!
D89: ホテル（選手団以外） | I89: =SUM(I90:I94) -> 7.8708056e+09 | J89: ホテル（選手団以外） | O89: =SUM(O90:O94) -> 2.0563535e+09 | P89: =SUM(P90:P94) -> 9.9271591e+09
D90: （ファミリーAINAGOC負担） | E90: ='財政見通し積算 (全SH全項目統合版）'!C27 -> 2204156998 | F90: 1 | G90: 1 | I90: =E90*F90*G90 -> 2204156998 | J90: （ファミリーAINAGOC負担） | K90: ='財政見通し積算 (全SH全項目統合版）'!C32-K39 -> 237817800 | L90: 1 | M90: 1 | O90: =K90*L90*M90 -> 237817800 | P90: =I90+O90 -> 2441974798
J91: （ファミリー利用者負担） | K91: =【250925】アジパラファミリー積算!BS29 -> 234300000 | L91: 1 | M91: 1 | O91: =K91*L91*M91 -> 234300000 | P91: =I91+O91 -> 234300000
D92: （技術役員） | E92: ='財政見通し積算 (全SH全項目統合版）'!C28 -> 1724607631 | F92: 1 | G92: 1 | I92: =E92*F92*G92 -> 1724607631 | J92: （技術役員） | K92: ='財政見通し積算 (全SH全項目統合版）'!C33 -> 344907436 | L92: 1 | M92: 1 | O92: =K92*L92*M92 -> 344907436 | P92: =I92+O92 -> 2069515067
D93: （スポンサー利用者負担） | E93: ='財政見通し積算 (全SH全項目統合版）'!C29 -> 1.2854877e+09 | F93: 1 | G93: 1 | I93: =E93*F93*G93 -> 1.2854877e+09 | J93: （スポンサー利用者負担） | K93: ='財政見通し積算 (全SH全項目統合版）'!C34 -> 8.3703864e+08 | L93: 1 | M93: 1 | O93: =K93*L93*M93 -> 8.3703864e+08 | P93: =I93+O93 -> 2.1225263e+09
D94: （メディア利用者負担） | E94: ='財政見通し積算 (全SH全項目統合版）'!C30 -> 2656553304 | F94: 1 | G94: 1 | I94: =E94*F94*G94 -> 2656553304 | J94: （メディア利用者負担） | K94: ='財政見通し積算 (全SH全項目統合版）'!C35 -> 4.022896e+08 | L94: 1 | M94: 1 | O94: =K94*L94*M94 -> 4.022896e+08 | P94: =I94+O94 -> 3.0588429e+09
B95: 飲食費（昼食及び夕食） | C95: =SUM(P43,P44,P45) -> 3091220580 | D95: ホテル（選手団）昼食及び夕食 | E95: 22104 | F95: 58549 | G95: 1 | I95: =E95*F95*G95 -> 1294167096 | J95: ホテル（選手団）昼食及び夕食 | K95: 22104 | L95: 32390 | M95: 1 | N95: =L95*M95 -> 32390 | O95: =K95*L95*M95 -> 715948560 | P95: =I95+O95 -> 2010115656 | Q95: =SUM(P95:P100)-C95 -> #REF! | R95: =SUM(P95:P97)-C95 -> #REF!
B96: ※飲食費（通常食対応） | D96: ホテル（選手団）ｱｽﾘｰﾄﾐｰﾙ差額 | E96: ='財政見通し積算 (全SH全項目統合版）'!E26 -> #REF! | F96: 1 | G96: 1 | I96: =E96*F96*G96 -> #REF! | J96: ホテル（選手団）ｱｽﾘｰﾄﾐｰﾙ差額 | K96: ='財政見通し積算 (全SH全項目統合版）'!E31 -> #REF! | L96: 1 | M96: 1 | O96: =K96*L96*M96 -> #REF! | P96: =SUM(I96,O96) -> #REF!
D97: ホテル（選手団以外） | I97: =SUM(I98,I100) -> 1179968416 | J97: ホテル（選手団以外） | O97: =SUM(O98:O100) -> 267855150 | P97: =SUM(P98:P100) -> 1447823566
D98: （ファミリーAINAGOC負担） | E98: ='財政見通し積算 (全SH全項目統合版）'!E27 -> 453261666 | F98: 1 | G98: 1 | I98: =E98*F98*G98 -> 453261666 | J98: （ファミリーAINAGOC負担） | K98: ='財政見通し積算 (全SH全項目統合版）'!E32-K47 -> 12202608 | L98: 1 | M98: 1 | O98: =K98*L98*M98 -> 12202608 | P98: =I98+O98 -> 465464274
J99: （ファミリー利用者負担） | K99: =【250925】アジパラファミリー積算!BV29 -> 60203792 | L99: 1 | M99: 1 | O99: =K99*L99*M99 -> 60203792 | P99: =I99+O99 -> 60203792
D100: （技術役員） | E100: ='財政見通し積算 (全SH全項目統合版）'!E28 -> 726706750 | F100: 1 | G100: 1 | I100: =E100*F100*G100 -> 726706750 | J100: （技術役員） | K100: ='財政見通し積算 (全SH全項目統合版）'!E33 -> 195448750 | L100: 1 | M100: 1 | O100: =K100*L100*M100 -> 195448750 | P100: =I100+O100 -> 922155500
B101: 飲食費（ハラル・ヴィーガン対応） | C101: =SUM(P50,P52) -> 1288076800 | D101: ホテル自前 | E101: 22104 | F101: 8589 | G101: 1 | I101: =E101*F101*G101 -> 189851256 | J101: ホテル自前 | K101: 22104 | L101: 5101 | M101: 1 | N101: =L101*M101 -> 5101 | O101: =K101*L101*M101 -> 112752504 | P101: =I101+O101 -> 302603760 | Q101: =SUM(P101:P102)-C101 -> 1021314212 | R101: =SUM(P101,P102)-C101 -> 1021314212
D102: 完調品対応 | I102: =SUM(I103:I104) -> 1301645530 | J102: 完調品対応 | N102: =L102*M102 -> 0 | O102: =SUM(O103:O104) -> 705141722 | P102: =I102+O102 -> 2006787252
D103: （完調品調達費用） | E103: 22164 | F103: 30445 | G103: 1 | I103: =E103*F103*G103 -> 674782980 | J103: （完調品調達費用） | K103: 22164 | L103: 16493 | M103: 1 | N103: =L103*M103 -> 16493 | O103: =K103*L103*M103 -> 365550852 | P103: =I103+O103 -> 1040333832
D104: （ホテル経費） | E104: 20590 | F104: 30445 | G104: 1 | I104: =E104*F104*G104 -> 626862550 | J104: （ホテル経費） | K104: 20590 | L104: 16493 | M104: 1 | O104: =K104*L104*M104 -> 339590870 | P104: =I104+O104 -> 966453420
B105: 飲食費（グラブアンドゴー） | C105: =SUM(P53) -> 132220000 | D105: ホテル | E105: 880 | F105: 97583 | G105: 1 | I105: =E105*F105*G105 -> 85873040 | J105: ホテル | K105: 880 | L105: 53984 | M105: 1 | N105: =L105*M105 -> 53984 | O105: =K105*L105*M105 -> 47505920 | P105: =I105+O105 -> 133378960 | Q105: =SUM(P105:P105)-C105 -> 1158960 | R105: =SUM(P105)-C105 -> 1158960
...

Sheet 新予算管理比較積算（VIL移管反映）
A2: 24/10時点 | B2: 全体予算 | D2: アジア | H2: 一旦計算（非表示） | J2: パラ | N2: 一旦計算（非表示） | P2: 全体
B3: 予算項目 | C3: 予算金額（VIL移管分含む） | D3: 項目 | E3: 単価 | F3: 人数 | G3: 泊数 | I3: 小計 | J3: 項目 | K3: 単価 | L3: 人数 | M3: 泊数 | O3: 小計 | P3: 合計
B4: 客室確保費（朝食付） | C4: =SUM(P4,P5) -> 15457292778 | D4: ホテル（選手団） | E4: 3042691395 | F4: 1 | G4: 1 | I4: =E4*F4*G4 -> 3042691395 | J4: ホテル（選手団） | K4: 2596055904 | L4: 1 | M4: 1 | O4: =K4*L4*M4 -> 2596055904 | P4: =I4+O4 -> 5638747299
D5: ホテル（選手団以外） | E5: 7718814575 | F5: 1 | G5: 1 | I5: =E5*F5*G5 -> 7718814575 | J5: ホテル（選手団以外） | K5: 2099730904 | L5: 1 | M5: 1 | O5: =K5*L5*M5 -> 2099730904 | P5: =I5+O5 -> 9818545479
D6: （ファミリーAINAGOC負担） | E6: 2004704909 | F6: 1 | G6: 1 | I6: =E6*F6*G6 -> 2004704909 | J6: （ファミリーAINAGOC負担） | K6: 197828150 | L6: 1 | M6: 1 | O6: =K6*L6*M6 -> 197828150 | P6: =I6+O6 -> 2202533059
D7: （ファミリー利用者負担） | E7: 881565432 | F7: 1 | G7: 1 | I7: =E7*F7*G7 -> 881565432 | J7: （ファミリー利用者負担） | K7: 449927739 | L7: 1 | M7: 1 | O7: =K7*L7*M7 -> 449927739 | P7: =I7+O7 -> 1331493171
D8: （技術役員） | E8: 723774664 | F8: 1 | G8: 1 | I8: =E8*F8*G8 -> 723774664 | J8: （技術役員） | K8: 217404288 | L8: 1 | M8: 1 | O8: =K8*L8*M8 -> 217404288 | P8: =I8+O8 -> 941178952
D9: （スポンサー利用者負担） | E9: =SUM('財政見通し積算 (全SH全項目統合版）'!AD29) -> 2342187094 | F9: 1 | G9: 1 | I9: =E9*F9*G9 -> 2342187094 | J9: （スポンサー利用者負担） | K9: 783186617 | L9: 1 | M9: 1 | O9: =K9*L9*M9 -> 783186617 | P9: =I9+O9 -> 3125373711
D10: （メディア利用者負担） | E10: =SUM('財政見通し積算 (全SH全項目統合版）'!AD30) -> 1766582476 | F10: 1 | G10: 1 | I10: =E10*F10*G10 -> 1766582476 | J10: （メディア利用者負担） | K10: =SUM('財政見通し積算 (全SH全項目統合版）'!AD35) -> 451384110 | L10: 1 | M10: 1 | O10: =K10*L10*M10 -> 451384110 | P10: =I10+O10 -> 2217966586
B11: 飲食費（昼食及び夕食） | C11: =SUM(P11:P12) -> 1660274332 | D11: ホテル（選手団） | E11: 16900 | F11: 3546 | G11: 11 | H11: =F11*G11 -> 39006 | I11: =E11*F11*G11 -> 659201400 | J11: ホテル（選手団） | K11: 16900 | L11: =3305*0.6 -> 1983 | M11: 13 | N11: =L11*M11 -> 25779 | O11: =K11*L11*M11 -> 435665100 | P11: =I11+O11 -> 1094866500
D12: ホテル（選手団以外） | E12: =SUM(E13:E14) -> 487471732 | F12: 1 | G12: 1 | I12: =E12*F12*G12 -> 487471732 | J12: ホテル（選手団以外） | K12: =SUM(K13:K14) -> 77936100 | L12: 1 | M12: 1 | O12: =K12*L12*M12 -> 77936100 | P12: =I12+O12 -> 565407832
D13: （ファミリーAINAGOC負担） | E13: 324285720 | F13: 1 | G13: 1 | I13: =E13*F13*G13 -> 324285720 | J13: （ファミリーAINAGOC負担） | K13: 23802106 | L13: 1 | M13: 1 | O13: =K13*L13*M13 -> 23802106 | P13: =I13+O13 -> 348087826
D14: （ファミリー利用者負担） | E14: 163186012 | F14: 1 | G14: 1 | I14: =E14*F14*G14 -> 163186012 | J14: （ファミリー利用者負担） | K14: 54133994 | L14: 1 | M14: 1 | O14: =K14*L14*M14 -> 54133994 | P14: =I14+O14 -> 217320006
D15: コンテナ | E15: 21000 | F15: 725 | G15: 11 | H15: =F15*G15 -> 7975 | I15: 167496000 | J15: コンテナ（選手団） | K15: 21000 | L15: =695*0.6 -> 417 | M15: 13 | N15: =L15*M15 -> 5421 | O15: =K15*L15*M15 -> 113841000 | P15: =I15+O15 -> 281337000
I16: =E16*F16*G16 -> 0 | J16: コンテナ（NOC本部） | K16: 21000 | L16: 200 | M16: 15 | N16: =L16*M16 -> 3000 | O16: =K16*L16*M16 -> 63000000 | P16: =I16+O16 -> 63000000
B17: 飲食費（ハラル・ヴィーガン対応） | C17: =SUM(P17) -> 1202035000 | D17: ホテル | E17: 19000 | F17: 4189 | G17: 11 | H17: =F17*G17 -> 46079 | I17: =E17*F17*G17 -> 875501000 | J17: ホテル | K17: 19000 | L17: =3305*0.4 -> 1322 | M17: 13 | N17: =L17*M17 -> 17186 | O17: =K17*L17*M17 -> 326534000 | P17: =I17+O17 -> 1202035000
D18: コンテナ | E18: 19000 | F18: 401 | G18: 11 | H18: =F18*G18 -> 4411 | I18: =E18*F18*G18 -> 83809000 | J18: コンテナ | K18: 19000 | L18: =695*0.4 -> 278 | M18: 13 | N18: =L18*M18 -> 3614 | O18: =K18*L18*M18 -> 68666000 | P18: =I18+O18 -> 152475000
B19: 飲食費（グラブアンドゴー） | C19: =SUM(P19) -> 127204000 | D19: ホテル | E19: 880 | F19: 9235 | G19: 11 | H19: =F19*G19 -> 101585 | I19: =E19*F19*G19 -> 89394800 | J19: ホテル | K19: 880 | L19: 3305 | M19: 13 | N19: =L19*M19 -> 42965 | O19: =K19*L19*M19 -> 37809200 | P19: =I19+O19 -> 127204000
D20: コンテナ | E20: 880 | F20: 1002 | G20: 11 | H20: =F20*G20 -> 11022 | I20: =E20*F20*G20 -> 9699360 | J20: コンテナ | K20: 880 | L20: 695 | M20: 13 | N20: =L20*M20 -> 9035 | O20: =K20*L20*M20 -> 7950800 | P20: =I20+O20 -> 17650160
D21: 船 | E21: 880 | F21: 2436 | G21: 18 | H21: =F21*G21 -> 43848 | I21: =E21*F21*G21 -> 38586240 | O21: =K21*L21*M21 -> 0 | P21: =I21+O21 -> 38586240
B22: 飲食費（アスリートミール：船） | C22: 920808000 | D22: 船 | E22: 21000 | F22: 2436 | G22: 18 | H22: =F22*G22 -> 43848 | I22: =E22*F22*G22 -> 920808000 | O22: =K22*L22*M22 -> 0 | P22: =I22+O22 -> 920808000
B23: 飲食費（空港島運営及びガーデンふ頭運営及び仮設厨房） | C23: =SUM(P23:P24) -> 1437358140 | D23: 空港島運営経費 | E23: 1336000000 | F23: 1 | G23: 1 | I23: =E23*F23*G23 -> 1336000000 | P23: =I23+O23 -> 1336000000
B24: 内容については別紙参照 | D24: 空港島仮設厨房経費 | E24: 101358140 | F24: 1 | G24: 1 | I24: =E24*F24*G24 -> 101358140 | O24: =K24*L24*M24 -> 0 | P24: =I24+O24 -> 101358140
D25: ガーデン運営経費 | E25: 408277000 | F25: 1 | G25: 1 | I25: =E25*F25*G25 -> 408277000 | J25: ガーデン運営経費 | K25: 360000000 | L25: 1 | M25: 1 | O25: =K25*L25*M25 -> 360000000 | P25: =I25+O25 -> 768277000
D26: ガーデン仮設厨房経費 | E26: 205723000 | F26: 1 | G26: 1 | I26: =E26*F26*G26 -> 205723000 | O26: =K26*L26*M26 -> 0 | P26: =I26+O26 -> 205723000
B27: 飲食費（その他経費（支援機器設置等）） | C27: =SUM(P27) -> 88652020 | D27: ホテル | E27: 6000000 | F27: 12 | G27: 1 | I27: =E27*F27*G27 -> 72000000 | J27: ホテル | K27: 2378860 | L27: 7 | M27: 1 | O27: =K27*L27*M27 -> 16652020 | P27: =I27+O27 -> 88652020
B28: 会議室等確保費 | C28: =SUM(P28:P29) -> 3450377147 | D28: ホテル（選手団） | E28: 858587762 | F28: 1 | G28: 1 | I28: =E28*F28*G28 -> 858587762 | J28: ホテル（選手団） | K28: 1030634912 | L28: 1 | M28: 1 | O28: =K28*L28*M28 -> 1030634912 | P28: =I28+O28 -> 1889222674
D29: ホテル（選手団以外）（ファミリー） | E29: 1178445153 | F29: 1 | G29: 1 | I29: =E29*F29*G29 -> 1178445153 | J29: ホテル（選手団以外）（ファミリー） | K29: 382709320 | L29: 1 | M29: 1 | O29: =K29*L29*M29 -> 382709320 | P29: =I29+O29 -> 1561154473
B30: 営業補償費 | C30: =SUM(P30) -> 54466667 | D30: ホテル（選手団以外）（ファミリー） | E30: 34400000 | F30: 1 | G30: 1 | I30: =E30*F30*G30 -> 34400000 | J30: ホテル（選手団以外）（ファミリー） | K30: 20066667 | L30: 1 | M30: 1 | O30: =K30*L30*M30 -> 20066667 | P30: =I30+O30 -> 54466667
B31: 合計 | C31: =SUM(C4,C11,C17,C19,C23,C27,C28,C30) -> 23477660084 | I31: =SUM(I4:I5,I11:I12,I17,I19,I23:I24,I27,I28:I29,I30) -> 16453865957 | O31: =SUM(O4:O5,O11:O12,O17,O19,O27,O28:O29,O30) -> 7023794127 | P31: =SUM(P4:P5,P11:Q12,P17,P19,P23:P24,P27,P28:P29,P30) -> 23477660084
A34: 25/6時点 | B34: 全体額 | D34: アジア | J34: パラ | P34: 全体
B35: 予算項目 | C35: 予算金額（VIL移管分含む） | D35: 項目 | E35: 単価 | F35: 人数 | G35: 泊数 | I35: 小計 | J35: 項目 | K35: 単価 | L35: 人数 | M35: 泊数 | O35: 小計 | P35: 合計 | Q35: 差し引き（項目ごと） | R35: 差し引き（項目ごと）
B36: 客室確保費（朝食付） | C36: =C4 -> 15457292778 | D36: ホテル（選手団） | E36: 3364680671 | F36: 1 | G36: 1 | I36: =E36*F36*G36 -> 3364680671 | J36: ホテル（選手団） | K36: 2615539538 | L36: 1 | M36: 1 | O36: =K36*L36*M36 -> 2615539538 | P36: =I36+O36 -> 5980220209 | Q36: =SUM(P36:P37)-C36 -> 7.7311319e+08 | R36: =SUM(P36:P37)-C36 -> 7.7311319e+08
D37: ホテル（選手団以外） | I37: =SUM(I38:I42) -> 7.8714323e+09 | J37: ホテル（選手団以外） | O37: =SUM(O38:O42) -> 2.3787535e+09 | P37: =SUM(P38:P42) -> 1.0250186e+10
D38: （ファミリーAINAGOC負担） | E38: 2334813782 | F38: 1 | G38: 1 | I38: =E38*F38*G38 -> 2334813782 | J38: （ファミリーAINAGOC負担） | K38: 237817800 | L38: 1 | M38: 1 | O38: =K38*L38*M38 -> 237817800 | P38: =I38+O38 -> 2572631582
J39: （ファミリー利用者負担） | K39: 234300000 | L39: 1 | M39: 1 | O39: =K39*L39*M39 -> 234300000 | P39: =I39+O39 -> 234300000
D40: （技術役員） | E40: 1.7067982e+09 | F40: 1 | G40: 1 | I40: =E40*F40*G40 -> 1.7067982e+09 | J40: （技術役員） | K40: 412159612 | L40: 1 | M40: 1 | O40: =K40*L40*M40 -> 412159612 | P40: =I40+O40 -> 2.1189579e+09
D41: （スポンサー利用者負担） | E41: 1.4860979e+09 | F41: 1 | G41: 1 | I41: =E41*F41*G41 -> 1.4860979e+09 | J41: （スポンサー利用者負担） | K41: 7.99788e+08 | L41: 1 | M41: 1 | O41: =K41*L41*M41 -> 7.99788e+08 | P41: =I41+O41 -> 2.2858859e+09
D42: （メディア利用者負担） | E42: 2.3437223e+09 | F42: 1 | G42: 1 | I42: =E42*F42*G42 -> 2.3437223e+09 | J42: （メディア利用者負担） | K42: 6.9468807e+08 | L42: 1 | M42: 1 | O42: =K42*L42*M42 -> 6.9468807e+08 | P42: =I42+O42 -> 3.0384104e+09
B43: 飲食費（昼食及び夕食） | C43: =C11 -> 1660274332 | D43: ホテル（選手団）昼食及び夕食 | E43: 16900 | F43: 58451 | G43: 1 | I43: =E43*F43*G43 -> 987821900 | J43: ホテル（選手団）昼食及び夕食 | K43: 16900 | L43: 31699 | M43: 1 | N43: =L43*M43 -> 31699 | O43: =K43*L43*M43 -> 535713100 | P43: =I43+O43 -> 1523535000 | Q43: =SUM(P43:P49)-C43 -> 3552291218 | R43: =SUM(P43:P45)-C43 -> 1430946248
D44: ホテル（選手団）ｱｽﾘｰﾄﾐｰﾙ差額 | E44: 79313574 | F44: 1 | G44: 1 | I44: =E44*F44*G44 -> 79313574 | J44: ホテル（選手団）ｱｽﾘｰﾄﾐｰﾙ差額 | K44: 30879036 | L44: 1 | M44: 1 | O44: =K44*L44*M44 -> 30879036 | P44: =SUM(I44,O44) -> 110192610
D45: ホテル（選手団以外） | I45: =SUM(I46,I48) -> 1181442570 | J45: ホテル（選手団以外） | O45: =SUM(O46:O48) -> 276050400 | P45: =SUM(P46:P48) -> 1457492970
D46: （ファミリーAINAGOC負担） | E46: 4.4624657e+08 | F46: 1 | G46: 1 | I46: =E46*F46*G46 -> 4.4624657e+08 | J46: （ファミリーAINAGOC負担） | K46: 12202608 | L46: 1 | M46: 1 | O46: =K46*L46*M46 -> 12202608 | P46: =I46+O46 -> 4.5844918e+08
J47: （ファミリー利用者負担） | K47: 60203792 | L47: 1 | M47: 1 | O47: =K47*L47*M47 -> 60203792 | P47: =I47+O47 -> 60203792
D48: （技術役員） | E48: 735196000 | F48: 1 | G48: 1 | I48: =E48*F48*G48 -> 735196000 | J48: （技術役員） | K48: 203644000 | L48: 1 | M48: 1 | O48: =K48*L48*M48 -> 203644000 | P48: =I48+O48 -> 938840000
D49: コンテナ（選手団・NOC）※3食 | E49: 21000 | F49: 22972 | G49: 1 | I49: =E49*F49*G49 -> 482412000 | J49: コンテナ（選手団・NOC）※3食 | K49: 21000 | L49: 8640 | M49: 1 | N49: =L49*M49 -> 8640 | O49: =K49*L49*M49 -> 181440000 | P49: =I49+O49 -> 663852000
B50: 飲食費（ハラル・ヴィーガン対応） | C50: =C17 -> 1202035000 | D50: ホテル自前 | E50: 19000 | F50: 8364 | G50: 1 | I50: =E50*F50*G50 -> 158916000 | J50: ホテル自前 | K50: 19000 | L50: 5536 | M50: 1 | N50: =L50*M50 -> 5536 | O50: =K50*L50*M50 -> 105184000 | P50: =I50+O50 -> 264100000 | Q50: =SUM(P50:P52)-C50 -> 469252800 | R50: =SUM(P50,P52)-C50 -> 86041800
D51: コンテナ | E51: 19000 | F51: 14409 | G51: 1 | I51: =E51*F51*G51 -> 273771000 | J51: コンテナ | K51: 19000 | L51: 5760 | M51: 1 | O51: =K51*L51*M51 -> 109440000 | P51: =I51+O51 -> 383211000
D52: 完調品対応 | E52: 22164 | F52: 30603 | G52: 1 | I52: =E52*F52*G52 -> 678284892 | J52: 完調品対応 | K52: 22164 | L52: 15597 | M52: 1 | N52: =L52*M52 -> 15597 | O52: =K52*L52*M52 -> 345691908 | P52: =I52+O52 -> 1023976800
B53: 飲食費（グラブアンドゴー） | C53: =C19 -> 127204000 | D53: ホテル | E53: 880 | F53: 97418 | G53: 1 | I53: =E53*F53*G53 -> 85727840 | J53: ホテル | K53: 880 | L53: 52832 | M53: 1 | N53: =L53*M53 -> 52832 | O53: =K53*L53*M53 -> 46492160 | P53: =I53+O53 -> 132220000 | Q53: =SUM(P53:P55)-C53 -> 96855440 | R53: =SUM(P53)-C53 -> 5016000
D54: コンテナ | E54: 880 | F54: 37381 | G54: 1 | I54: =E54*F54*G54 -> 32895280 | J54: コンテナ | K54: 880 | L54: 14400 | M54: 1 | N54: =L54*M54 -> 14400 | O54: =K54*L54*M54 -> 12672000 | P54: =I54+O54 -> 45567280
D55: 船 | E55: 880 | F55: 52582 | G55: 1 | I55: =E55*F55*G55 -> 46272160 | O55: =K55*L55*M55 -> 0 | P55: =I55+O55 -> 46272160
B56: 飲食費（アスリートミール：船） | C56: 920808000 | D56: 船 | E56: 21000 | F56: 52582 | G56: 1 | I56: =E56*F56*G56 -> 1104222000 | O56: =K56*L56*M56 -> 0 | P56: =I56+O56 -> 1104222000 | Q56: =SUM(P56)-C56 -> 183414000
B57: 飲食費（空港島運営及びガーデンふ頭運営及び仮設厨房） | C57: =C23 -> 1437358140 | D57: 空港島運営経費 | E57: 1336000000 | F57: 1 | G57: 1 | I57: =E57*F57*G57 -> 1336000000 | P57: =I57+O57 -> 1336000000 | Q57: =SUM(P57:P60)-C57 -> 974000860 | R57: =SUM(P57:P58)-C57 -> 860
D58: 空港島仮設厨房経費 | E58: 101359000 | F58: 1 | G58: 1 | I58: =E58*F58*G58 -> 101359000 | O58: =K58*L58*M58 -> 0 | P58: =I58+O58 -> 101359000
D59: ガーデン運営経費 | E59: 408277000 | F59: 1 | G59: 1 | I59: =E59*F59*G59 -> 408277000 | J59: ガーデン運営経費 | K59: 360000000 | L59: 1 | M59: 1 | O59: =K59*L59*M59 -> 360000000 | P59: =I59+O59 -> 768277000
D60: ガーデン仮設厨房経費 | E60: 205723000 | F60: 1 | G60: 1 | I60: =E60*F60*G60 -> 205723000 | O60: =K60*L60*M60 -> 0 | P60: =I60+O60 -> 205723000
B61: 飲食費（その他経費（支援機器設置等）） | C61: =C27 -> 88652020 | D61: ホテル厨房機器レンタル | E61: 6000000 | F61: 12 | G61: 1 | I61: =E61*F61*G61 -> 72000000 | J61: ホテル厨房機器レンタル | K61: 2379000 | L61: 7 | M61: 1 | O61: =K61*L61*M61 -> 16653000 | P61: =I61+O61 -> 88653000 | Q61: =SUM(P61:P62,P63)-C61 -> 10458980 | R61: =SUM(P61)-C61 -> 980
D62: シップグラブ＆ゴー設備レンタル | E62: 9351000 | F62: 1 | G62: 1 | I62: =E62*F62*G62 -> 9351000 | P62: =I62+O62 -> 9351000
D63: シップグラブ＆ゴー備品レンタル | E63: 1107000 | F63: 1 | G63: 1 | I63: =E63*F63*G63 -> 1107000 | P63: =I63+O63 -> 1107000
B64: 会議室等確保費 | C64: =C28 -> 3450377147 | D64: ホテル（選手団） | E64: 1.618789e+09 | F64: 1 | G64: 1 | I64: =E64*F64*G64 -> 1.618789e+09 | J64: ホテル（選手団） | K64: 1.0971813e+09 | L64: 1 | M64: 1 | O64: =K64*L64*M64 -> 1.0971813e+09 | P64: =I64+O64 -> 2.7159704e+09 | Q64: =SUM(P64:P65)-C64 -> 2.072415e+09 | R64: =SUM(P64:P65)-C64 -> 2.072415e+09
D65: ホテル（選手団以外） | I65: =SUM(I66:I67) -> 1.9880305e+09 | J65: ホテル（選手団以外） | O65: =SUM(O66:O67) -> 8.187913e+08 | P65: =SUM(P66:P67) -> 2.8068218e+09
D66: （ファミリー） | E66: 1.1408776e+09 | F66: 1 | G66: 1 | I66: =E66*F66*G66 -> 1.1408776e+09 | J66: （ファミリー） | K66: 2.886576e+08 | L66: 1 | M66: 1 | O66: =K66*L66*M66 -> 2.886576e+08 | P66: =I66+O66 -> 1.4295352e+09
D67: （技術役員） | E67: 8.4715285e+08 | F67: 1 | G67: 1 | I67: =E67*F67*G67 -> 8.4715285e+08 | J67: （技術役員） | K67: 5.301337e+08 | L67: 1 | M67: 1 | O67: =K67*L67*M67 -> 5.301337e+08 | P67: =I67+O67 -> 1.3772865e+09
B68: 営業補償費 | C68: =C30 -> 54466667 | D68: ホテル（一棟貸しによる補償） | I68: =SUM(I69:I70) -> 1.1773603e+08 | J68: ホテル（一棟貸しによる補償） | O68: =SUM(O69:O70) -> 91897355 | P68: =I68+O68 -> 2.0963338e+08 | Q68: =SUM(P68)-C68 -> 1.5516671e+08 | R68: =SUM(P68,P71)-C68 -> 4.5893617e+09
D69: （選手団） | E69: 71660120 | F69: 1 | G69: 1 | I69: =E69*F69*G69 -> 71660120 | J69: （選手団） | K69: 91105355 | L69: 1 | M69: 1 | O69: =K69*L69*M69 -> 91105355 | P69: =I69+O69 -> 1.6276548e+08
D70: （ファミリー） | E70: 46075905 | F70: 1 | G70: 1 | I70: =E70*F70*G70 -> 46075905 | J70: （ファミリー） | K70: 792000 | L70: 1 | M70: 1 | O70: =K70*L70*M70 -> 792000 | P70: =I70+O70 -> 46867905
D71: ホテル（クリーンベニューによる補償） | I71: =SUM(I72:I73) -> 2707445000 | J71: ホテル（クリーンベニューによる補償） | O71: =SUM(O72:O73) -> 1726750000 | P71: =I71+O71 -> 4434195000
D72: （選手団※自動販売機補償） | E72: 10045000 | F72: 1 | G72: 1 | I72: =E72*F72*G72 -> 10045000 | J72: （選手団※自動販売機補償） | K72: 6750000 | L72: 1 | M72: 1 | O72: =K72*L72*M72 -> 6750000 | P72: =I72+O72 -> 16795000
D73: （選手団※テナント等補償） | E73: 2697400000 | F73: 1 | G73: 1 | I73: =E73*F73*G73 -> 2697400000 | J73: （選手団※テナント等補償） | K73: 1720000000 | L73: 1 | M73: 1 | O73: =K73*L73*M73 -> 1720000000 | P73: =I73+O73 -> 4417400000
B74: ランドリーサービス費 | C74: 0 | D74: ランドリーサービス費（選手団以外） | E74: 136866942 | F74: 1 | G74: 1 | I74: =E74*F74*G74 -> 136866942 | J74: ランドリーサービス費（選手団以外） | K74: 23176780 | L74: 1 | M74: 1 | O74: =K74*L74*M74 -> 23176780 | P74: =SUM(I74,O74) -> 160043722 | R74: =SUM(P74)-C74 -> 160043722
B75: 合計 | C75: =SUM(C36,C43,C50,C53,C57,C61,C64,C68,C74) -> 23477660084 | I75: =SUM(I36:I37,I43:I45,I50,I52,I53,I57:I58,I61,I64:I65,I68,I71,I74) -> 2.2485846e+10 | O75: =SUM(O36:O37,O43:O45,O50,O52,O53,O61,O64:O65,O68,O71,O74) -> 1.0108753e+10 | P75: =SUM(P36,P37,P43,P44,P45,P50,P52,P53,P57,P58,P61,P64,P65,P68,P71,P74) -> 3.25946e+10 | Q75: =P75-C75 -> 9.1169395e+09 | R75: =SUM(R36:R74) -> 9.1169395e+09
B76: ※技術役員・スポンサー・メディアのホテルについては、積算単価が2021年時点のものであるため、客室単価に1.34（宿泊料物価上昇率）を掛けている | P76: ↑要求額 ※32,594,602千円 | Q76: 全体差し引き
B77: ※技術役員の会議室費用については1.1（総合物価上昇率）を掛けている | G77: アジア差し引き | I77: =I75-I31 -> 6.0319802e+09 | M77: パラ差し引き | O77: =O75-O31 -> 3.0849593e+09
B78: ※技術役員の昼食夕食について、延べ人数の3割に5,000円の昼食提供、10割に10,000円の夕食提供、5割に1,500円の夜食提供という前提で算出。
B79: ※クリーンベニューの営業補償については、どこまでの範囲を行うのか、どのSHを行うのか不明のため、少なくとも選手村として運用するホテルの全てのテナントに対して行う想定で算出。
B80: ※自動販売機の補償については、1台5,000円の換算で、各施設2フロアにつき1台がある想定で仮置きし算出
B81: ※テナント営業補償について、レストランやコンビニ、ゴルフ場など補償額が高そうなものが多くあるため各施設1,800,000円/日にて計算（ヒルトンしか参照単価がないためこの金額を参考）
B82: ➡なお、500,000円/日だとしても1,200,000,000円程度になる計算。
B83: ※ファミリーのランドリーサービス費については、昨年度要求時、財政見通し時にアジア86,508千円、パラ22,496千円にて積算するも予算要求資料には記載せず。ただし来年度の支払で必要になるため今回の予算要求時には積算
A86: 25/10時点 | B86: 全体額 | D86: アジア | J86: パラ | P86: 全体
B87: 予算項目 | C87: 内示金額（7/31枠要求） | D87: 項目 | E87: 単価 | F87: 人数 | G87: 泊数 | I87: 小計 | J87: 項目 | K87: 単価 | L87: 人数 | M87: 泊数 | O87: 小計 | P87: 合計 | Q87: 差し引き（項目ごと） | R87: 差し引き（項目ごと）
B88: 客室確保費（朝食付） | C88: =SUM(P36,P37) -> 1.6230406e+10 | D88: ホテル（選手団） | E88: ='財政見通し積算 (全SH全項目統合版）'!C26 -> #REF! | F88: 1 | G88: 1 | I88: =E88*F88*G88 -> #REF! | J88: ホテル（選手団） | K88: ='財政見通し積算 (全SH全項目統合版）'!C31 -> #REF! | L88: 1 | M88: 1 | O88: =K88*L88*M88 -> #REF! | P88: =I88+O88 -> #REF! | Q88: =SUM(P88:P89)-C88 -> #REF! | R88: =SUM(P88:P89)-C88 -> #REF!
D89: ホテル（選手団以外） | I89: =SUM(I90:I94) -> 7.8708056e+09 | J89: ホテル（選手団以外） | O89: =SUM(O90:O94) -> 2.0563535e+09 | P89: =SUM(P90:P94) -> 9.9271591e+09
D90: （ファミリーAINAGOC負担） | E90: ='財政見通し積算 (全SH全項目統合版）'!C27 -> 2204156998 | F90: 1 | G90: 1 | I90: =E90*F90*G90 -> 2204156998 | J90: （ファミリーAINAGOC負担） | K90: ='財政見通し積算 (全SH全項目統合版）'!C32-K39 -> 237817800 | L90: 1 | M90: 1 | O90: =K90*L90*M90 -> 237817800 | P90: =I90+O90 -> 2441974798
J91: （ファミリー利用者負担） | K91: =【250925】アジパラファミリー積算!BS29 -> 234300000 | L91: 1 | M91: 1 | O91: =K91*L91*M91 -> 234300000 | P91: =I91+O91 -> 234300000
D92: （技術役員） | E92: ='財政見通し積算 (全SH全項目統合版）'!C28 -> 1724607631 | F92: 1 | G92: 1 | I92: =E92*F92*G92 -> 1724607631 | J92: （技術役員） | K92: ='財政見通し積算 (全SH全項目統合版）'!C33 -> 344907436 | L92: 1 | M92: 1 | O92: =K92*L92*M92 -> 344907436 | P92: =I92+O92 -> 2069515067
D93: （スポンサー利用者負担） | E93: ='財政見通し積算 (全SH全項目統合版）'!C29 -> 1.2854877e+09 | F93: 1 | G93: 1 | I93: =E93*F93*G93 -> 1.2854877e+09 | J93: （スポンサー利用者負担） | K93: ='財政見通し積算 (全SH全項目統合版）'!C34 -> 8.3703864e+08 | L93: 1 | M93: 1 | O93: =K93*L93*M93 -> 8.3703864e+08 | P93: =I93+O93 -> 2.1225263e+09
D94: （メディア利用者負担） | E94: ='財政見通し積算 (全SH全項目統合版）'!C30 -> 2656553304 | F94: 1 | G94: 1 | I94: =E94*F94*G94 -> 2656553304 | J94: （メディア利用者負担） | K94: ='財政見通し積算 (全SH全項目統合版）'!C35 -> 4.022896e+08 | L94: 1 | M94: 1 | O94: =K94*L94*M94 -> 4.022896e+08 | P94: =I94+O94 -> 3.0588429e+09
B95: 飲食費（昼食及び夕食） | C95: =SUM(P43,P44,P45) -> 3091220580 | D95: ホテル（選手団）昼食及び夕食 | E95: 22104 | F95: 58549 | G95: 1 | I95: =E95*F95*G95 -> 1294167096 | J95: ホテル（選手団）昼食及び夕食 | K95: 22104 | L95: 32390 | M95: 1 | N95: =L95*M95 -> 32390 | O95: =K95*L95*M95 -> 715948560 | P95: =I95+O95 -> 2010115656 | Q95: =SUM(P95:P100)-C95 -> #REF! | R95: =SUM(P95:P97)-C95 -> #REF!
B96: ※飲食費（通常食対応） | D96: ホテル（選手団）ｱｽﾘｰﾄﾐｰﾙ差額 | E96: ='財政見通し積算 (全SH全項目統合版）'!E26 -> #REF! | F96: 1 | G96: 1 | I96: =E96*F96*G96 -> #REF! | J96: ホテル（選手団）ｱｽﾘｰﾄﾐｰﾙ差額 | K96: ='財政見通し積算 (全SH全項目統合版）'!E31 -> #REF! | L96: 1 | M96: 1 | O96: =K96*L96*M96 -> #REF! | P96: =SUM(I96,O96) -> #REF!
D97: ホテル（選手団以外） | I97: =SUM(I98,I100) -> 1179968416 | J97: ホテル（選手団以外） | O97: =SUM(O98:O100) -> 267855150 | P97: =SUM(P98:P100) -> 1447823566
D98: （ファミリーAINAGOC負担） | E98: ='財政見通し積算 (全SH全項目統合版）'!E27 -> 453261666 | F98: 1 | G98: 1 | I98: =E98*F98*G98 -> 453261666 | J98: （ファミリーAINAGOC負担） | K98: ='財政見通し積算 (全SH全項目統合版）'!E32-K47 -> 12202608 | L98: 1 | M98: 1 | O98: =K98*L98*M98 -> 12202608 | P98: =I98+O98 -> 465464274
J99: （ファミリー利用者負担） | K99: =【250925】アジパラファミリー積算!BV29 -> 60203792 | L99: 1 | M99: 1 | O99: =K99*L99*M99 -> 60203792 | P99: =I99+O99 -> 60203792
D100: （技術役員） | E100: ='財政見通し積算 (全SH全項目統合版）'!E28 -> 726706750 | F100: 1 | G100: 1 | I100: =E100*F100*G100 -> 726706750 | J100: （技術役員） | K100: ='財政見通し積算 (全SH全項目統合版）'!E33 -> 195448750 | L100: 1 | M100: 1 | O100: =K100*L100*M100 -> 195448750 | P100: =I100+O100 -> 922155500
B101: 飲食費（ハラル・ヴィーガン対応） | C101: =SUM(P50,P52) -> 1288076800 | D101: ホテル自前 | E101: 22104 | F101: 8589 | G101: 1 | I101: =E101*F101*G101 -> 189851256 | J101: ホテル自前 | K101: 22104 | L101: 5101 | M101: 1 | N101: =L101*M101 -> 5101 | O101: =K101*L101*M101 -> 112752504 | P101: =I101+O101 -> 302603760 | Q101: =SUM(P101:P102)-C101 -> 1021314212 | R101: =SUM(P101,P102)-C101 -> 1021314212
D102: 完調品対応 | I102: =SUM(I103:I104) -> 1301645530 | J102: 完調品対応 | N102: =L102*M102 -> 0 | O102: =SUM(O103:O104) -> 705141722 | P102: =I102+O102 -> 2006787252
D103: （完調品調達費用） | E103: 22164 | F103: 30445 | G103: 1 | I103: =E103*F103*G103 -> 674782980 | J103: （完調品調達費用） | K103: 22164 | L103: 16493 | M103: 1 | N103: =L103*M103 -> 16493 | O103: =K103*L103*M103 -> 365550852 | P103: =I103+O103 -> 1040333832
D104: （ホテル経費） | E104: 20590 | F104: 30445 | G104: 1 | I104: =E104*F104*G104 -> 626862550 | J104: （ホテル経費） | K104: 20590 | L104: 16493 | M104: 1 | O104: =K104*L104*M104 -> 339590870 | P104: =I104+O104 -> 966453420
B105: 飲食費（グラブアンドゴー） | C105: =SUM(P53) -> 132220000 | D105: ホテル | E105: 880 | F105: 97583 | G105: 1 | I105: =E105*F105*G105 -> 85873040 | J105: ホテル | K105: 880 | L105: 53984 | M105: 1 | N105: =L105*M105 -> 53984 | O105: =K105*L105*M105 -> 47505920 | P105: =I105+O105 -> 133378960 | Q105: =SUM(P105:P105)-C105 -> 1158960 | R105: =SUM(P105)-C105 -> 1158960
...

Sheet 予算管理比較積算（VIL移管反映）
A1: 24/10時点 | B1: 全体予算 | D1: アジア | H1: 一旦計算（非表示） | J1: パラ | N1: 一旦計算（非表示） | P1: 全体
B2: 予算項目 | C2: 予算金額（VIL移管分含む） | D2: 項目 | E2: 単価 | F2: 人数 | G2: 泊数 | I2: 小計 | J2: 項目 | K2: 単価 | L2: 人数 | M2: 泊数 | O2: 小計 | P2: 合計
B3: 客室確保費（朝食付） | C3: =SUM(P3,P4) -> 15457292778 | D3: ホテル（選手団） | E3: 3042691395 | F3: 1 | G3: 1 | I3: =E3*F3*G3 -> 3042691395 | J3: ホテル（選手団） | K3: 2596055904 | L3: 1 | M3: 1 | O3: =K3*L3*M3 -> 2596055904 | P3: =I3+O3 -> 5638747299
D4: ホテル（選手団以外） | E4: 7718814575 | F4: 1 | G4: 1 | I4: =E4*F4*G4 -> 7718814575 | J4: ホテル（選手団以外） | K4: 2099730904 | L4: 1 | M4: 1 | O4: =K4*L4*M4 -> 2099730904 | P4: =I4+O4 -> 9818545479
D5: （ファミリーAINAGOC負担） | E5: 2004704909 | F5: 1 | G5: 1 | I5: =E5*F5*G5 -> 2004704909 | J5: （ファミリーAINAGOC負担） | K5: 197828150 | L5: 1 | M5: 1 | O5: =K5*L5*M5 -> 197828150 | P5: =I5+O5 -> 2202533059
D6: （ファミリー利用者負担） | E6: 881565432 | F6: 1 | G6: 1 | I6: =E6*F6*G6 -> 881565432 | J6: （ファミリー利用者負担） | K6: 449927739 | L6: 1 | M6: 1 | O6: =K6*L6*M6 -> 449927739 | P6: =I6+O6 -> 1331493171
D7: （技術役員） | E7: 723774664 | F7: 1 | G7: 1 | I7: =E7*F7*G7 -> 723774664 | J7: （技術役員） | K7: 217404288 | L7: 1 | M7: 1 | O7: =K7*L7*M7 -> 217404288 | P7: =I7+O7 -> 941178952
D8: （スポンサー利用者負担） | E8: =SUM('財政見通し積算 (全SH全項目統合版）'!AD29) -> 2342187094 | F8: 1 | G8: 1 | I8: =E8*F8*G8 -> 2342187094 | J8: （スポンサー利用者負担） | K8: 783186617 | L8: 1 | M8: 1 | O8: =K8*L8*M8 -> 783186617 | P8: =I8+O8 -> 3125373711
D9: （メディア利用者負担） | E9: =SUM('財政見通し積算 (全SH全項目統合版）'!AD30) -> 1766582476 | F9: 1 | G9: 1 | I9: =E9*F9*G9 -> 1766582476 | J9: （メディア利用者負担） | K9: =SUM('財政見通し積算 (全SH全項目統合版）'!AD35) -> 451384110 | L9: 1 | M9: 1 | O9: =K9*L9*M9 -> 451384110 | P9: =I9+O9 -> 2217966586
B10: 飲食費（昼食及び夕食） | C10: =SUM(P10:P11) -> 1660274332 | D10: ホテル（選手団） | E10: 16900 | F10: 3546 | G10: 11 | H10: =F10*G10 -> 39006 | I10: =E10*F10*G10 -> 659201400 | J10: ホテル（選手団） | K10: 16900 | L10: =3305*0.6 -> 1983 | M10: 13 | N10: =L10*M10 -> 25779 | O10: =K10*L10*M10 -> 435665100 | P10: =I10+O10 -> 1094866500
D11: ホテル（選手団以外） | E11: =SUM(E12:E13) -> 487471732 | F11: 1 | G11: 1 | I11: =E11*F11*G11 -> 487471732 | J11: ホテル（選手団以外） | K11: =SUM(K12:K13) -> 77936100 | L11: 1 | M11: 1 | O11: =K11*L11*M11 -> 77936100 | P11: =I11+O11 -> 565407832
D12: （ファミリーAINAGOC負担） | E12: 324285720 | F12: 1 | G12: 1 | I12: =E12*F12*G12 -> 324285720 | J12: （ファミリーAINAGOC負担） | K12: 23802106 | L12: 1 | M12: 1 | O12: =K12*L12*M12 -> 23802106 | P12: =I12+O12 -> 348087826
D13: （ファミリー利用者負担） | E13: 163186012 | F13: 1 | G13: 1 | I13: =E13*F13*G13 -> 163186012 | J13: （ファミリー利用者負担） | K13: 54133994 | L13: 1 | M13: 1 | O13: =K13*L13*M13 -> 54133994 | P13: =I13+O13 -> 217320006
D14: コンテナ | E14: 21000 | F14: 725 | G14: 11 | H14: =F14*G14 -> 7975 | I14: 167496000 | J14: コンテナ（選手団） | K14: 21000 | L14: =695*0.6 -> 417 | M14: 13 | N14: =L14*M14 -> 5421 | O14: =K14*L14*M14 -> 113841000 | P14: =I14+O14 -> 281337000
I15: =E15*F15*G15 -> 0 | J15: コンテナ（NOC本部） | K15: 21000 | L15: 200 | M15: 15 | N15: =L15*M15 -> 3000 | O15: =K15*L15*M15 -> 63000000 | P15: =I15+O15 -> 63000000
B16: 飲食費（ハラル・ヴィーガン対応） | C16: =SUM(P16) -> 1202035000 | D16: ホテル | E16: 19000 | F16: 4189 | G16: 11 | H16: =F16*G16 -> 46079 | I16: =E16*F16*G16 -> 875501000 | J16: ホテル | K16: 19000 | L16: =3305*0.4 -> 1322 | M16: 13 | N16: =L16*M16 -> 17186 | O16: =K16*L16*M16 -> 326534000 | P16: =I16+O16 -> 1202035000
D17: コンテナ | E17: 19000 | F17: 401 | G17: 11 | H17: =F17*G17 -> 4411 | I17: =E17*F17*G17 -> 83809000 | J17: コンテナ | K17: 19000 | L17: =695*0.4 -> 278 | M17: 13 | N17: =L17*M17 -> 3614 | O17: =K17*L17*M17 -> 68666000 | P17: =I17+O17 -> 152475000
B18: 飲食費（グラブアンドゴー） | C18: =SUM(P18) -> 127204000 | D18: ホテル | E18: 880 | F18: 9235 | G18: 11 | H18: =F18*G18 -> 101585 | I18: =E18*F18*G18 -> 89394800 | J18: ホテル | K18: 880 | L18: 3305 | M18: 13 | N18: =L18*M18 -> 42965 | O18: =K18*L18*M18 -> 37809200 | P18: =I18+O18 -> 127204000
D19: コンテナ | E19: 880 | F19: 1002 | G19: 11 | H19: =F19*G19 -> 11022 | I19: =E19*F19*G19 -> 9699360 | J19: コンテナ | K19: 880 | L19: 695 | M19: 13 | N19: =L19*M19 -> 9035 | O19: =K19*L19*M19 -> 7950800 | P19: =I19+O19 -> 17650160
D20: 船 | E20: 880 | F20: 2436 | G20: 18 | H20: =F20*G20 -> 43848 | I20: =E20*F20*G20 -> 38586240 | O20: =K20*L20*M20 -> 0 | P20: =I20+O20 -> 38586240
B21: 飲食費（アスリートミール：船） | C21: 920808000 | D21: 船 | E21: 21000 | F21: 2436 | G21: 18 | H21: =F21*G21 -> 43848 | I21: =E21*F21*G21 -> 920808000 | O21: =K21*L21*M21 -> 0 | P21: =I21+O21 -> 920808000
B22: 飲食費（空港島運営及びガーデンふ頭運営及び仮設厨房） | C22: =SUM(P22:P23) -> 1437358140 | D22: 空港島運営経費 | E22: 1336000000 | F22: 1 | G22: 1 | I22: =E22*F22*G22 -> 1336000000 | P22: =I22+O22 -> 1336000000
B23: 内容については別紙参照 | D23: 空港島仮設厨房経費 | E23: 101358140 | F23: 1 | G23: 1 | I23: =E23*F23*G23 -> 101358140 | O23: =K23*L23*M23 -> 0 | P23: =I23+O23 -> 101358140
D24: ガーデン運営経費 | E24: 408277000 | F24: 1 | G24: 1 | I24: =E24*F24*G24 -> 408277000 | J24: ガーデン運営経費 | K24: 360000000 | L24: 1 | M24: 1 | O24: =K24*L24*M24 -> 360000000 | P24: =I24+O24 -> 768277000
D25: ガーデン仮設厨房経費 | E25: 205723000 | F25: 1 | G25: 1 | I25: =E25*F25*G25 -> 205723000 | O25: =K25*L25*M25 -> 0 | P25: =I25+O25 -> 205723000
B26: 飲食費（その他経費（支援機器設置等）） | C26: =SUM(P26) -> 88652020 | D26: ホテル | E26: 6000000 | F26: 12 | G26: 1 | I26: =E26*F26*G26 -> 72000000 | J26: ホテル | K26: 2378860 | L26: 7 | M26: 1 | O26: =K26*L26*M26 -> 16652020 | P26: =I26+O26 -> 88652020
B27: 会議室等確保費 | C27: =SUM(P27:P28) -> 3450377147 | D27: ホテル（選手団） | E27: 858587762 | F27: 1 | G27: 1 | I27: =E27*F27*G27 -> 858587762 | J27: ホテル（選手団） | K27: 1030634912 | L27: 1 | M27: 1 | O27: =K27*L27*M27 -> 1030634912 | P27: =I27+O27 -> 1889222674
D28: ホテル（選手団以外）（ファミリー） | E28: 1178445153 | F28: 1 | G28: 1 | I28: =E28*F28*G28 -> 1178445153 | J28: ホテル（選手団以外）（ファミリー） | K28: 382709320 | L28: 1 | M28: 1 | O28: =K28*L28*M28 -> 382709320 | P28: =I28+O28 -> 1561154473
B29: 営業補償費 | C29: =SUM(P29) -> 54466667 | D29: ホテル（選手団以外）（ファミリー） | E29: 34400000 | F29: 1 | G29: 1 | I29: =E29*F29*G29 -> 34400000 | J29: ホテル（選手団以外）（ファミリー） | K29: 20066667 | L29: 1 | M29: 1 | O29: =K29*L29*M29 -> 20066667 | P29: =I29+O29 -> 54466667
B30: 合計 | C30: =SUM(C3,C10,C16,C18,C22,C26,C27,C29) -> 23477660084 | I30: =SUM(I3:I4,I10:I11,I16,I18,I22:I23,I26,I27:I28,I29) -> 16453865957 | O30: =SUM(O3:O4,O10:O11,O16,O18,O26,O27:O28,O29) -> 7023794127 | P30: =SUM(P3:P4,P10:Q11,P16,P18,P22:P23,P26,P27:P28,P29) -> 23477660084
A33: 25/6時点 | B33: 全体額 | D33: アジア | J33: パラ | P33: 全体
B34: 予算項目 | C34: 予算金額（VIL移管分含む） | D34: 項目 | E34: 単価 | F34: 人数 | G34: 泊数 | I34: 小計 | J34: 項目 | K34: 単価 | L34: 人数 | M34: 泊数 | O34: 小計 | P34: 合計 | Q34: 差し引き（項目ごと） | R34: 差し引き（項目ごと）
B35: 客室確保費（朝食付） | C35: =C3 -> 15457292778 | D35: ホテル（選手団） | E35: ='財政見通し積算 (全SH全項目統合版）'!C26 -> #REF! | F35: 1 | G35: 1 | I35: =E35*F35*G35 -> #REF! | J35: ホテル（選手団） | K35: ='財政見通し積算 (全SH全項目統合版）'!C31 -> #REF! | L35: 1 | M35: 1 | O35: =K35*L35*M35 -> #REF! | P35: =I35+O35 -> #REF! | Q35: =SUM(P35:P36)-C35 -> #REF! | R35: =SUM(P35:P36)-C35 -> #REF!
D36: ホテル（選手団以外） | I36: =SUM(I37:I41) -> 7.8708056e+09 | J36: ホテル（選手団以外） | O36: =SUM(O37:O41) -> 2.0563535e+09 | P36: =SUM(P37:P41) -> 9.9271591e+09
D37: （ファミリーAINAGOC負担） | E37: ='財政見通し積算 (全SH全項目統合版）'!C27 -> 2204156998 | F37: 1 | G37: 1 | I37: =E37*F37*G37 -> 2204156998 | J37: （ファミリーAINAGOC負担） | K37: ='財政見通し積算 (全SH全項目統合版）'!C32-K38 -> 237817800 | L37: 1 | M37: 1 | O37: =K37*L37*M37 -> 237817800 | P37: =I37+O37 -> 2441974798
J38: （ファミリー利用者負担） | K38: =【250925】アジパラファミリー積算!BS29 -> 234300000 | L38: 1 | M38: 1 | O38: =K38*L38*M38 -> 234300000 | P38: =I38+O38 -> 234300000
D39: （技術役員） | E39: ='財政見通し積算 (全SH全項目統合版）'!C28 -> 1724607631 | F39: 1 | G39: 1 | I39: =E39*F39*G39 -> 1724607631 | J39: （技術役員） | K39: ='財政見通し積算 (全SH全項目統合版）'!C33 -> 344907436 | L39: 1 | M39: 1 | O39: =K39*L39*M39 -> 344907436 | P39: =I39+O39 -> 2069515067
D40: （スポンサー利用者負担） | E40: ='財政見通し積算 (全SH全項目統合版）'!C29 -> 1.2854877e+09 | F40: 1 | G40: 1 | I40: =E40*F40*G40 -> 1.2854877e+09 | J40: （スポンサー利用者負担） | K40: ='財政見通し積算 (全SH全項目統合版）'!C34 -> 8.3703864e+08 | L40: 1 | M40: 1 | O40: =K40*L40*M40 -> 8.3703864e+08 | P40: =I40+O40 -> 2.1225263e+09
D41: （メディア利用者負担） | E41: ='財政見通し積算 (全SH全項目統合版）'!C30 -> 2656553304 | F41: 1 | G41: 1 | I41: =E41*F41*G41 -> 2656553304 | J41: （メディア利用者負担） | K41: ='財政見通し積算 (全SH全項目統合版）'!C35 -> 4.022896e+08 | L41: 1 | M41: 1 | O41: =K41*L41*M41 -> 4.022896e+08 | P41: =I41+O41 -> 3.0588429e+09
B42: 飲食費（昼食及び夕食） | C42: =C10 -> 1660274332 | D42: ホテル（選手団）昼食及び夕食 | E42: 16900 | F42: 58451 | G42: 1 | I42: =E42*F42*G42 -> 987821900 | J42: ホテル（選手団）昼食及び夕食 | K42: 16900 | L42: 31699 | M42: 1 | N42: =L42*M42 -> 31699 | O42: =K42*L42*M42 -> 535713100 | P42: =I42+O42 -> 1523535000 | Q42: =SUM(P42:P48)-C42 -> #REF! | R42: =SUM(P42:P44)-C42 -> #REF!
D43: ホテル（選手団）ｱｽﾘｰﾄﾐｰﾙ差額 | E43: ='財政見通し積算 (全SH全項目統合版）'!E26 -> #REF! | F43: 1 | G43: 1 | I43: =E43*F43*G43 -> #REF! | J43: ホテル（選手団）ｱｽﾘｰﾄﾐｰﾙ差額 | K43: ='財政見通し積算 (全SH全項目統合版）'!E31 -> #REF! | L43: 1 | M43: 1 | O43: =K43*L43*M43 -> #REF! | P43: =SUM(I43,O43) -> #REF!
D44: ホテル（選手団以外） | I44: =SUM(I45,I47) -> 1179968416 | J44: ホテル（選手団以外） | O44: =SUM(O45:O47) -> 267855150 | P44: =SUM(P45:P47) -> 1447823566
D45: （ファミリーAINAGOC負担） | E45: ='財政見通し積算 (全SH全項目統合版）'!E27 -> 453261666 | F45: 1 | G45: 1 | I45: =E45*F45*G45 -> 453261666 | J45: （ファミリーAINAGOC負担） | K45: ='財政見通し積算 (全SH全項目統合版）'!E32-K46 -> 12202608 | L45: 1 | M45: 1 | O45: =K45*L45*M45 -> 12202608 | P45: =I45+O45 -> 465464274
J46: （ファミリー利用者負担） | K46: =【250925】アジパラファミリー積算!BV29 -> 60203792 | L46: 1 | M46: 1 | O46: =K46*L46*M46 -> 60203792 | P46: =I46+O46 -> 60203792
D47: （技術役員） | E47: ='財政見通し積算 (全SH全項目統合版）'!E28 -> 726706750 | F47: 1 | G47: 1 | I47: =E47*F47*G47 -> 726706750 | J47: （技術役員） | K47: ='財政見通し積算 (全SH全項目統合版）'!E33 -> 195448750 | L47: 1 | M47: 1 | O47: =K47*L47*M47 -> 195448750 | P47: =I47+O47 -> 922155500
D48: コンテナ（選手団・NOC）※3食 | E48: 21000 | F48: 22972 | G48: 1 | I48: =E48*F48*G48 -> 482412000 | J48: コンテナ（選手団・NOC）※3食 | K48: 21000 | L48: 8640 | M48: 1 | N48: =L48*M48 -> 8640 | O48: =K48*L48*M48 -> 181440000 | P48: =I48+O48 -> 663852000
B49: 飲食費（ハラル・ヴィーガン対応） | C49: =C16 -> 1202035000 | D49: ホテル自前 | E49: 19000 | F49: 8364 | G49: 1 | I49: =E49*F49*G49 -> 158916000 | J49: ホテル自前 | K49: 19000 | L49: 5536 | M49: 1 | N49: =L49*M49 -> 5536 | O49: =K49*L49*M49 -> 105184000 | P49: =I49+O49 -> 264100000 | Q49: =SUM(P49:P51)-C49 -> 469252800 | R49: =SUM(P49,P51)-C49 -> 86041800
D50: コンテナ | E50: 19000 | F50: 14409 | G50: 1 | I50: =E50*F50*G50 -> 273771000 | J50: コンテナ | K50: 19000 | L50: 5760 | M50: 1 | O50: =K50*L50*M50 -> 109440000 | P50: =I50+O50 -> 383211000
D51: 完調品対応 | E51: 22164 | F51: 30603 | G51: 1 | I51: =E51*F51*G51 -> 678284892 | J51: 完調品対応 | K51: 22164 | L51: 15597 | M51: 1 | N51: =L51*M51 -> 15597 | O51: =K51*L51*M51 -> 345691908 | P51: =I51+O51 -> 1023976800
B52: 飲食費（グラブアンドゴー） | C52: =C18 -> 127204000 | D52: ホテル | E52: 880 | F52: 97418 | G52: 1 | I52: =E52*F52*G52 -> 85727840 | J52: ホテル | K52: 880 | L52: 52832 | M52: 1 | N52: =L52*M52 -> 52832 | O52: =K52*L52*M52 -> 46492160 | P52: =I52+O52 -> 132220000 | Q52: =SUM(P52:P54)-C52 -> 96855440 | R52: =SUM(P52)-C52 -> 5016000
D53: コンテナ | E53: 880 | F53: 37381 | G53: 1 | I53: =E53*F53*G53 -> 32895280 | J53: コンテナ | K53: 880 | L53: 14400 | M53: 1 | N53: =L53*M53 -> 14400 | O53: =K53*L53*M53 -> 12672000 | P53: =I53+O53 -> 45567280
D54: 船 | E54: 880 | F54: 52582 | G54: 1 | I54: =E54*F54*G54 -> 46272160 | O54: =K54*L54*M54 -> 0 | P54: =I54+O54 -> 46272160
B55: 飲食費（アスリートミール：船） | C55: 920808000 | D55: 船 | E55: 21000 | F55: 52582 | G55: 1 | I55: =E55*F55*G55 -> 1104222000 | O55: =K55*L55*M55 -> 0 | P55: =I55+O55 -> 1104222000 | Q55: =SUM(P55)-C55 -> 183414000
B56: 飲食費（空港島運営及びガーデンふ頭運営及び仮設厨房） | C56: =C22 -> 1437358140 | D56: 空港島運営経費 | E56: 1336000000 | F56: 1 | G56: 1 | I56: =E56*F56*G56 -> 1336000000 | P56: =I56+O56 -> 1336000000 | Q56: =SUM(P56:P59)-C56 -> 974000860 | R56: =SUM(P56:P57)-C56 -> 860
D57: 空港島仮設厨房経費 | E57: 101359000 | F57: 1 | G57: 1 | I57: =E57*F57*G57 -> 101359000 | O57: =K57*L57*M57 -> 0 | P57: =I57+O57 -> 101359000
D58: ガーデン運営経費 | E58: 408277000 | F58: 1 | G58: 1 | I58: =E58*F58*G58 -> 408277000 | J58: ガーデン運営経費 | K58: 360000000 | L58: 1 | M58: 1 | O58: =K58*L58*M58 -> 360000000 | P58: =I58+O58 -> 768277000
D59: ガーデン仮設厨房経費 | E59: 205723000 | F59: 1 | G59: 1 | I59: =E59*F59*G59 -> 205723000 | O59: =K59*L59*M59 -> 0 | P59: =I59+O59 -> 205723000
B60: 飲食費（その他経費（支援機器設置等）） | C60: =C26 -> 88652020 | D60: ホテル厨房機器レンタル | E60: 6000000 | F60: 12 | G60: 1 | I60: =E60*F60*G60 -> 72000000 | J60: ホテル厨房機器レンタル | K60: 2379000 | L60: 7 | M60: 1 | O60: =K60*L60*M60 -> 16653000 | P60: =I60+O60 -> 88653000 | Q60: =SUM(P60:P61,P62)-C60 -> 10458980 | R60: =SUM(P60)-C60 -> 980
D61: シップグラブ＆ゴー設備レンタル | E61: 9351000 | F61: 1 | G61: 1 | I61: =E61*F61*G61 -> 9351000 | P61: =I61+O61 -> 9351000
D62: シップグラブ＆ゴー備品レンタル | E62: 1107000 | F62: 1 | G62: 1 | I62: =E62*F62*G62 -> 1107000 | P62: =I62+O62 -> 1107000
B63: 会議室等確保費 | C63: =C27 -> 3450377147 | D63: ホテル（選手団） | E63: ='財政見通し積算 (全SH全項目統合版）'!D26 -> #REF! | F63: 1 | G63: 1 | I63: =E63*F63*G63 -> #REF! | J63: ホテル（選手団） | K63: ='財政見通し積算 (全SH全項目統合版）'!D31 -> #REF! | L63: 1 | M63: 1 | O63: =K63*L63*M63 -> #REF! | P63: =I63+O63 -> #REF! | Q63: =SUM(P63:P64)-C63 -> #REF! | R63: =SUM(P63:P64)-C63 -> #REF!
D64: ホテル（選手団以外） | I64: =SUM(I65:I66) -> 1.8941956e+09 | J64: ホテル（選手団以外） | O64: =SUM(O65:O66) -> 6.5639053e+08 | P64: =SUM(P65:P66) -> 2.5505861e+09
D65: （ファミリー） | E65: ='財政見通し積算 (全SH全項目統合版）'!D27 -> 1133891586 | F65: 1 | G65: 1 | I65: =E65*F65*G65 -> 1133891586 | J65: （ファミリー） | K65: ='財政見通し積算 (全SH全項目統合版）'!D32 -> 2.886576e+08 | L65: 1 | M65: 1 | O65: =K65*L65*M65 -> 2.886576e+08 | P65: =I65+O65 -> 1422549186
D66: （技術役員） | E66: ='財政見通し積算 (全SH全項目統合版）'!D28 -> 7.6030401e+08 | F66: 1 | G66: 1 | I66: =E66*F66*G66 -> 7.6030401e+08 | J66: （技術役員） | K66: ='財政見通し積算 (全SH全項目統合版）'!D33 -> 3.6773293e+08 | L66: 1 | M66: 1 | O66: =K66*L66*M66 -> 3.6773293e+08 | P66: =I66+O66 -> 1.1280369e+09
B67: 営業補償費 | C67: =C29 -> 54466667 | D67: ホテル（一棟貸しによる補償） | I67: =SUM(I68:I69) -> #REF! | J67: ホテル（一棟貸しによる補償） | O67: =SUM(O68:O69) -> #REF! | P67: =I67+O67 -> #REF! | Q67: =SUM(P67)-C67 -> #REF! | R67: =SUM(P67,P70)-C67 -> #REF!
D68: （選手団） | E68: ='財政見通し積算 (全SH全項目統合版）'!F26 -> #REF! | F68: 1 | G68: 1 | I68: =E68*F68*G68 -> #REF! | J68: （選手団） | K68: ='財政見通し積算 (全SH全項目統合版）'!F31 -> #REF! | L68: 1 | M68: 1 | O68: =K68*L68*M68 -> #REF! | P68: =I68+O68 -> #REF!
D69: （ファミリー） | E69: ='財政見通し積算 (全SH全項目統合版）'!F27 -> 35875905 | F69: 1 | G69: 1 | I69: =E69*F69*G69 -> 35875905 | J69: （ファミリー） | K69: ='財政見通し積算 (全SH全項目統合版）'!F32 -> 792000 | L69: 1 | M69: 1 | O69: =K69*L69*M69 -> 792000 | P69: =I69+O69 -> 36667905
D70: ホテル（クリーンベニューによる補償） | I70: =SUM(I71:I72) -> #REF! | J70: ホテル（クリーンベニューによる補償） | O70: =SUM(O71:O72) -> #REF! | P70: =I70+O70 -> #REF!
D71: （選手団※自動販売機補償） | E71: ='財政見通し積算 (全SH全項目統合版）'!G26 -> #REF! | F71: 1 | G71: 1 | I71: =E71*F71*G71 -> #REF! | J71: （選手団※自動販売機補償） | K71: ='財政見通し積算 (全SH全項目統合版）'!G31 -> #REF! | L71: 1 | M71: 1 | O71: =K71*L71*M71 -> #REF! | P71: =I71+O71 -> #REF!
D72: （選手団※テナント等補償） | E72: ='財政見通し積算 (全SH全項目統合版）'!H26 -> #REF! | F72: 1 | G72: 1 | I72: =E72*F72*G72 -> #REF! | J72: （選手団※テナント等補償） | K72: ='財政見通し積算 (全SH全項目統合版）'!H31 -> #REF! | L72: 1 | M72: 1 | O72: =K72*L72*M72 -> #REF! | P72: =I72+O72 -> #REF!
B73: ランドリーサービス費 | C73: 0 | D73: ランドリーサービス費（選手団以外） | E73: ='財政見通し積算 (全SH全項目統合版）'!I39 -> 74703200 | F73: 1 | G73: 1 | I73: =E73*F73*G73 -> 74703200 | J73: ランドリーサービス費（選手団以外） | K73: ='財政見通し積算 (全SH全項目統合版）'!I40 -> 20944000 | L73: 1 | M73: 1 | O73: =K73*L73*M73 -> 20944000 | P73: =SUM(I73,O73) -> 95647200 | R73: =SUM(P73)-C73 -> 95647200
B74: 合計 | C74: =SUM(C35,C42,C49,C52,C56,C60,C63,C67,C73) -> 23477660084 | I74: =SUM(I35:I36,I42:I44,I49,I51,I52,I56:I57,I60,I63:I64,I67,I70,I73) -> #REF! | O74: =SUM(O35:O36,O42:O44,O49,O51,O52,O60,O63:O64,O67,O70,O73) -> #REF! | P74: =SUM(P35,P36,P42,P43,P44,P49,P51,P52,P56,P57,P60,P63,P64,P67,P70,P73) -> #REF! | Q74: =P74-C74 -> #REF! | R74: =SUM(I84,O84) -> #REF!
B75: ※技術役員・スポンサー・メディアのホテルについては、積算単価が2021年時点のものであるため、客室単価に1.34（宿泊料物価上昇率）を掛けている | Q75: 全体差し引き | R75: VIL移管Ver.
B76: ※技術役員の会議室費用については1.1（総合物価上昇率）を掛けている | G76: アジア差し引き | I76: =I74-I30 -> #REF! | M76: パラ差し引き | O76: =O74-O30 -> #REF!
B77: ※技術役員の昼食夕食について、延べ人数の3割に5,000円の昼食提供、10割に10,000円の夕食提供、5割に1,500円の夜食提供という前提で算出。
B78: ※クリーンベニューの営業補償については、どこまでの範囲を行うのか、どのSHを行うのか不明のため、少なくとも選手村として運用するホテルの全てのテナントに対して行う想定で算出。
B79: ※自動販売機の補償については、1台5,000円の換算で、各施設2フロアにつき1台がある想定で仮置きし算出
B80: ※テナント営業補償について、レストランやコンビニ、ゴルフ場など補償額が高そうなものが多くあるため各施設1,800,000円/日にて計算（ヒルトンしか参照単価がないためこの金額を参考）
B81: ➡なお、500,000円/日だとしても1,200,000,000円程度になる計算。
B82: ※ファミリーのランドリーサービス費については、昨年度要求時、財政見通し時にアジア86,508千円、パラ22,496千円にて積算するも予算要求資料には記載せず。ただし来年度の支払で必要になるため今回の予算要求時には積算
G84: アジア差し引き | I84: =I74-I30 -> #REF! | M84: パラ差し引き | O84: =O74-O30 -> #REF!
G85: うち ACM積算分差し引き | I85: =SUM(I35,I36,I43,I44,I63,I64,I67,I70,I73)-SUM(I3,I4,I11,I27,I28,I29) -> #REF! | M85: うち ACM積算分差し引き | O85: =SUM(O35,O36,O43,O44,O63,O64,O67,O70,O73)-SUM(O3,O4,O11,O27,O28,O29) -> #REF! | Q85: 歳入減 | R85: 歳入減
G86: うち FNB積算分差し引き（ACM積算分） | I86: =SUM(I42,I49,I51,I52,I56,I57,I60)-SUM(I10,I16,I18,I22,I23,I26) -> 286654292 | M86: うち FNB積算分差し引き（ACM積算分） | O86: =SUM(O42,O49,O51,O52,O60)-SUM(O10,O16,O18,O26) -> 233073848 | Q86: =SUM(I88,O88) -> -1.4162805e+09 | R86: =SUM(I88,O88) -> -1.4162805e+09
G87: うち FNB積算分差し引き（VIL移管分） | I87: =SUM(I48,I50,I53,I54,I55,I58,I59,I61,I62)-SUM(I14,I17,I19,I20,I21,I24,I25) -> 729631840 | M87: うち FNB積算分差し引き（VIL移管分） | O87: =SUM(O48,O50,O53,O55,O58)-SUM(O14,O15,O17,O19,O24) -> 50094200
G88: 利用者負担（歳入）差し引き | I88: =SUM(I38,I40,I41,I46)-SUM(I6,I8,I9,I13) -> -1.21148e+09 | M88: 利用者負担（歳入）差し引き | O88: =SUM(O38,O40,O41,O46)-SUM(O6,O8,O9,O13) -> -2.0480043e+08 | Q88: 実質全体差し引き | R88: 実質全体差し引き
G89: 参考 利用者負担を除いた場合の差し引き | I89: =SUM(I35,I37,I39,I42:I43,I45,I49,I51,I52,I56:I57,I60,I63:I64,I67,I73)-SUM(I3,I5,I7,I10,I12,I16,I18,I22:I23,I26,I27:I28,I29) -> #REF! | M89: 参考 利用者負担を除いた場合の差し引き | O89: =SUM(O35,O37,O39,O42:O43,O45,,O49,O51,O52,O60,O63:O64,O67,O73)-SUM(O3,O5,O7,O10,O12,O16,O18,O26,O27:O28,O29) -> #REF! | Q89: =I89+O89 -> #REF! | R89: =R74-R86 -> #REF!
B91: 現状積算外の費用 | D91: アジア | H91: 一旦計算（非表示） | J91: パラ | N91: 一旦計算（非表示）
D92: 項目 | E92: 単価 | F92: 人数 | G92: 泊数 | I92: 小計 | J92: 項目 | K92: 単価 | L92: 人数 | M92: 泊数 | O92: 小計
B93: 飲食費（昼食及び夕食） | D93: ホテル（選手団以外） （技術役員） | E93: ='財政見通し積算 (全SH全項目統合版）'!E28 -> 726706750 | F93: 1 | G93: 1 | I93: =E93*F93*G93 -> 726706750 | J93: ホテル（選手団以外） （技術役員） | K93: ='財政見通し積算 (全SH全項目統合版）'!E33 -> 195448750 | L93: 1 | M93: 1 | O93: =K93*L93*M93 -> 195448750 | P93: =I93+O93 -> 922155500
B94: 営業補償費 | D94: ホテル （クリーンベニュー自販機） | E94: ='財政見通し積算 (全SH全項目統合版）'!G26 -> #REF! | F94: 1 | G94: 1 | I94: =E94*F94*G94 -> #REF! | J94: ホテル （クリーンベニュー自販機） | K94: ='財政見通し積算 (全SH全項目統合版）'!G31 -> #REF! | L94: 1 | M94: 1 | O94: =K94*L94*M94 -> #REF! | P94: =I94+O94 -> #REF!
D95: ホテル （クリーンベニューテナント） | E95: ='財政見通し積算 (全SH全項目統合版）'!H26 -> #REF! | F95: 1 | G95: 1 | I95: =E95*F95*G95 -> #REF! | J95: ホテル （クリーンベニューテナント） | K95: ='財政見通し積算 (全SH全項目統合版）'!H31 -> #REF! | L95: 1 | M95: 1 | O95: =K95*L95*M95 -> #REF! | P95: =I95+O95 -> #REF!
B96: ※技術役員の昼食夕食については、参照できる単価がないためアスリートミールの単価（通常：16,900円 ハラル19,000円）を参照
B97: ※技術役員の昼食夕食について、延べ人数の3割に5,000円の昼食提供、10割に10,000円の夕食提供、5割に1,500円の夜食提供という前提で算出。
B98: ※クリーンベニューの営業補償については、どこまでの範囲を行うのか、どのSHを行うのか不明のため、少なくとも選手村として運用するホテルの全てのテナントに対して行う想定で算出。
B99: ※自動販売機の補償については、1台5,000円の換算で、各施設2フロアにつき1台がある想定で仮置きし算出
B100: ※テナント営業補償について、レストランやコンビニ、ゴルフ場など補償額が高そうなものが多くあるため各施設1,800,000円/日にて計算（ヒルトンしか参照単価がないためこの金額を参考）
B101: ➡なお、500,000円/日だとしても1,200,000,000円程度になる計算。
G102: 選手団ホテルにかかっている総費用（会議室費用およびサポート含む、グラブアンドゴーおよび営業補償除く） | I102: =SUM(I35,I42,I43,I49,I51,I60,I63,I56,I57) -> #REF! | M102: 選手団ホテルにかかっている総費用（会議室費用およびサポート含む、グラブアンドゴーおよび営業補償除く） | O102: =SUM(O35,O42,O43,O49,O51,O60,O63) -> #REF!
G103: 選手団のべ人数 | I103: =【251001】アジア選手積算!#REF! -> #REF! | M103: 選手団のべ人数 | O103: =【251001】パラ選手積算!#REF! -> #REF!
G104: 選手ホテルで1人あたりにかかっている費用 | I104: =I102/I103 -> #REF! | M104: 選手ホテルで1人あたりにかかっている費用 | O104: =O102/O103 -> #REF!
...

Sheet 食事単価の考え方
B2: 客室単価＋通常朝食と、アスリートミールの財政見通し上の関係性とこれまでの経緯
B3: 例：客室単価9,000円（税込）＋通常朝食1,500円（税込）の場合
B4: ※ハラルヴィーガン単価については別軸
B6: 基本
C7: 客室単価 | E7: 朝食
C10: 9000円 | E10: 1,500円
B12: 財政見通し時（24年10月）
C13: 客室単価 | E13: 朝食 | F13: アスリートミール単価
F14: 朝食4,100円 | H14: 昼食7,400円 | I14: 夕食9,500円
C16: 9000円 | E16: 1,500円 | H16: 21,000円
B18: 査定
C19: 客室単価 | E19: 朝食 | F19: アスリートミール単価
F20: 二重計上という | H20: 昼食7,400円 | I20: 夕食9,500円
F21: ことで切られる
C22: 9000円 | E22: 1,500円 | H22: 16,900円
B25: 昨年度の立てつけ（現実的には破綻）
C27: 客室単価 | D27: アスリートミール単価
D28: 差額の | E28: 通常朝食 | H28: 昼食7,400円 | I28: 夕食9,500円
D29: 2,600円 | E29: 1,500円
C30: 9,000円-2,600円？？ | D30: 4,100円 | H30: 16,900円
C32: ※ホテルへは、【アスリートミール対応朝食と通常朝食の差額】＋【アスリートミール対応昼食】＋【アスリートミール対応夕食】で16,900円程度で案内
C33: ※反応としては、この金額では対応は出来ないと言われている状況。
B35: 今回
C36: 客室単価 | E36: アスリートミール単価
E37: 通常朝食 | F37: 差額の | H37: 昼食7,400円 | I37: 夕食9,500円
E38: 1,500円 | F38: 2,600円
C39: 9,000円 | E39: 4,100円 | H39: 16,900円

Sheet 債務負担行為積算  (全部盛り) 
A1: 債務負担行為（キャンセル期限前の契約金額ベース）
A2: 宿泊料 | G2: 案3 | K2: ※財政見通しver（キャンセル期限後に実際に支払う金額ベース）
B3: ステークホルダー | C3: 1室あたりの 平均単価 | D3: 室数 ※シミュレーションの客室数 | E3: 契約泊数 | F3: 金額 物価上昇前 （G、H列固定値） | G3: 物価上昇率（宿泊） 2021➡2026 | H3: 金額 物価上昇後 （G、H列固定値） | I3: 総 計 | K3: 【参考値】 金額 物価上昇前 （シミュレーション） | L3: 【参考値】 金額 物価上昇後 （シミュレーション）
A4: アジア | B4: 選手団15,000 | C4: =IF(COUNTIF(Results【技術役員スポンサーメディア積算】!C:C, "選手15000")=0, 0, SUMIF(Results【技術役員スポンサーメディア積算】!C:C, "選手15000", Results【技術役員スポンサーメディア積算】!AA:AA) / COUNTIF(Results【技術役員スポンサーメディア積算】!C:C, "選手15000")) -> 0 | D4: 11937 | E4: 32 | F4: =$E$4*$C$4*$D$4 -> 0 | G4: ='物価（案3）'!$I$10 -> 1.34 | H4: =ROUNDUP($C4*$D4*$E4*$G4,0) -> 0 | I4: =H4 -> 0 | K4: =Results【技術役員スポンサーメディア積算】!BC283 -> 1720770931 | L4: =$K4*$G4 -> 2.305833e+09
B5: 選手団12,000 | C5: =IF(COUNTIF(Results【技術役員スポンサーメディア積算】!D:D, "選手12000")=0, 0, SUMIF(Results【技術役員スポンサーメディア積算】!D:D, "選手12000", Results【技術役員スポンサーメディア積算】!AA:AA) / COUNTIF(Results【技術役員スポンサーメディア積算】!D:D, "選手12000")) -> 0 | D5: 9962 | E5: 32 | F5: =E5*C5*D5 -> 0 | G5: ='物価（案3）'!$I$10 -> 1.34 | H5: =ROUNDUP($C5*$D5*$E5*$G5,0) -> 0 | I5: =H5 -> 0 | J5: 不要？ | K5: =Results【技術役員スポンサーメディア積算】!#REF! -> #REF! | L5: =$K5*$G5 -> #REF!
B6: ファミリー | C6: {=IF(SUMPRODUCT(--(Results【技術役員スポンサーメディア積算】!C:C="ファミリー") + --(Results【技術役員スポンサーメディア積算】!D:D="ファミリー"))=0, 0, SUMIFS(Results【技術役員スポンサーメディア積算】!AA:AA, Results【技術役員スポンサーメディア積算】!C:C, "ファミリー") + SUMIFS(Results【技術役員スポンサーメディア積算】!AA:AA, Results【技術役員スポンサーメディア積算】!D:D, "ファミリー") / SUMPRODUCT(--(Results【技術役員スポンサーメディア積算】!C:C="ファミリー") + --(Results【技術役員スポンサーメディア積算】!D:D="ファミリー")))} -> 0 | D6: 1645 | E6: 32 | F6: =E6*C6*D6 -> 0 | G6: ='物価（案3）'!$I$10 -> 1.34 | H6: =ROUNDUP($C6*$D6*$E6*$G6,0) -> 0 | I6: =SUM(H6:H11) -> 10511814540 | K6: =Results【技術役員スポンサーメディア積算】!BD283 -> 959319162 | L6: =$K6*$G6 -> 1.2854877e+09
B7: スポンサー | C7: {=IF(SUMPRODUCT(--(Results【技術役員スポンサーメディア積算】!C:C="スポンサー") + --(Results【技術役員スポンサーメディア積算】!D:D="スポンサー"))=0, 0, (SUMIFS(Results【技術役員スポンサーメディア積算】!AA:AA, Results【技術役員スポンサーメディア積算】!C:C, "スポンサー") + SUMIFS(Results【技術役員スポンサーメディア積算】!AA:AA, Results【技術役員スポンサーメディア積算】!D:D, "スポンサー")) / SUMPRODUCT(--(Results【技術役員スポンサーメディア積算】!C:C="スポンサー") + --(Results【技術役員スポンサーメディア積算】!D:D="スポンサー")))} -> 60684.639 | D7: 2560 | E7: 32 | F7: =E7*C7*D7 -> 4.9712856e+09 | G7: ='物価（案3）'!$I$10 -> 1.34 | H7: =ROUNDUP($C7*$D7*$E7*$G7,0) -> 6661522704 | K7: =Results【技術役員スポンサーメディア積算】!#REF! -> #REF! | L7: =$K7*$G7 -> #REF!
B8: NOC本部 | C8: {=IF(SUMPRODUCT(--(Results【技術役員スポンサーメディア積算】!C:C="本部") + --(Results【技術役員スポンサーメディア積算】!D:D="本部"))=0, 0, (SUMIFS(Results【技術役員スポンサーメディア積算】!AA:AA, Results【技術役員スポンサーメディア積算】!C:C, "本部") + SUMIFS(Results【技術役員スポンサーメディア積算】!AA:AA, Results【技術役員スポンサーメディア積算】!D:D, "本部")) / SUMPRODUCT(--(Results【技術役員スポンサーメディア積算】!C:C="本部") + --(Results【技術役員スポンサーメディア積算】!D:D="本部")))} -> 0 | D8: 286 | E8: 36 | F8: =E8*C8*D8 -> 0 | G8: ='物価（案3）'!$I$10 -> 1.34 | H8: =ROUNDUP($C8*$D8*$E8*$G8,0) -> 0 | K8: =Results【技術役員スポンサーメディア積算】!#REF! -> #REF! | L8: =$K8*$G8 -> #REF!
B9: メディア | C9: {=IF(SUMPRODUCT(--(Results【技術役員スポンサーメディア積算】!C:C="メディア") + --(Results【技術役員スポンサーメディア積算】!D:D="メディア"))=0, 0, (SUMIFS(Results【技術役員スポンサーメディア積算】!AA:AA, Results【技術役員スポンサーメディア積算】!C:C, "メディア") + SUMIFS(Results【技術役員スポンサーメディア積算】!AA:AA, Results【技術役員スポンサーメディア積算】!D:D, "メディア")) / SUMPRODUCT(--(Results【技術役員スポンサーメディア積算】!C:C="メディア") + --(Results【技術役員スポンサーメディア積算】!D:D="メディア")))} -> 0 | D9: 3000 | E9: 32 | F9: =E9*C9*D9 -> 0 | G9: ='物価（案3）'!$I$10 -> 1.34 | H9: =ROUNDUP($C9*$D9*$E9*$G9,0) -> 0 | K9: =Results【技術役員スポンサーメディア積算】!BE283 -> 1980375600 | L9: =$K9*$G9 -> 2653703304
B10: 技術役員（競技役員） | C10: {=IF(SUMPRODUCT(--(Results【技術役員スポンサーメディア積算】!C:C="技術役員") + --(Results【技術役員スポンサーメディア積算】!D:D="技術役員"))=0, 0, (SUMIFS(Results【技術役員スポンサーメディア積算】!AA:AA, Results【技術役員スポンサーメディア積算】!C:C, "技術役員") + SUMIFS(Results【技術役員スポンサーメディア積算】!AA:AA, Results【技術役員スポンサーメディア積算】!D:D, "技術役員")) / SUMPRODUCT(--(Results【技術役員スポンサーメディア積算】!C:C="技術役員") + --(Results【技術役員スポンサーメディア積算】!D:D="技術役員")))} -> 26771.692 | D10: 3354 | E10: 32 | F10: =E10*C10*D10 -> 2.8733521e+09 | G10: ='物価（案3）'!$I$10 -> 1.34 | H10: =ROUNDUP($C10*$D10*$E10*$G10,0) -> 3850291836 | K10: =Results【技術役員スポンサーメディア積算】!#REF! -> #REF! | L10: =$K10*$G10 -> #REF!
B11: 技術役員（DCO) | C11: {=IF(SUMPRODUCT(--(Results【技術役員スポンサーメディア積算】!C:C="DCO") + --(Results【技術役員スポンサーメディア積算】!D:D="DCO") + --(Results【技術役員スポンサーメディア積算】!E:E="DCO"))=0, 0, (SUMIFS(Results【技術役員スポンサーメディア積算】!AA:AA, Results【技術役員スポンサーメディア積算】!C:C, "DCO") + SUMIFS(Results【技術役員スポンサーメディア積算】!AA:AA, Results【技術役員スポンサーメディア積算】!D:D, "DCO") + SUMIFS(Results【技術役員スポンサーメディア積算】!AA:AA, Results【技術役員スポンサーメディア積算】!E:E, "DCO")) / SUMPRODUCT(--(Results【技術役員スポンサーメディア積算】!C:C="DCO") + --(Results【技術役員スポンサーメディア積算】!D:D="DCO") + --(Results【技術役員スポンサーメディア積算】!E:E="DCO")))} -> 0 | D11: 504 | E11: 32 | F11: =E11*C11*D11 -> 0 | G11: ='物価（案3）'!$I$10 -> 1.34 | H11: =ROUNDUP($C11*$D11*$E11*$G11,0) -> 0 | K11: =Results【技術役員スポンサーメディア積算】!#REF! -> #REF! | L11: =$K11*$G11 -> #REF!
A12: パラ | B12: 選手団4,000 | C12: {=IF(SUMPRODUCT(--(Results【技術役員スポンサーメディア積算】!F:F="選手") + --(Results【技術役員スポンサーメディア積算】!G:G="選手"))=0, 0, (SUMIFS(Results【技術役員スポンサーメディア積算】!AA:AA, Results【技術役員スポンサーメディア積算】!F:F, "選手") + SUMIFS(Results【技術役員スポンサーメディア積算】!AA:AA, Results【技術役員スポンサーメディア積算】!G:G, "選手")) / SUMPRODUCT(--(Results【技術役員スポンサーメディア積算】!F:F="選手") + --(Results【技術役員スポンサーメディア積算】!G:G="選手")))} -> 0 | D12: 4988 | E12: 18 | F12: =E12*C12*D12 -> 0 | G12: ='物価（案3）'!$I$10 -> 1.34 | H12: =ROUNDUP($C12*$D12*$E12*$G12,0) -> 0 | I12: =H12 -> 0 | K12: =Results【技術役員スポンサーメディア積算】!BF283 -> 344907436 | L12: =$K12*$G12 -> 4.6217596e+08
B13: 選手団3,600 | C13: {=IF(SUMPRODUCT(--(Results【技術役員スポンサーメディア積算】!F:F="選手") + --(Results【技術役員スポンサーメディア積算】!G:G="選手"))=0, 0, (SUMIFS(Results【技術役員スポンサーメディア積算】!AA:AA, Results【技術役員スポンサーメディア積算】!F:F, "選手") + SUMIFS(Results【技術役員スポンサーメディア積算】!AA:AA, Results【技術役員スポンサーメディア積算】!G:G, "選手")) / SUMPRODUCT(--(Results【技術役員スポンサーメディア積算】!F:F="選手") + --(Results【技術役員スポンサーメディア積算】!G:G="選手")))} -> 0 | D13: 4988 | E13: 18 | F13: =E13*C13*D13 -> 0 | G13: ='物価（案3）'!$I$10 -> 1.34 | H13: =ROUNDUP($C13*$D13*$E13*$G13,0) -> 0 | I13: =H13 -> 0 | J13: 不要？ | K13: =Results【技術役員スポンサーメディア積算】!BG283 -> 624655701 | L13: =$K13*$G13 -> 8.3703864e+08
B14: ファミリー | C14: {=IF(SUMPRODUCT(--(Results【技術役員スポンサーメディア積算】!F:F="ファミリー") + --(Results【技術役員スポンサーメディア積算】!G:G="ファミリー"))=0, 0, (SUMIFS(Results【技術役員スポンサーメディア積算】!AA:AA, Results【技術役員スポンサーメディア積算】!F:F, "ファミリー") + SUMIFS(Results【技術役員スポンサーメディア積算】!AA:AA, Results【技術役員スポンサーメディア積算】!G:G, "ファミリー")) / SUMPRODUCT(--(Results【技術役員スポンサーメディア積算】!F:F="ファミリー") + --(Results【技術役員スポンサーメディア積算】!G:G="ファミリー")))} -> 0 | D14: 370 | E14: 18 | F14: =E14*C14*D14 -> 0 | G14: ='物価（案3）'!$I$10 -> 1.34 | H14: =ROUNDUP($C14*$D14*$E14*$G14,0) -> 0 | I14: =SUM(H14:H19) -> 2457049000 | K14: =Results【技術役員スポンサーメディア積算】!BH283 -> 300216120 | L14: =$K14*$G14 -> 4.022896e+08
B15: スポンサー | C15: {=IF(SUMPRODUCT(--(Results【技術役員スポンサーメディア積算】!F:F="スポンサー") + --(Results【技術役員スポンサーメディア積算】!G:G="スポンサー"))=0, 0, (SUMIFS(Results【技術役員スポンサーメディア積算】!AA:AA, Results【技術役員スポンサーメディア積算】!F:F, "スポンサー") + SUMIFS(Results【技術役員スポンサーメディア積算】!AA:AA, Results【技術役員スポンサーメディア積算】!G:G, "スポンサー")) / SUMPRODUCT(--(Results【技術役員スポンサーメディア積算】!F:F="スポンサー") + --(Results【技術役員スポンサーメディア積算】!G:G="スポンサー")))} -> 53371.432 | D15: 1560 | E15: 18 | F15: =E15*C15*D15 -> 1.4986698e+09 | G15: ='物価（案3）'!$I$10 -> 1.34 | H15: =ROUNDUP($C15*$D15*$E15*$G15,0) -> 2008217561 | K15: =Results【技術役員スポンサーメディア積算】!#REF! -> #REF! | L15: =$K15*$G15 -> #REF!
B16: NPC本部 | C16: {=IF(SUMPRODUCT(--(Results【技術役員スポンサーメディア積算】!F:F="本部") + --(Results【技術役員スポンサーメディア積算】!G:G="本部"))=0, 0, (SUMIFS(Results【技術役員スポンサーメディア積算】!AA:AA, Results【技術役員スポンサーメディア積算】!F:F, "本部") + SUMIFS(Results【技術役員スポンサーメディア積算】!AA:AA, Results【技術役員スポンサーメディア積算】!G:G, "本部")) / SUMPRODUCT(--(Results【技術役員スポンサーメディア積算】!F:F="本部") + --(Results【技術役員スポンサーメディア積算】!G:G="本部")))} -> 0 | D16: 116 | E16: 19 | F16: =E16*C16*D16 -> 0 | G16: ='物価（案3）'!$I$10 -> 1.34 | H16: =ROUNDUP($C16*$D16*$E16*$G16,0) -> 0 | K16: =Results【技術役員スポンサーメディア積算】!#REF! -> #REF! | L16: =$K16*$G16 -> #REF!
B17: メディア | C17: {=IF(SUMPRODUCT(--(Results【技術役員スポンサーメディア積算】!F:F="メディア") + --(Results【技術役員スポンサーメディア積算】!G:G="メディア"))=0, 0, (SUMIFS(Results【技術役員スポンサーメディア積算】!AA:AA, Results【技術役員スポンサーメディア積算】!F:F, "メディア") + SUMIFS(Results【技術役員スポンサーメディア積算】!AA:AA, Results【技術役員スポンサーメディア積算】!G:G, "メディア")) / SUMPRODUCT(--(Results【技術役員スポンサーメディア積算】!F:F="メディア") + --(Results【技術役員スポンサーメディア積算】!G:G="メディア")))} -> 0 | D17: 1600 | E17: 18 | F17: =E17*C17*D17 -> 0 | G17: ='物価（案3）'!$I$10 -> 1.34 | H17: =ROUNDUP($C17*$D17*$E17*$G17,0) -> 0 | K17: =Results【技術役員スポンサーメディア積算】!#REF! -> #REF! | L17: =$K17*$G17 -> #REF!
B18: 技術役員（競技役員） | C18: {=IF(SUMPRODUCT(--(Results【技術役員スポンサーメディア積算】!F:F="技術役員") + --(Results【技術役員スポンサーメディア積算】!G:G="技術役員"))=0, 0, (SUMIFS(Results【技術役員スポンサーメディア積算】!AA:AA, Results【技術役員スポンサーメディア積算】!F:F, "技術役員") + SUMIFS(Results【技術役員スポンサーメディア積算】!AA:AA, Results【技術役員スポンサーメディア積算】!G:G, "技術役員")) / SUMPRODUCT(--(Results【技術役員スポンサーメディア積算】!F:F="技術役員") + --(Results【技術役員スポンサーメディア積算】!G:G="技術役員")))} -> 22916.587 | D18: 812 | E18: 18 | F18: =E18*C18*D18 -> 3.3494884e+08 | G18: ='物価（案3）'!$I$10 -> 1.34 | H18: =ROUNDUP($C18*$D18*$E18*$G18,0) -> 448831439 | K18: =Results【技術役員スポンサーメディア積算】!#REF! -> #REF! | L18: =$K18*$G18 -> #REF!
B19: 技術役員（DCO) | C19: {=IF(SUMPRODUCT(--(Results【技術役員スポンサーメディア積算】!F:F="DCO") + --(Results【技術役員スポンサーメディア積算】!G:G="DCO"))=0, 0, (SUMIFS(Results【技術役員スポンサーメディア積算】!AA:AA, Results【技術役員スポンサーメディア積算】!F:F, "DCO") + SUMIFS(Results【技術役員スポンサーメディア積算】!AA:AA, Results【技術役員スポンサーメディア積算】!G:G, "DCO")) / SUMPRODUCT(--(Results【技術役員スポンサーメディア積算】!F:F="DCO") + --(Results【技術役員スポンサーメディア積算】!G:G="DCO")))} -> 0 | D19: 122 | E19: 18 | F19: =E19*C19*D19 -> 0 | G19: ='物価（案3）'!$I$10 -> 1.34 | H19: =ROUNDUP($C19*$D19*$E19*$G19,0) -> 0 | K19: =Results【技術役員スポンサーメディア積算】!#REF! -> #REF! | L19: =$K19*$G19 -> #REF!
A20: 合計 | B20: - | C20: - | D20: - | E20: - | F20: =SUBTOTAL(109,F4:F19) -> 9.6782564e+09 | G20: - | H20: =SUBTOTAL(109,H4:H19) -> 12968863540 | I20: =SUBTOTAL(109,I4:I19) -> 12968863540 | K20: =SUBTOTAL(109,K4:K19) -> #REF! | L20: =SUBTOTAL(109,L4:L19) -> #REF!
A22: FR料
B23: ステークホルダー | C23: 1室あたりの 平均単価 | D23: 部屋数 ※施設保有FR数 | E23: 契約日数 | F23: 金額 物価上昇前 （G、H列固定値） | G23: 物価上昇率（宿泊） 2021➡2026 | H23: 金額 物価上昇後 （G、H列固定値） | I23: 総 計 | K23: 【参考値】 金額 物価上昇前 （シミュレーション） | L23: 【参考値】 金額 物価上昇後 （シミュレーション）
A24: アジア | B24: 選手団 | C24: =IF(COUNTIFS(Results【技術役員スポンサーメディア積算】!C:C, "選手15000", Results【技術役員スポンサーメディア積算】!V:V, ">0")=0, 0, SUMIFS(Results【技術役員スポンサーメディア積算】!V:V, Results【技術役員スポンサーメディア積算】!C:C, "選手15000", Results【技術役員スポンサーメディア積算】!V:V, ">0") / COUNTIFS(Results【技術役員スポンサーメディア積算】!C:C, "選手15000", Results【技術役員スポンサーメディア積算】!V:V, ">0")) -> 0 | D24: =IF(COUNTIF(Results【技術役員スポンサーメディア積算】!C:C, "選手15000")=0, 0, SUMIF(Results【技術役員スポンサーメディア積算】!C:C, "選手15000", Results【技術役員スポンサーメディア積算】!I:I)) -> 0 | E24: =$E4+1 -> 33 | F24: =E24*C24*D24 -> 0 | G24: ='物価（案3）'!$I$10 -> 1.34 | H24: =ROUNDUP($C24*$D24*$E24*$G24,0) -> 0 | I24: =H24 -> 0 | K24: =Results【技術役員スポンサーメディア積算】!BI283 -> 691185467 | L24: =$K24*$G24 -> 9.2618853e+08
B25: ファミリー | C25: =IF(COUNTIFS(Results【技術役員スポンサーメディア積算】!D:D, "ファミリー", Results【技術役員スポンサーメディア積算】!V:V, ">0")=0, 0, SUMIFS(Results【技術役員スポンサーメディア積算】!V:V, Results【技術役員スポンサーメディア積算】!D:D, "ファミリー", Results【技術役員スポンサーメディア積算】!V:V, ">0") / COUNTIFS(Results【技術役員スポンサーメディア積算】!D:D, "ファミリー", Results【技術役員スポンサーメディア積算】!V:V, ">0")) -> 0 | D25: =IF(COUNTIF(Results【技術役員スポンサーメディア積算】!D:D, "ファミリー")=0, 0, SUMIF(Results【技術役員スポンサーメディア積算】!D:D, "ファミリー", Results【技術役員スポンサーメディア積算】!I:I)) -> 0 | E25: =$E6+1 -> 33 | F25: =E25*C25*D25 -> 0 | G25: ='物価（案3）'!$I$10 -> 1.34 | H25: =ROUNDUP($C25*$D25*$E25*$G25,0) -> 0 | I25: =SUM(H25:H27) -> 0 | K25: =Results【技術役員スポンサーメディア積算】!BJ283 -> 1898926146 | L25: =$K25*$G25 -> 2.544561e+09
B26: スポンサー | G26: ='物価（案3）'!$I$10 -> 1.34 | H26: =ROUNDUP($C26*$D26*$E26*$G26,0) -> 0 | L26: =$K26*$G26 -> 0
B27: NOC本部 | C27: {=IF(SUMPRODUCT(--(Results【技術役員スポンサーメディア積算】!C:C="本部") + --(Results【技術役員スポンサーメディア積算】!D:D="本部"))=0, 0, (SUMIFS(Results【技術役員スポンサーメディア積算】!V:V, Results【技術役員スポンサーメディア積算】!C:C, "本部") + SUMIFS(Results【技術役員スポンサーメディア積算】!V:V, Results【技術役員スポンサーメディア積算】!D:D, "本部")) / SUMPRODUCT(--(Results【技術役員スポンサーメディア積算】!C:C="本部") + --(Results【技術役員スポンサーメディア積算】!D:D="本部")))} -> 0 | D27: =IF(AND(COUNTIF(Results【技術役員スポンサーメディア積算】!C:C, "本部")=0, COUNTIF(Results【技術役員スポンサーメディア積算】!D:D, "本部")=0), 0, IFERROR(SUMIF(Results【技術役員スポンサーメディア積算】!C:C, "本部", Results【技術役員スポンサーメディア積算】!I:I), 0) + IFERROR(SUMIF(Results【技術役員スポンサーメディア積算】!D:D, "本部", Results【技術役員スポンサーメディア積算】!I:I), 0)) -> 0 | E27: =$E8+1 -> 37 | F27: =E27*C27*D27 -> 0 | G27: ='物価（案3）'!$I$10 -> 1.34 | H27: =ROUNDUP($C27*$D27*$E27*$G27,0) -> 0 | K27: =Results【技術役員スポンサーメディア積算】!BK283 -> 87385650 | L27: =$K27*$G27 -> 117096771
A28: パラ | B28: 選手団 | C28: =IF(COUNTIFS(Results【技術役員スポンサーメディア積算】!F:F, "選手", Results【技術役員スポンサーメディア積算】!V:V, ">0")=0, 0, SUMIFS(Results【技術役員スポンサーメディア積算】!V:V, Results【技術役員スポンサーメディア積算】!F:F, "選手", Results【技術役員スポンサーメディア積算】!V:V, ">0") / COUNTIFS(Results【技術役員スポンサーメディア積算】!F:F, "選手", Results【技術役員スポンサーメディア積算】!V:V, ">0")) -> 0 | D28: =IF(COUNTIF(Results【技術役員スポンサーメディア積算】!F:F, "選手")=0, 0, IFERROR(SUMIF(Results【技術役員スポンサーメディア積算】!F:F, "選手", Results【技術役員スポンサーメディア積算】!I:I), 0)) -> 0 | E28: =$E12+1 -> 19 | F28: =E28*C28*D28 -> 0 | G28: ='物価（案3）'!$I$10 -> 1.34 | H28: =ROUNDUP($C28*$D28*$E28*$G28,0) -> 0 | I28: =H28 -> 0 | K28: =Results【技術役員スポンサーメディア積算】!BL283 -> 321313565 | L28: =$K28*$G28 -> 4.3056018e+08
B29: ファミリー | C29: {=IF(SUMPRODUCT(--(Results【技術役員スポンサーメディア積算】!F:F="ファミリー") + --(Results【技術役員スポンサーメディア積算】!G:G="ファミリー"))=0, 0, (SUMIFS(Results【技術役員スポンサーメディア積算】!V:V, Results【技術役員スポンサーメディア積算】!F:F, "ファミリー") + SUMIFS(Results【技術役員スポンサーメディア積算】!V:V, Results【技術役員スポンサーメディア積算】!G:G, "ファミリー")) / SUMPRODUCT(--(Results【技術役員スポンサーメディア積算】!F:F="ファミリー") + --(Results【技術役員スポンサーメディア積算】!G:G="ファミリー")))} -> 0 | D29: =IF(COUNTIF(Results【技術役員スポンサーメディア積算】!F:F, "ファミリー")=0, 0, IFERROR(SUMIF(Results【技術役員スポンサーメディア積算】!F:F, "ファミリー", Results【技術役員スポンサーメディア積算】!I:I), 0)) -> 0 | E29: =$E14+1 -> 19 | F29: =E29*C29*D29 -> 0 | G29: ='物価（案3）'!$I$10 -> 1.34 | H29: =ROUNDUP($C29*$D29*$E29*$G29,0) -> 0 | I29: =SUM(H29:H30) -> 0 | K29: =Results【技術役員スポンサーメディア積算】!BN283 -> 0 | L29: =$K29*$G29 -> 0
B30: NPC本部 | C30: {=IF(SUMPRODUCT(--(Results【技術役員スポンサーメディア積算】!F:F="本部") + --(Results【技術役員スポンサーメディア積算】!G:G="本部"))=0, 0, (SUMIFS(Results【技術役員スポンサーメディア積算】!V:V, Results【技術役員スポンサーメディア積算】!F:F, "本部") + SUMIFS(Results【技術役員スポンサーメディア積算】!V:V, Results【技術役員スポンサーメディア積算】!G:G, "本部")) / SUMPRODUCT(--(Results【技術役員スポンサーメディア積算】!F:F="本部") + --(Results【技術役員スポンサーメディア積算】!G:G="本部")))} -> 0 | D30: =IF(COUNTIF(Results【技術役員スポンサーメディア積算】!F:F, "本部")=0, 0, IFERROR(SUMIF(Results【技術役員スポンサーメディア積算】!F:F, "本部", Results【技術役員スポンサーメディア積算】!I:I), 0)) -> 0 | E30: =$E16+1 -> 20 | F30: =E30*C30*D30 -> 0 | G30: ='物価（案3）'!$I$10 -> 1.34 | H30: =ROUNDUP($C30*$D30*$E30*$G30,0) -> 0 | K30: =Results【技術役員スポンサーメディア積算】!#REF! -> #REF! | L30: =$K30*$G30 -> #REF!
A31: 合計 | B31: - | C31: - | D31: - | E31: - | F31: =SUBTOTAL(109,F24:F30) -> 0 | G31: - | H31: =SUBTOTAL(109,H24:H30) -> 0 | I31: =SUBTOTAL(109,I24:I30) -> 0 | K31: =SUBTOTAL(109,K24:K30) -> #REF! | L31: =SUBTOTAL(109,L24:L30) -> #REF!
A32: ※契約泊数及び日数についてシミュレーションが流動的であるため最大利用期間で契約見込、その後精査しキャンセル期限までにキャンセルする。
H34: 宿泊料＋FR料
H35: アジア | I35: =I4+I6+I24+I25 -> 10511814540
H36: パラ | I36: =I12+I14+I28+I29 -> 2457049000
H37: 合計 | I37: =I35+I36 -> 12968863540
A39: 【パラ本部泊数式修正】（泊数減＋パラ4,000一棟借上げ原則ヤメ）ACM財政見通（v4.3c）
A41: 宿泊料 | G41: 案3 | K41: ※財政見通しver（キャンセル期限後に実際に支払う金額ベース）
B42: ステークホルダー | C42: 1室あたりの 平均単価 | D42: 室数 ※シミュレーションの客室数 | E42: 契約泊数 | F42: 金額 物価上昇前 （G、H列固定値） | G42: 物価上昇率（宿泊） 2021➡2026 | H42: 金額 物価上昇後 （G、H列固定値） | I42: 総 計 | K42: 【参考値】 金額 物価上昇前 （シミュレーション） | L42: 【参考値】 金額 物価上昇後 （シミュレーション）
A43: アジア | B43: 選手団15,000 | C43: ='[48]債務負担行為積算 (数式)'!C4 -> 33756.68 | D43: ='[48]債務負担行為積算 (数式)'!D4 -> 11937 | E43: ='[48]債務負担行為積算 (数式)'!E4 -> 32 | F43: ='[48]債務負担行為積算 (数式)'!F4 -> 1.2894512e+10 | G43: ='[48]債務負担行為積算 (数式)'!G4 -> 1.22 | H43: ='[48]債務負担行為積算 (数式)'!H4 -> 15731304246 | I43: ='[48]債務負担行為積算 (数式)'!I4 -> 15731304246 | J43: ='[48]債務負担行為積算 (数式)'!J4 -> 0 | ... L43: ='[48]債務負担行為積算 (数式)'!L4 -> 1.0689792e+10
B44: 選手団12,000 | C44: ='[48]債務負担行為積算 (数式)'!C5 -> 35104.891 | D44: ='[48]債務負担行為積算 (数式)'!D5 -> 9962 | E44: ='[48]債務負担行為積算 (数式)'!E5 -> 32 | F44: ='[48]債務負担行為積算 (数式)'!F5 -> 1.1190878e+10 | G44: ='[48]債務負担行為積算 (数式)'!G5 -> 1.22 | H44: ='[48]債務負担行為積算 (数式)'!H5 -> 13652870698 | I44: ='[48]債務負担行為積算 (数式)'!I5 -> 13652870698 | J44: ='[48]債務負担行為積算 (数式)'!J5 -> 不要？ | ... L44: ='[48]債務負担行為積算 (数式)'!L5 -> 9.5891368e+09
B45: ファミリー | C45: ='[48]債務負担行為積算 (数式)'!C6 -> 104002.93 | D45: ='[48]債務負担行為積算 (数式)'!D6 -> 1645 | E45: ='[48]債務負担行為積算 (数式)'!E6 -> 32 | F45: ='[48]債務負担行為積算 (数式)'!F6 -> 5.4747141e+09 | G45: ='[48]債務負担行為積算 (数式)'!G6 -> 1.22 | H45: ='[48]債務負担行為積算 (数式)'!H6 -> 6679151237 | I45: ='[48]債務負担行為積算 (数式)'!I6 -> 20710310555 | J45: ='[48]債務負担行為積算 (数式)'!J6 -> 0 | ... L45: ='[48]債務負担行為積算 (数式)'!L6 -> 4.5155697e+09
B46: スポンサー | C46: ='[48]債務負担行為積算 (数式)'!C7 -> 48153.528 | D46: ='[48]債務負担行為積算 (数式)'!D7 -> 2560 | E46: ='[48]債務負担行為積算 (数式)'!E7 -> 32 | F46: ='[48]債務負担行為積算 (数式)'!F7 -> 3.944737e+09 | G46: ='[48]債務負担行為積算 (数式)'!G7 -> 1.22 | H46: ='[48]債務負担行為積算 (数式)'!H7 -> 4812579181 | J46: ='[48]債務負担行為積算 (数式)'!J7 -> 0 | K46: ='[48]債務負担行為積算 (数式)'!K7 -> 2.3857605e+09 | L46: ='[48]債務負担行為積算 (数式)'!L7 -> 2.9106278e+09
B47: NOC本部 | C47: ='[48]債務負担行為積算 (数式)'!C8 -> 67393.897 | D47: ='[48]債務負担行為積算 (数式)'!D8 -> 286 | E47: ='[48]債務負担行為積算 (数式)'!E8 -> 36 | F47: ='[48]債務負担行為積算 (数式)'!F8 -> 6.9388756e+08 | G47: ='[48]債務負担行為積算 (数式)'!G8 -> 1.22 | H47: ='[48]債務負担行為積算 (数式)'!H8 -> 846542823 | J47: ='[48]債務負担行為積算 (数式)'!J8 -> 0 | K47: ='[48]債務負担行為積算 (数式)'!K8 -> 719947332 | L47: ='[48]債務負担行為積算 (数式)'!L8 -> 8.7833575e+08
B48: メディア | C48: ='[48]債務負担行為積算 (数式)'!C9 -> 25177.548 | D48: ='[48]債務負担行為積算 (数式)'!D9 -> 3000 | E48: ='[48]債務負担行為積算 (数式)'!E9 -> 32 | F48: ='[48]債務負担行為積算 (数式)'!F9 -> 2.4170446e+09 | G48: ='[48]債務負担行為積算 (数式)'!G9 -> 1.22 | H48: ='[48]債務負担行為積算 (数式)'!H9 -> 2948794448 | J48: ='[48]債務負担行為積算 (数式)'!J9 -> 0 | K48: ='[48]債務負担行為積算 (数式)'!K9 -> 2.05575e+09 | L48: ='[48]債務負担行為積算 (数式)'!L9 -> 2.5080149e+09
B49: 技術役員（競技役員） | C49: ='[48]債務負担行為積算 (数式)'!C10 -> 34913.68 | D49: ='[48]債務負担行為積算 (数式)'!D10 -> 3354 | E49: ='[48]債務負担行為積算 (数式)'!E10 -> 32 | F49: ='[48]債務負担行為積算 (数式)'!F10 -> 3.7472155e+09 | G49: ='[48]債務負担行為積算 (数式)'!G10 -> 1.22 | H49: ='[48]債務負担行為積算 (数式)'!H10 -> 4571602860 | J49: ='[48]債務負担行為積算 (数式)'!J10 -> 0 | K49: ='[48]債務負担行為積算 (数式)'!K10 -> 1.1249505e+09 | L49: ='[48]債務負担行為積算 (数式)'!L10 -> 1.3724397e+09
B50: 技術役員（DCO) | C50: ='[48]債務負担行為積算 (数式)'!C11 -> 43282.836 | D50: ='[48]債務負担行為積算 (数式)'!D11 -> 504 | E50: ='[48]債務負担行為積算 (数式)'!E11 -> 32 | F50: ='[48]債務負担行為積算 (数式)'!F11 -> 6.9806558e+08 | G50: ='[48]債務負担行為積算 (数式)'!G11 -> 1.22 | H50: ='[48]債務負担行為積算 (数式)'!H11 -> 851640006 | J50: ='[48]債務負担行為積算 (数式)'!J11 -> 0 | K50: ='[48]債務負担行為積算 (数式)'!K11 -> 4.5768295e+08 | L50: ='[48]債務負担行為積算 (数式)'!L11 -> 5.583732e+08
A51: パラ | B51: 選手団4,000 | C51: ='[48]債務負担行為積算 (数式)'!C12 -> 48113.183 | D51: ='[48]債務負担行為積算 (数式)'!D12 -> 4988 | E51: ='[48]債務負担行為積算 (数式)'!E12 -> 18 | F51: ='[48]債務負担行為積算 (数式)'!F12 -> 4.319794e+09 | G51: ='[48]債務負担行為積算 (数式)'!G12 -> 1.22 | H51: ='[48]債務負担行為積算 (数式)'!H12 -> 5270148679 | I51: ='[48]債務負担行為積算 (数式)'!I12 -> 5270148679 | J51: ='[48]債務負担行為積算 (数式)'!J12 -> 0 | ... L51: ='[48]債務負担行為積算 (数式)'!L12 -> 4.6037715e+09
B52: 選手団3,600 | C52: ='[48]債務負担行為積算 (数式)'!C13 -> 48113.183 | D52: ='[48]債務負担行為積算 (数式)'!D13 -> 4988 | E52: ='[48]債務負担行為積算 (数式)'!E13 -> 18 | F52: ='[48]債務負担行為積算 (数式)'!F13 -> 4.319794e+09 | G52: ='[48]債務負担行為積算 (数式)'!G13 -> 1.22 | H52: ='[48]債務負担行為積算 (数式)'!H13 -> 5270148679 | I52: ='[48]債務負担行為積算 (数式)'!I13 -> 5270148679 | J52: ='[48]債務負担行為積算 (数式)'!J13 -> 不要？ | ... L52: ='[48]債務負担行為積算 (数式)'!L13 -> 4.6037715e+09
B53: ファミリー | C53: ='[48]債務負担行為積算 (数式)'!C14 -> 163100.02 | D53: ='[48]債務負担行為積算 (数式)'!D14 -> 370 | E53: ='[48]債務負担行為積算 (数式)'!E14 -> 18 | F53: ='[48]債務負担行為積算 (数式)'!F14 -> 1.0862461e+09 | G53: ='[48]債務負担行為積算 (数式)'!G14 -> 1.22 | H53: ='[48]債務負担行為積算 (数式)'!H14 -> 1325220269 | I53: ='[48]債務負担行為積算 (数式)'!I14 -> 4852210296 | J53: ='[48]債務負担行為積算 (数式)'!J14 -> 0 | ... L53: ='[48]債務負担行為積算 (数式)'!L14 -> 9.5710353e+08
B54: スポンサー | C54: ='[48]債務負担行為積算 (数式)'!C15 -> 62210.38 | D54: ='[48]債務負担行為積算 (数式)'!D15 -> 1560 | E54: ='[48]債務負担行為積算 (数式)'!E15 -> 18 | F54: ='[48]債務負担行為積算 (数式)'!F15 -> 1.7468675e+09 | G54: ='[48]債務負担行為積算 (数式)'!G15 -> 1.22 | H54: ='[48]債務負担行為積算 (数式)'!H15 -> 2131178308 | J54: ='[48]債務負担行為積算 (数式)'!J15 -> 0 | K54: ='[48]債務負担行為積算 (数式)'!K15 -> 8.5123701e+08 | L54: ='[48]債務負担行為積算 (数式)'!L15 -> 1.0385091e+09
B55: NPC本部 | C55: ='[48]債務負担行為積算 (数式)'!C16 -> 53988.664 | D55: ='[48]債務負担行為積算 (数式)'!D16 -> 116 | E55: ='[48]債務負担行為積算 (数式)'!E16 -> 19 | F55: ='[48]債務負担行為積算 (数式)'!F16 -> 118991015 | G55: ='[48]債務負担行為積算 (数式)'!G16 -> 1.22 | H55: ='[48]債務負担行為積算 (数式)'!H16 -> 145169039 | J55: ='[48]債務負担行為積算 (数式)'!J16 -> 0 | K55: ='[48]債務負担行為積算 (数式)'!K16 -> 106465645 | L55: ='[48]債務負担行為積算 (数式)'!L16 -> 1.2988809e+08
B56: メディア | C56: ='[48]債務負担行為積算 (数式)'!C17 -> 20629.837 | D56: ='[48]債務負担行為積算 (数式)'!D17 -> 1600 | E56: ='[48]債務負担行為積算 (数式)'!E17 -> 18 | F56: ='[48]債務負担行為積算 (数式)'!F17 -> 5.9413932e+08 | G56: ='[48]債務負担行為積算 (数式)'!G17 -> 1.22 | H56: ='[48]債務負担行為積算 (数式)'!H17 -> 724849965 | J56: ='[48]債務負担行為積算 (数式)'!J17 -> 0 | K56: ='[48]債務負担行為積算 (数式)'!K17 -> 5.467908e+08 | L56: ='[48]債務負担行為積算 (数式)'!L17 -> 6.6708478e+08
B57: 技術役員（競技役員） | C57: ='[48]債務負担行為積算 (数式)'!C18 -> 23446.052 | D57: ='[48]債務負担行為積算 (数式)'!D18 -> 812 | E57: ='[48]債務負担行為積算 (数式)'!E18 -> 18 | F57: ='[48]債務負担行為積算 (数式)'!F18 -> 3.4268749e+08 | G57: ='[48]債務負担行為積算 (数式)'!G18 -> 1.22 | H57: ='[48]債務負担行為積算 (数式)'!H18 -> 418078743 | J57: ='[48]債務負担行為積算 (数式)'!J18 -> 0 | K57: ='[48]債務負担行為積算 (数式)'!K18 -> 1.9644399e+08 | L57: ='[48]債務負担行為積算 (数式)'!L18 -> 2.3966166e+08
B58: 技術役員（DCO) | C58: ='[48]債務負担行為積算 (数式)'!C19 -> 40204.982 | D58: ='[48]債務負担行為積算 (数式)'!D19 -> 122 | E58: ='[48]債務負担行為積算 (数式)'!E19 -> 18 | F58: ='[48]債務負担行為積算 (数式)'!F19 -> 88290141 | G58: ='[48]債務負担行為積算 (数式)'!G19 -> 1.22 | H58: ='[48]債務負担行為積算 (数式)'!H19 -> 107713972 | J58: ='[48]債務負担行為積算 (数式)'!J19 -> 0 | K58: ='[48]債務負担行為積算 (数式)'!K19 -> 46172589 | L58: ='[48]債務負担行為積算 (数式)'!L19 -> 56330558
A59: 合計 | B59: - | C59: ='[48]債務負担行為積算 (数式)'!C20 -> - | D59: ='[48]債務負担行為積算 (数式)'!D20 -> - | E59: ='[48]債務負担行為積算 (数式)'!E20 -> - | F59: ='[48]債務負担行為積算 (数式)'!F20 -> 3.8167192e+10 | G59: ='[48]債務負担行為積算 (数式)'!G20 -> - | H59: ='[48]債務負担行為積算 (数式)'!H20 -> 46563973776 | I59: ='[48]債務負担行為積算 (数式)'!I20 -> 46563973776 | J59: ='[48]債務負担行為積算 (数式)'!J20 -> 0 | ... L59: ='[48]債務負担行為積算 (数式)'!L20 -> 3.1125502e+10
A61: FR料
B62: ステークホルダー | C62: 1室あたりの 平均単価 | D62: 部屋数 ※施設保有FR数 | E62: 契約日数 | F62: 金額 物価上昇前 （G、H列固定値） | G62: 物価上昇率（宿泊） 2021➡2026 | H62: 金額 物価上昇後 （G、H列固定値） | I62: 総 計 | K62: 【参考値】 金額 物価上昇前 （シミュレーション） | L62: 【参考値】 金額 物価上昇後 （シミュレーション）
A63: アジア | B63: 選手団 | C63: ='[48]債務負担行為積算 (数式)'!C24 -> 535555.17 | D63: ='[48]債務負担行為積算 (数式)'!D24 -> 465 | E63: ='[48]債務負担行為積算 (数式)'!E24 -> 33 | F63: ='[48]債務負担行為積算 (数式)'!F24 -> 8.2180941e+09 | G63: ='[48]債務負担行為積算 (数式)'!G24 -> 1.22 | H63: ='[48]債務負担行為積算 (数式)'!H24 -> 10026074790 | I63: ='[48]債務負担行為積算 (数式)'!I24 -> 10026074790 | J63: ='[48]債務負担行為積算 (数式)'!J24 -> 0 | ... L63: ='[48]債務負担行為積算 (数式)'!L24 -> 5.9913397e+09
B64: ファミリー | C64: ='[48]債務負担行為積算 (数式)'!C25 -> 2025837.3 | D64: ='[48]債務負担行為積算 (数式)'!D25 -> 56 | E64: ='[48]債務負担行為積算 (数式)'!E25 -> 33 | F64: ='[48]債務負担行為積算 (数式)'!F25 -> 3.7437473e+09 | G64: ='[48]債務負担行為積算 (数式)'!G25 -> 1.22 | H64: ='[48]債務負担行為積算 (数式)'!H25 -> 4567371748 | I64: ='[48]債務負担行為積算 (数式)'!I25 -> 6082352041 | J64: ='[48]債務負担行為積算 (数式)'!J25 -> 0 | ... L64: ='[48]債務負担行為積算 (数式)'!L25 -> 2.3129462e+09
B65: スポンサー | C65: ='[48]債務負担行為積算 (数式)'!C26 -> 0 | D65: ='[48]債務負担行為積算 (数式)'!D26 -> 0 | E65: ='[48]債務負担行為積算 (数式)'!E26 -> 0 | F65: ='[48]債務負担行為積算 (数式)'!F26 -> 0 | G65: ='[48]債務負担行為積算 (数式)'!G26 -> 1.22 | H65: ='[48]債務負担行為積算 (数式)'!H26 -> 0 | J65: ='[48]債務負担行為積算 (数式)'!J26 -> 0 | K65: ='[48]債務負担行為積算 (数式)'!K26 -> 0 | L65: ='[48]債務負担行為積算 (数式)'!L26 -> 0
B66: NOC本部 | C66: ='[48]債務負担行為積算 (数式)'!C27 -> 500922.6 | D66: ='[48]債務負担行為積算 (数式)'!D27 -> 67 | E66: ='[48]債務負担行為積算 (数式)'!E27 -> 37 | F66: ='[48]債務負担行為積算 (数式)'!F27 -> 1.2417871e+09 | G66: ='[48]債務負担行為積算 (数式)'!G27 -> 1.22 | H66: ='[48]債務負担行為積算 (数式)'!H27 -> 1514980293 | J66: ='[48]債務負担行為積算 (数式)'!J27 -> 0 | K66: ='[48]債務負担行為積算 (数式)'!K27 -> 530888760 | L66: ='[48]債務負担行為積算 (数式)'!L27 -> 6.4768429e+08
A67: パラ | B67: 選手団 | C67: ='[48]債務負担行為積算 (数式)'!C28 -> 1158248.9 | D67: ='[48]債務負担行為積算 (数式)'!D28 -> 259 | E67: ='[48]債務負担行為積算 (数式)'!E28 -> 19 | F67: ='[48]債務負担行為積算 (数式)'!F28 -> 5.699743e+09 | G67: ='[48]債務負担行為積算 (数式)'!G28 -> 1.22 | H67: ='[48]債務負担行為積算 (数式)'!H28 -> 6953686475 | I67: ='[48]債務負担行為積算 (数式)'!I28 -> 6953686475 | J67: ='[48]債務負担行為積算 (数式)'!J28 -> 0 | ... L67: ='[48]債務負担行為積算 (数式)'!L28 -> 2.8533128e+09
B68: ファミリー | C68: ='[48]債務負担行為積算 (数式)'!C29 -> 2529412.3 | D68: ='[48]債務負担行為積算 (数式)'!D29 -> 16 | E68: ='[48]債務負担行為積算 (数式)'!E29 -> 19 | F68: ='[48]債務負担行為積算 (数式)'!F29 -> 768941343 | G68: ='[48]債務負担行為積算 (数式)'!G29 -> 1.22 | H68: ='[48]債務負担行為積算 (数式)'!H29 -> 938108439 | I68: ='[48]債務負担行為積算 (数式)'!I29 -> 1069432802 | J68: ='[48]債務負担行為積算 (数式)'!J29 -> 0 | ... L68: ='[48]債務負担行為積算 (数式)'!L29 -> 6.4186367e+08
B69: NPC本部 | C69: ='[48]債務負担行為積算 (数式)'!C30 -> 768878 | D69: ='[48]債務負担行為積算 (数式)'!D30 -> 7 | E69: ='[48]債務負担行為積算 (数式)'!E30 -> 20 | F69: ='[48]債務負担行為積算 (数式)'!F30 -> 107642920 | G69: ='[48]債務負担行為積算 (数式)'!G30 -> 1.22 | H69: ='[48]債務負担行為積算 (数式)'!H30 -> 131324363 | J69: ='[48]債務負担行為積算 (数式)'!J30 -> 0 | K69: ='[48]債務負担行為積算 (数式)'!K30 -> 13070926 | L69: ='[48]債務負担行為積算 (数式)'!L30 -> 15946530
A70: 合計 | B70: - | C70: ='[48]債務負担行為積算 (数式)'!C31 -> - | D70: ='[48]債務負担行為積算 (数式)'!D31 -> - | E70: ='[48]債務負担行為積算 (数式)'!E31 -> - | F70: ='[48]債務負担行為積算 (数式)'!F31 -> 1.9779956e+10 | G70: ='[48]債務負担行為積算 (数式)'!G31 -> - | H70: ='[48]債務負担行為積算 (数式)'!H31 -> 24131546108 | I70: ='[48]債務負担行為積算 (数式)'!I31 -> 24131546108 | J70: ='[48]債務負担行為積算 (数式)'!J31 -> 0 | ... L70: ='[48]債務負担行為積算 (数式)'!L31 -> 1.2463093e+10
A71: ※契約泊数及び日数についてシミュレーションが流動的であるため最大利用期間で契約見込、その後精査しキャンセル期限までにキャンセルする。
H73: 宿泊料＋FR料
H74: アジア | I74: ='[48]債務負担行為積算 (数式)'!I36 -> 52550041632
H75: パラ | I75: ='[48]債務負担行為積算 (数式)'!I37 -> 18145478252
H76: 合計 | I76: ='[48]債務負担行為積算 (数式)'!I38 -> 70695519884
A78: （パラ4,000一棟借上げ原則ヤメ）ACM財政見通（v4.3c）
A80: 宿泊料 | G80: 案3 | K80: ※財政見通しver（キャンセル期限後に実際に支払う金額ベース）
B81: ステークホルダー | C81: 1室あたりの 平均単価 | D81: 室数 ※シミュレーションの客室数 | E81: 契約泊数 | F81: 金額 物価上昇前 （G、H列固定値） | G81: 物価上昇率（宿泊） 2021➡2026 | H81: 金額 物価上昇後 （G、H列固定値） | I81: 総 計 | K81: 【参考値】 金額 物価上昇前 （シミュレーション） | L81: 【参考値】 金額 物価上昇後 （シミュレーション）
A82: アジア | B82: 選手団15,000 | C82: ='[49]債務負担行為積算 (数式)'!C4 -> 33756.68 | D82: ='[49]債務負担行為積算 (数式)'!D4 -> 11937 | E82: ='[49]債務負担行為積算 (数式)'!E4 -> 32 | F82: ='[49]債務負担行為積算 (数式)'!F4 -> 1.2894512e+10 | G82: ='[49]債務負担行為積算 (数式)'!G4 -> 1.22 | H82: ='[49]債務負担行為積算 (数式)'!H4 -> 15731304246 | I82: ='[49]債務負担行為積算 (数式)'!I4 -> 15731304246 | J82: ='[49]債務負担行為積算 (数式)'!J4 -> 0 | ... L82: ='[49]債務負担行為積算 (数式)'!L4 -> 1.0689792e+10
B83: 選手団12,000 | C83: ='[49]債務負担行為積算 (数式)'!C5 -> 35104.891 | D83: ='[49]債務負担行為積算 (数式)'!D5 -> 9962 | E83: ='[49]債務負担行為積算 (数式)'!E5 -> 32 | F83: ='[49]債務負担行為積算 (数式)'!F5 -> 1.1190878e+10 | G83: ='[49]債務負担行為積算 (数式)'!G5 -> 1.22 | H83: ='[49]債務負担行為積算 (数式)'!H5 -> 13652870698 | I83: ='[49]債務負担行為積算 (数式)'!I5 -> 13652870698 | J83: ='[49]債務負担行為積算 (数式)'!J5 -> 不要？ | ... L83: ='[49]債務負担行為積算 (数式)'!L5 -> 9.5891368e+09
B84: ファミリー | C84: ='[49]債務負担行為積算 (数式)'!C6 -> 104002.93 | D84: ='[49]債務負担行為積算 (数式)'!D6 -> 1645 | E84: ='[49]債務負担行為積算 (数式)'!E6 -> 32 | F84: ='[49]債務負担行為積算 (数式)'!F6 -> 5.4747141e+09 | G84: ='[49]債務負担行為積算 (数式)'!G6 -> 1.22 | H84: ='[49]債務負担行為積算 (数式)'!H6 -> 6679151237 | I84: ='[49]債務負担行為積算 (数式)'!I6 -> 20710310555 | J84: ='[49]債務負担行為積算 (数式)'!J6 -> 0 | ... L84: ='[49]債務負担行為積算 (数式)'!L6 -> 4.5155697e+09
B85: スポンサー | C85: ='[49]債務負担行為積算 (数式)'!C7 -> 48153.528 | D85: ='[49]債務負担行為積算 (数式)'!D7 -> 2560 | E85: ='[49]債務負担行為積算 (数式)'!E7 -> 32 | F85: ='[49]債務負担行為積算 (数式)'!F7 -> 3.944737e+09 | G85: ='[49]債務負担行為積算 (数式)'!G7 -> 1.22 | H85: ='[49]債務負担行為積算 (数式)'!H7 -> 4812579181 | J85: ='[49]債務負担行為積算 (数式)'!J7 -> 0 | K85: ='[49]債務負担行為積算 (数式)'!K7 -> 2.3857605e+09 | L85: ='[49]債務負担行為積算 (数式)'!L7 -> 2.9106278e+09
B86: NOC本部 | C86: ='[49]債務負担行為積算 (数式)'!C8 -> 67393.897 | D86: ='[49]債務負担行為積算 (数式)'!D8 -> 286 | E86: ='[49]債務負担行為積算 (数式)'!E8 -> 36 | F86: ='[49]債務負担行為積算 (数式)'!F8 -> 6.9388756e+08 | G86: ='[49]債務負担行為積算 (数式)'!G8 -> 1.22 | H86: ='[49]債務負担行為積算 (数式)'!H8 -> 846542823 | J86: ='[49]債務負担行為積算 (数式)'!J8 -> 0 | K86: ='[49]債務負担行為積算 (数式)'!K8 -> 719947332 | L86: ='[49]債務負担行為積算 (数式)'!L8 -> 8.7833575e+08
B87: メディア | C87: ='[49]債務負担行為積算 (数式)'!C9 -> 25177.548 | D87: ='[49]債務負担行為積算 (数式)'!D9 -> 3000 | E87: ='[49]債務負担行為積算 (数式)'!E9 -> 32 | F87: ='[49]債務負担行為積算 (数式)'!F9 -> 2.4170446e+09 | G87: ='[49]債務負担行為積算 (数式)'!G9 -> 1.22 | H87: ='[49]債務負担行為積算 (数式)'!H9 -> 2948794448 | J87: ='[49]債務負担行為積算 (数式)'!J9 -> 0 | K87: ='[49]債務負担行為積算 (数式)'!K9 -> 2.05575e+09 | L87: ='[49]債務負担行為積算 (数式)'!L9 -> 2.5080149e+09
B88: 技術役員（競技役員） | C88: ='[49]債務負担行為積算 (数式)'!C10 -> 34913.68 | D88: ='[49]債務負担行為積算 (数式)'!D10 -> 3354 | E88: ='[49]債務負担行為積算 (数式)'!E10 -> 32 | F88: ='[49]債務負担行為積算 (数式)'!F10 -> 3.7472155e+09 | G88: ='[49]債務負担行為積算 (数式)'!G10 -> 1.22 | H88: ='[49]債務負担行為積算 (数式)'!H10 -> 4571602860 | J88: ='[49]債務負担行為積算 (数式)'!J10 -> 0 | K88: ='[49]債務負担行為積算 (数式)'!K10 -> 1.1249505e+09 | L88: ='[49]債務負担行為積算 (数式)'!L10 -> 1.3724397e+09
B89: 技術役員（DCO) | C89: ='[49]債務負担行為積算 (数式)'!C11 -> 43282.836 | D89: ='[49]債務負担行為積算 (数式)'!D11 -> 504 | E89: ='[49]債務負担行為積算 (数式)'!E11 -> 32 | F89: ='[49]債務負担行為積算 (数式)'!F11 -> 6.9806558e+08 | G89: ='[49]債務負担行為積算 (数式)'!G11 -> 1.22 | H89: ='[49]債務負担行為積算 (数式)'!H11 -> 851640006 | J89: ='[49]債務負担行為積算 (数式)'!J11 -> 0 | K89: ='[49]債務負担行為積算 (数式)'!K11 -> 4.5768295e+08 | L89: ='[49]債務負担行為積算 (数式)'!L11 -> 5.583732e+08
A90: パラ | B90: 選手団4,000 | C90: ='[49]債務負担行為積算 (数式)'!C12 -> 48113.183 | D90: ='[49]債務負担行為積算 (数式)'!D12 -> 4988 | E90: ='[49]債務負担行為積算 (数式)'!E12 -> 18 | F90: ='[49]債務負担行為積算 (数式)'!F12 -> 4.319794e+09 | G90: ='[49]債務負担行為積算 (数式)'!G12 -> 1.22 | H90: ='[49]債務負担行為積算 (数式)'!H12 -> 5270148679 | I90: ='[49]債務負担行為積算 (数式)'!I12 -> 5270148679 | J90: ='[49]債務負担行為積算 (数式)'!J12 -> 0 | ... L90: ='[49]債務負担行為積算 (数式)'!L12 -> 5.179243e+09
B91: 選手団3,600 | C91: ='[49]債務負担行為積算 (数式)'!C13 -> 48113.183 | D91: ='[49]債務負担行為積算 (数式)'!D13 -> 4988 | E91: ='[49]債務負担行為積算 (数式)'!E13 -> 18 | F91: ='[49]債務負担行為積算 (数式)'!F13 -> 4.319794e+09 | G91: ='[49]債務負担行為積算 (数式)'!G13 -> 1.22 | H91: ='[49]債務負担行為積算 (数式)'!H13 -> 5270148679 | I91: ='[49]債務負担行為積算 (数式)'!I13 -> 5270148679 | J91: ='[49]債務負担行為積算 (数式)'!J13 -> 不要？ | ... L91: ='[49]債務負担行為積算 (数式)'!L13 -> 5.179243e+09
B92: ファミリー | C92: ='[49]債務負担行為積算 (数式)'!C14 -> 163100.02 | D92: ='[49]債務負担行為積算 (数式)'!D14 -> 370 | E92: ='[49]債務負担行為積算 (数式)'!E14 -> 18 | F92: ='[49]債務負担行為積算 (数式)'!F14 -> 1.0862461e+09 | G92: ='[49]債務負担行為積算 (数式)'!G14 -> 1.22 | H92: ='[49]債務負担行為積算 (数式)'!H14 -> 1325220269 | I92: ='[49]債務負担行為積算 (数式)'!I14 -> 4852210296 | J92: ='[49]債務負担行為積算 (数式)'!J14 -> 0 | ... L92: ='[49]債務負担行為積算 (数式)'!L14 -> 9.5710353e+08
B93: スポンサー | C93: ='[49]債務負担行為積算 (数式)'!C15 -> 62210.38 | D93: ='[49]債務負担行為積算 (数式)'!D15 -> 1560 | E93: ='[49]債務負担行為積算 (数式)'!E15 -> 18 | F93: ='[49]債務負担行為積算 (数式)'!F15 -> 1.7468675e+09 | G93: ='[49]債務負担行為積算 (数式)'!G15 -> 1.22 | H93: ='[49]債務負担行為積算 (数式)'!H15 -> 2131178308 | J93: ='[49]債務負担行為積算 (数式)'!J15 -> 0 | K93: ='[49]債務負担行為積算 (数式)'!K15 -> 8.5123701e+08 | L93: ='[49]債務負担行為積算 (数式)'!L15 -> 1.0385091e+09
B94: NPC本部 | C94: ='[49]債務負担行為積算 (数式)'!C16 -> 53988.664 | D94: ='[49]債務負担行為積算 (数式)'!D16 -> 116 | E94: ='[49]債務負担行為積算 (数式)'!E16 -> 19 | F94: ='[49]債務負担行為積算 (数式)'!F16 -> 118991015 | G94: ='[49]債務負担行為積算 (数式)'!G16 -> 1.22 | H94: ='[49]債務負担行為積算 (数式)'!H16 -> 145169039 | J94: ='[49]債務負担行為積算 (数式)'!J16 -> 0 | K94: ='[49]債務負担行為積算 (数式)'!K16 -> 118991015 | L94: ='[49]債務負担行為積算 (数式)'!L16 -> 1.4516904e+08
B95: メディア | C95: ='[49]債務負担行為積算 (数式)'!C17 -> 20629.837 | D95: ='[49]債務負担行為積算 (数式)'!D17 -> 1600 | E95: ='[49]債務負担行為積算 (数式)'!E17 -> 18 | F95: ='[49]債務負担行為積算 (数式)'!F17 -> 5.9413932e+08 | G95: ='[49]債務負担行為積算 (数式)'!G17 -> 1.22 | H95: ='[49]債務負担行為積算 (数式)'!H17 -> 724849965 | J95: ='[49]債務負担行為積算 (数式)'!J17 -> 0 | K95: ='[49]債務負担行為積算 (数式)'!K17 -> 5.467908e+08 | L95: ='[49]債務負担行為積算 (数式)'!L17 -> 6.6708478e+08
B96: 技術役員（競技役員） | C96: ='[49]債務負担行為積算 (数式)'!C18 -> 23446.052 | D96: ='[49]債務負担行為積算 (数式)'!D18 -> 812 | E96: ='[49]債務負担行為積算 (数式)'!E18 -> 18 | F96: ='[49]債務負担行為積算 (数式)'!F18 -> 3.4268749e+08 | G96: ='[49]債務負担行為積算 (数式)'!G18 -> 1.22 | H96: ='[49]債務負担行為積算 (数式)'!H18 -> 418078743 | J96: ='[49]債務負担行為積算 (数式)'!J18 -> 0 | K96: ='[49]債務負担行為積算 (数式)'!K18 -> 1.9644399e+08 | L96: ='[49]債務負担行為積算 (数式)'!L18 -> 2.3966166e+08
B97: 技術役員（DCO) | C97: ='[49]債務負担行為積算 (数式)'!C19 -> 40204.982 | D97: ='[49]債務負担行為積算 (数式)'!D19 -> 122 | E97: ='[49]債務負担行為積算 (数式)'!E19 -> 18 | F97: ='[49]債務負担行為積算 (数式)'!F19 -> 88290141 | G97: ='[49]債務負担行為積算 (数式)'!G19 -> 1.22 | H97: ='[49]債務負担行為積算 (数式)'!H19 -> 107713972 | J97: ='[49]債務負担行為積算 (数式)'!J19 -> 0 | K97: ='[49]債務負担行為積算 (数式)'!K19 -> 46172589 | L97: ='[49]債務負担行為積算 (数式)'!L19 -> 56330558
A98: 合計 | B98: - | C98: ='[49]債務負担行為積算 (数式)'!C20 -> - | D98: ='[49]債務負担行為積算 (数式)'!D20 -> - | E98: ='[49]債務負担行為積算 (数式)'!E20 -> - | F98: ='[49]債務負担行為積算 (数式)'!F20 -> 3.8167192e+10 | G98: ='[49]債務負担行為積算 (数式)'!G20 -> - | H98: ='[49]債務負担行為積算 (数式)'!H20 -> 46563973776 | I98: ='[49]債務負担行為積算 (数式)'!I20 -> 46563973776 | J98: ='[49]債務負担行為積算 (数式)'!J20 -> 0 | ... L98: ='[49]債務負担行為積算 (数式)'!L20 -> 3.1716254e+10
A100: FR料
B101: ステークホルダー | C101: 1室あたりの 平均単価 | D101: 部屋数 ※施設保有FR数 | E101: 契約日数 | F101: 金額 物価上昇前 （G、H列固定値） | G101: 物価上昇率（宿泊） 2021➡2026 | H101: 金額 物価上昇後 （G、H列固定値） | I101: 総 計 | K101: 【参考値】 金額 物価上昇前 （シミュレーション） | L101: 【参考値】 金額 物価上昇後 （シミュレーション）
A102: アジア | B102: 選手団 | C102: ='[49]債務負担行為積算 (数式)'!C24 -> 535555.17 | D102: ='[49]債務負担行為積算 (数式)'!D24 -> 465 | E102: ='[49]債務負担行為積算 (数式)'!E24 -> 33 | F102: ='[49]債務負担行為積算 (数式)'!F24 -> 8.2180941e+09 | G102: ='[49]債務負担行為積算 (数式)'!G24 -> 1.22 | H102: ='[49]債務負担行為積算 (数式)'!H24 -> 10026074790 | I102: ='[49]債務負担行為積算 (数式)'!I24 -> 10026074790 | J102: ='[49]債務負担行為積算 (数式)'!J24 -> 0 | ... L102: ='[49]債務負担行為積算 (数式)'!L24 -> 5.9913397e+09
B103: ファミリー | C103: ='[49]債務負担行為積算 (数式)'!C25 -> 2025837.3 | D103: ='[49]債務負担行為積算 (数式)'!D25 -> 56 | E103: ='[49]債務負担行為積算 (数式)'!E25 -> 33 | F103: ='[49]債務負担行為積算 (数式)'!F25 -> 3.7437473e+09 | G103: ='[49]債務負担行為積算 (数式)'!G25 -> 1.22 | H103: ='[49]債務負担行為積算 (数式)'!H25 -> 4567371748 | I103: ='[49]債務負担行為積算 (数式)'!I25 -> 6487398830 | J103: ='[49]債務負担行為積算 (数式)'!J25 -> 0 | ... L103: ='[49]債務負担行為積算 (数式)'!L25 -> 2.3129462e+09
B104: スポンサー | C104: ='[49]債務負担行為積算 (数式)'!C26 -> 0 | D104: ='[49]債務負担行為積算 (数式)'!D26 -> 0 | E104: ='[49]債務負担行為積算 (数式)'!E26 -> 0 | F104: ='[49]債務負担行為積算 (数式)'!F26 -> 0 | G104: ='[49]債務負担行為積算 (数式)'!G26 -> 1.22 | H104: ='[49]債務負担行為積算 (数式)'!H26 -> 0 | J104: ='[49]債務負担行為積算 (数式)'!J26 -> 0 | K104: ='[49]債務負担行為積算 (数式)'!K26 -> 0 | L104: ='[49]債務負担行為積算 (数式)'!L26 -> 0
B105: NOC本部 | C105: ='[49]債務負担行為積算 (数式)'!C27 -> 634849.81 | D105: ='[49]債務負担行為積算 (数式)'!D27 -> 67 | E105: ='[49]債務負担行為積算 (数式)'!E27 -> 37 | F105: ='[49]債務負担行為積算 (数式)'!F27 -> 1.5737927e+09 | G105: ='[49]債務負担行為積算 (数式)'!G27 -> 1.22 | H105: ='[49]債務負担行為積算 (数式)'!H27 -> 1920027082 | J105: ='[49]債務負担行為積算 (数式)'!J27 -> 0 | K105: ='[49]債務負担行為積算 (数式)'!K27 -> 764465724 | L105: ='[49]債務負担行為積算 (数式)'!L27 -> 9.3264818e+08
A106: パラ | B106: 選手団 | C106: ='[49]債務負担行為積算 (数式)'!C28 -> 1158248.9 | D106: ='[49]債務負担行為積算 (数式)'!D28 -> 259 | E106: ='[49]債務負担行為積算 (数式)'!E28 -> 19 | F106: ='[49]債務負担行為積算 (数式)'!F28 -> 5.699743e+09 | G106: ='[49]債務負担行為積算 (数式)'!G28 -> 1.22 | H106: ='[49]債務負担行為積算 (数式)'!H28 -> 6953686475 | I106: ='[49]債務負担行為積算 (数式)'!I28 -> 6953686475 | J106: ='[49]債務負担行為積算 (数式)'!J28 -> 0 | ... L106: ='[49]債務負担行為積算 (数式)'!L28 -> 3.2099769e+09
B107: ファミリー | C107: ='[49]債務負担行為積算 (数式)'!C29 -> 2529412.3 | D107: ='[49]債務負担行為積算 (数式)'!D29 -> 16 | E107: ='[49]債務負担行為積算 (数式)'!E29 -> 19 | F107: ='[49]債務負担行為積算 (数式)'!F29 -> 768941343 | G107: ='[49]債務負担行為積算 (数式)'!G29 -> 1.22 | H107: ='[49]債務負担行為積算 (数式)'!H29 -> 938108439 | I107: ='[49]債務負担行為積算 (数式)'!I29 -> 1115182338 | J107: ='[49]債務負担行為積算 (数式)'!J29 -> 0 | ... L107: ='[49]債務負担行為積算 (数式)'!L29 -> 6.4186367e+08
B108: NPC本部 | C108: ='[49]債務負担行為積算 (数式)'!C30 -> 1036732.4 | D108: ='[49]債務負担行為積算 (数式)'!D30 -> 7 | E108: ='[49]債務負担行為積算 (数式)'!E30 -> 20 | F108: ='[49]債務負担行為積算 (数式)'!F30 -> 145142540 | G108: ='[49]債務負担行為積算 (数式)'!G30 -> 1.22 | H108: ='[49]債務負担行為積算 (数式)'!H30 -> 177073899 | J108: ='[49]債務負担行為積算 (数式)'!J30 -> 0 | K108: ='[49]債務負担行為積算 (数式)'!K30 -> 137885413 | L108: ='[49]債務負担行為積算 (数式)'!L30 -> 1.682202e+08
A109: 合計 | B109: - | C109: ='[49]債務負担行為積算 (数式)'!C31 -> - | D109: ='[49]債務負担行為積算 (数式)'!D31 -> - | E109: ='[49]債務負担行為積算 (数式)'!E31 -> - | F109: ='[49]債務負担行為積算 (数式)'!F31 -> 2.0149461e+10 | G109: ='[49]債務負担行為積算 (数式)'!G31 -> - | H109: ='[49]債務負担行為積算 (数式)'!H31 -> 24582342433 | I109: ='[49]債務負担行為積算 (数式)'!I31 -> 24582342433 | J109: ='[49]債務負担行為積算 (数式)'!J31 -> 0 | ... L109: ='[49]債務負担行為積算 (数式)'!L31 -> 1.3256995e+10
...

Sheet 財政見通し積算
B2: 財政見通し積算にあたっての前提条件
B3: ○積算するにあたっての単価、泊数等は別シート（Results）にて宿泊施設毎に計算
B4: ○選手団は貸切想定（アジアもパラも）のため、選手団の宿泊施設数が同じの場合は同じ額になる
B5: ○ファミリーのOF1は貸切想定、OF2以下は貸切ではない
B6: ○ファンクションルームの積算については、基本選手、ファミリー、本部は（一応）全施設利用想定
B7: ○物価上昇率は、総務省の消費者物価指数（宿泊料：2021→2023で1.22倍）から算出
B9: Resultsシートの説明
B10: ○各宿泊施設で割り振られるSHを記載（C列～G列、被りの関係で列が分かれる）
B11: ○C列～G列のSH毎の、シミュレーション上の利用客室数をX列～AB列に記載
B12: ○C列～G列のSH毎を参照し、それぞれのSHの宿泊施設毎の泊数を拾ってきている（AK列～AU列）
B13: ○各宿泊施設の客室単価は各シートにて積算、その合計を拾っている（S列）
B14: ○S列を各シートの合計客室数（V列）で割って、一室あたりの平均単価を算出（T列）
... B19: ○宿泊施設毎に算出した金額を、SH毎にまとめている
C21: 客室金額合計 | D21: ファンクションルーム金額合計 | E21: 合計（物価上昇考慮前） | F21: 物価上昇率 | G21: 合計（物価上昇考慮後） | H21: 総計
B22: アジア 選手15,000人 | C22: =SUM(Results【技術役員スポンサーメディア積算】!BC283) -> 1720770931 | D22: =SUM(Results【技術役員スポンサーメディア積算】!BI283) -> 691185467 | E22: =SUM(C22:D22) -> 2411956398 | F22: ='物価（案3）'!$I$10 -> 1.34 | G22: =ROUNDUP($E22*$F22,0) -> 3232021574 | H22: =G22 -> 3232021574
B23: アジア 選手12,000人 | C23: =SUM(Results【技術役員スポンサーメディア積算】!#REF!) -> #REF! | D23: =SUM(Results【技術役員スポンサーメディア積算】!#REF!) -> #REF! | E23: =SUM(C23:D23) -> #REF! | F23: ='物価（案3）'!$I$10 -> 1.34 | G23: =ROUNDUP($E23*$F23,0) -> #REF! | H23: =G23 -> #REF!
B24: アジア ファミリー | C24: =SUM(Results【技術役員スポンサーメディア積算】!BD283) -> 959319162 | D24: =SUM(Results【技術役員スポンサーメディア積算】!BJ283) -> 1898926146 | E24: =SUM(C24:D24) -> 2858245308 | F24: ='物価（案3）'!$I$10 -> 1.34 | G24: =ROUNDUP($E24*$F24,0) -> 3830048713 | H24: =SUM(G24:G29) -> #REF!
B25: アジア スポンサー | C25: =SUM(Results【技術役員スポンサーメディア積算】!#REF!) -> #REF! | D25: =SUM(Results【技術役員スポンサーメディア積算】!#REF!) -> #REF! | E25: =SUM(C25:D25) -> #REF! | F25: ='物価（案3）'!$I$10 -> 1.34 | G25: =ROUNDUP($E25*$F25,0) -> #REF!
B26: アジア 本部 | C26: =SUM(Results【技術役員スポンサーメディア積算】!#REF!) -> #REF! | D26: =SUM(Results【技術役員スポンサーメディア積算】!BK283) -> 87385650 | E26: =SUM(C26:D26) -> #REF! | F26: ='物価（案3）'!$I$10 -> 1.34 | G26: =ROUNDUP($E26*$F26,0) -> #REF!
B27: アジア メディア | C27: =SUM(Results【技術役員スポンサーメディア積算】!BE283) -> 1980375600 | D27: 0 | E27: =SUM(C27:D27) -> 1980375600 | F27: ='物価（案3）'!$I$10 -> 1.34 | G27: =ROUNDUP($E27*$F27,0) -> 2653703304
B28: アジア 技術役員 | C28: =SUM(Results【技術役員スポンサーメディア積算】!#REF!) -> #REF! | D28: 0 | E28: =SUM(C28:D28) -> #REF! | F28: ='物価（案3）'!$I$10 -> 1.34 | G28: =ROUNDUP($E28*$F28,0) -> #REF!
B29: アジア DCO | C29: =SUM(Results【技術役員スポンサーメディア積算】!#REF!) -> #REF! | D29: 0 | E29: =SUM(C29:D29) -> #REF! | F29: ='物価（案3）'!$I$10 -> 1.34 | G29: =ROUNDUP($E29*$F29,0) -> #REF!
B30: パラ 選手4,000人 | C30: =SUM(Results【技術役員スポンサーメディア積算】!BF283) -> 344907436 | D30: =SUM(Results【技術役員スポンサーメディア積算】!BL283) -> 321313565 | E30: =SUM(C30:D30) -> 666221001 | F30: ='物価（案3）'!$I$10 -> 1.34 | G30: =ROUNDUP($E30*$F30,0) -> 892736142 | H30: =G30 -> 892736142
B31: パラ 選手3,600人 | C31: =SUM(Results【技術役員スポンサーメディア積算】!BG283) -> 624655701 | D31: =SUM(Results【技術役員スポンサーメディア積算】!BM283) -> 855630459 | E31: =SUM(C31:D31) -> 1480286160 | F31: ='物価（案3）'!$I$10 -> 1.34 | G31: =ROUNDUP($E31*$F31,0) -> 1983583455 | H31: =G31 -> 1983583455
B32: パラファミリー | C32: =SUM(Results【技術役員スポンサーメディア積算】!BH283) -> 300216120 | D32: =SUM(Results【技術役員スポンサーメディア積算】!BN283) -> 0 | E32: =SUM(C32:D32) -> 300216120 | F32: ='物価（案3）'!$I$10 -> 1.34 | G32: =ROUNDUP($E32*$F32,0) -> 402289601 | H32: =SUM(G32:G37) -> #REF!
B33: パラスポンサー | C33: =SUM(Results【技術役員スポンサーメディア積算】!#REF!) -> #REF! | D33: 0 | E33: =SUM(C33:D33) -> #REF! | F33: ='物価（案3）'!$I$10 -> 1.34 | G33: =ROUNDUP($E33*$F33,0) -> #REF!
B34: パラ本部 | C34: =SUM(Results【技術役員スポンサーメディア積算】!#REF!) -> #REF! | D34: =SUM(Results【技術役員スポンサーメディア積算】!#REF!) -> #REF! | E34: =SUM(C34:D34) -> #REF! | F34: ='物価（案3）'!$I$10 -> 1.34 | G34: =ROUNDUP($E34*$F34,0) -> #REF!
B35: パラメディア | C35: =SUM(Results【技術役員スポンサーメディア積算】!#REF!) -> #REF! | D35: 0 | E35: =SUM(C35:D35) -> #REF! | F35: ='物価（案3）'!$I$10 -> 1.34 | G35: =ROUNDUP($E35*$F35,0) -> #REF!
B36: パラ技術役員 | C36: =SUM(Results【技術役員スポンサーメディア積算】!#REF!) -> #REF! | D36: 0 | E36: =SUM(C36:D36) -> #REF! | F36: ='物価（案3）'!$I$10 -> 1.34 | G36: =ROUNDUP($E36*$F36,0) -> #REF!
B37: パラDCO | C37: =SUM(Results【技術役員スポンサーメディア積算】!#REF!) -> #REF! | D37: 0 | E37: =SUM(C37:D37) -> #REF! | F37: ='物価（案3）'!$I$10 -> 1.34 | G37: =ROUNDUP($E37*$F37,0) -> #REF!
B38: 小計 | C38: =SUM(C22:C37) -> #REF! | D38: =SUM(D22:D37) -> #REF! | E38: =SUM(E22:E37) -> #REF! | G38: =SUM(G22:G37) -> #REF! | H38: =SUM(H22:H37) -> #REF!
C40: 客室金額合計 | D40: ファンクションルーム金額合計 | E40: 合計（物価上昇考慮前） | G40: 合計（物価上昇考慮後）
B41: アジア15,000パターン計 | C41: =SUM(C22,C24:C29) -> #REF! | D41: =SUM(D22,D24:D29) -> #REF! | E41: =SUM(E22,E24:E29) -> #REF! | G41: =SUM(G22,G24:G29) -> #REF!
B42: アジア12,000パターン計 | C42: =SUM(C23,C24:C29) -> #REF! | D42: =SUM(D23,D24:D29) -> #REF! | E42: =SUM(E23,E24:E29) -> #REF! | G42: =SUM(G23,G24:G29) -> #REF!
B43: パラ4,000パターン計 | C43: =SUM(C30,C32:C37) -> #REF! | D43: =SUM(D30,D32:D37) -> #REF! | E43: =SUM(E30,E32:E37) -> #REF! | G43: =SUM(G30,G32:G37) -> #REF!
B44: パラ3,600パターン計 | C44: =SUM(C31,C32:C37) -> #REF! | D44: =SUM(D31,D32:D37) -> #REF! | E44: =SUM(E31,E32:E37) -> #REF! | G44: =SUM(G31,G32:G37) -> #REF!

Sheet 債務負担行為積算  (数式)
A1: 債務負担行為（キャンセル期限前の契約金額ベース）
A2: 宿泊料 | G2: 案3 | K2: ※財政見通しver（キャンセル期限後に実際に支払う金額ベース）
B3: ステークホルダー | C3: 1室あたりの 平均単価 | D3: 室数 ※シミュレーションの客室数 | E3: 契約泊数 | F3: 金額 物価上昇前 （G、H列固定値） | G3: 物価上昇率（宿泊） 2021➡2026 | H3: 金額 物価上昇後 （G、H列固定値） | I3: 総 計 | K3: 【参考値】 金額 物価上昇前 （シミュレーション） | L3: 【参考値】 金額 物価上昇後 （シミュレーション）
A4: アジア | B4: 選手団15,000 | C4: =IF(COUNTIF(Results【技術役員スポンサーメディア積算】!C:C, "選手15000")=0, 0, SUMIF(Results【技術役員スポンサーメディア積算】!C:C, "選手15000", Results【技術役員スポンサーメディア積算】!AA:AA) / COUNTIF(Results【技術役員スポンサーメディア積算】!C:C, "選手15000")) -> 0 | D4: 11937 | E4: 32 | F4: =$E$4*$C$4*$D$4 -> 0 | G4: ='物価（案3）'!$I$10 -> 1.34 | H4: =ROUNDUP($C4*$D4*$E4*$G4,0) -> 0 | I4: =H4 -> 0 | K4: =Results【技術役員スポンサーメディア積算】!BC283 -> 1720770931 | L4: =$K4*$G4 -> 2.305833e+09
B5: 選手団12,000 | C5: =IF(COUNTIF(Results【技術役員スポンサーメディア積算】!D:D, "選手12000")=0, 0, SUMIF(Results【技術役員スポンサーメディア積算】!D:D, "選手12000", Results【技術役員スポンサーメディア積算】!AA:AA) / COUNTIF(Results【技術役員スポンサーメディア積算】!D:D, "選手12000")) -> 0 | D5: 9962 | E5: 32 | F5: =E5*C5*D5 -> 0 | G5: ='物価（案3）'!$I$10 -> 1.34 | H5: =ROUNDUP($C5*$D5*$E5*$G5,0) -> 0 | I5: =H5 -> 0 | J5: 不要？ | K5: =Results【技術役員スポンサーメディア積算】!#REF! -> #REF! | L5: =$K5*$G5 -> #REF!
B6: ファミリー | C6: {=IF(SUMPRODUCT(--(Results【技術役員スポンサーメディア積算】!C:C="ファミリー") + --(Results【技術役員スポンサーメディア積算】!D:D="ファミリー"))=0, 0, SUMIFS(Results【技術役員スポンサーメディア積算】!AA:AA, Results【技術役員スポンサーメディア積算】!C:C, "ファミリー") + SUMIFS(Results【技術役員スポンサーメディア積算】!AA:AA, Results【技術役員スポンサーメディア積算】!D:D, "ファミリー") / SUMPRODUCT(--(Results【技術役員スポンサーメディア積算】!C:C="ファミリー") + --(Results【技術役員スポンサーメディア積算】!D:D="ファミリー")))} -> 0 | D6: 1645 | E6: 32 | F6: =E6*C6*D6 -> 0 | G6: ='物価（案3）'!$I$10 -> 1.34 | H6: =ROUNDUP($C6*$D6*$E6*$G6,0) -> 0 | I6: =SUM(H6:H11) -> 10511814540 | K6: =Results【技術役員スポンサーメディア積算】!BD283 -> 959319162 | L6: =$K6*$G6 -> 1.2854877e+09
B7: スポンサー | C7: {=IF(SUMPRODUCT(--(Results【技術役員スポンサーメディア積算】!C:C="スポンサー") + --(Results【技術役員スポンサーメディア積算】!D:D="スポンサー"))=0, 0, (SUMIFS(Results【技術役員スポンサーメディア積算】!AA:AA, Results【技術役員スポンサーメディア積算】!C:C, "スポンサー") + SUMIFS(Results【技術役員スポンサーメディア積算】!AA:AA, Results【技術役員スポンサーメディア積算】!D:D, "スポンサー")) / SUMPRODUCT(--(Results【技術役員スポンサーメディア積算】!C:C="スポンサー") + --(Results【技術役員スポンサーメディア積算】!D:D="スポンサー")))} -> 60684.639 | D7: 2560 | E7: 32 | F7: =E7*C7*D7 -> 4.9712856e+09 | G7: ='物価（案3）'!$I$10 -> 1.34 | H7: =ROUNDUP($C7*$D7*$E7*$G7,0) -> 6661522704 | K7: =Results【技術役員スポンサーメディア積算】!#REF! -> #REF! | L7: =$K7*$G7 -> #REF!
B8: NOC本部 | C8: {=IF(SUMPRODUCT(--(Results【技術役員スポンサーメディア積算】!C:C="本部") + --(Results【技術役員スポンサーメディア積算】!D:D="本部"))=0, 0, (SUMIFS(Results【技術役員スポンサーメディア積算】!AA:AA, Results【技術役員スポンサーメディア積算】!C:C, "本部") + SUMIFS(Results【技術役員スポンサーメディア積算】!AA:AA, Results【技術役員スポンサーメディア積算】!D:D, "本部")) / SUMPRODUCT(--(Results【技術役員スポンサーメディア積算】!C:C="本部") + --(Results【技術役員スポンサーメディア積算】!D:D="本部")))} -> 0 | D8: 286 | E8: 36 | F8: =E8*C8*D8 -> 0 | G8: ='物価（案3）'!$I$10 -> 1.34 | H8: =ROUNDUP($C8*$D8*$E8*$G8,0) -> 0 | K8: =Results【技術役員スポンサーメディア積算】!#REF! -> #REF! | L8: =$K8*$G8 -> #REF!
B9: メディア | C9: {=IF(SUMPRODUCT(--(Results【技術役員スポンサーメディア積算】!C:C="メディア") + --(Results【技術役員スポンサーメディア積算】!D:D="メディア"))=0, 0, (SUMIFS(Results【技術役員スポンサーメディア積算】!AA:AA, Results【技術役員スポンサーメディア積算】!C:C, "メディア") + SUMIFS(Results【技術役員スポンサーメディア積算】!AA:AA, Results【技術役員スポンサーメディア積算】!D:D, "メディア")) / SUMPRODUCT(--(Results【技術役員スポンサーメディア積算】!C:C="メディア") + --(Results【技術役員スポンサーメディア積算】!D:D="メディア")))} -> 0 | D9: 3000 | E9: 32 | F9: =E9*C9*D9 -> 0 | G9: ='物価（案3）'!$I$10 -> 1.34 | H9: =ROUNDUP($C9*$D9*$E9*$G9,0) -> 0 | K9: =Results【技術役員スポンサーメディア積算】!BE283 -> 1980375600 | L9: =$K9*$G9 -> 2653703304
B10: 技術役員（競技役員） | C10: {=IF(SUMPRODUCT(--(Results【技術役員スポンサーメディア積算】!C:C="技術役員") + --(Results【技術役員スポンサーメディア積算】!D:D="技術役員"))=0, 0, (SUMIFS(Results【技術役員スポンサーメディア積算】!AA:AA, Results【技術役員スポンサーメディア積算】!C:C, "技術役員") + SUMIFS(Results【技術役員スポンサーメディア積算】!AA:AA, Results【技術役員スポンサーメディア積算】!D:D, "技術役員")) / SUMPRODUCT(--(Results【技術役員スポンサーメディア積算】!C:C="技術役員") + --(Results【技術役員スポンサーメディア積算】!D:D="技術役員")))} -> 26771.692 | D10: 3354 | E10: 32 | F10: =E10*C10*D10 -> 2.8733521e+09 | G10: ='物価（案3）'!$I$10 -> 1.34 | H10: =ROUNDUP($C10*$D10*$E10*$G10,0) -> 3850291836 | K10: =Results【技術役員スポンサーメディア積算】!#REF! -> #REF! | L10: =$K10*$G10 -> #REF!
B11: 技術役員（DCO) | C11: {=IF(SUMPRODUCT(--(Results【技術役員スポンサーメディア積算】!C:C="DCO") + --(Results【技術役員スポンサーメディア積算】!D:D="DCO") + --(Results【技術役員スポンサーメディア積算】!E:E="DCO"))=0, 0, (SUMIFS(Results【技術役員スポンサーメディア積算】!AA:AA, Results【技術役員スポンサーメディア積算】!C:C, "DCO") + SUMIFS(Results【技術役員スポンサーメディア積算】!AA:AA, Results【技術役員スポンサーメディア積算】!D:D, "DCO") + SUMIFS(Results【技術役員スポンサーメディア積算】!AA:AA, Results【技術役員スポンサーメディア積算】!E:E, "DCO")) / SUMPRODUCT(--(Results【技術役員スポンサーメディア積算】!C:C="DCO") + --(Results【技術役員スポンサーメディア積算】!D:D="DCO") + --(Results【技術役員スポンサーメディア積算】!E:E="DCO")))} -> 0 | D11: 504 | E11: 32 | F11: =E11*C11*D11 -> 0 | G11: ='物価（案3）'!$I$10 -> 1.34 | H11: =ROUNDUP($C11*$D11*$E11*$G11,0) -> 0 | K11: =Results【技術役員スポンサーメディア積算】!#REF! -> #REF! | L11: =$K11*$G11 -> #REF!
A12: パラ | B12: 選手団4,000 | C12: {=IF(SUMPRODUCT(--(Results【技術役員スポンサーメディア積算】!F:F="選手") + --(Results【技術役員スポンサーメディア積算】!G:G="選手"))=0, 0, (SUMIFS(Results【技術役員スポンサーメディア積算】!AA:AA, Results【技術役員スポンサーメディア積算】!F:F, "選手") + SUMIFS(Results【技術役員スポンサーメディア積算】!AA:AA, Results【技術役員スポンサーメディア積算】!G:G, "選手")) / SUMPRODUCT(--(Results【技術役員スポンサーメディア積算】!F:F="選手") + --(Results【技術役員スポンサーメディア積算】!G:G="選手")))} -> 0 | D12: 4988 | E12: 18 | F12: =E12*C12*D12 -> 0 | G12: ='物価（案3）'!$I$10 -> 1.34 | H12: =ROUNDUP($C12*$D12*$E12*$G12,0) -> 0 | I12: =H12 -> 0 | K12: =Results【技術役員スポンサーメディア積算】!BF283 -> 344907436 | L12: =$K12*$G12 -> 4.6217596e+08
B13: 選手団3,600 | C13: {=IF(SUMPRODUCT(--(Results【技術役員スポンサーメディア積算】!F:F="選手") + --(Results【技術役員スポンサーメディア積算】!G:G="選手"))=0, 0, (SUMIFS(Results【技術役員スポンサーメディア積算】!AA:AA, Results【技術役員スポンサーメディア積算】!F:F, "選手") + SUMIFS(Results【技術役員スポンサーメディア積算】!AA:AA, Results【技術役員スポンサーメディア積算】!G:G, "選手")) / SUMPRODUCT(--(Results【技術役員スポンサーメディア積算】!F:F="選手") + --(Results【技術役員スポンサーメディア積算】!G:G="選手")))} -> 0 | D13: 4988 | E13: 18 | F13: =E13*C13*D13 -> 0 | G13: ='物価（案3）'!$I$10 -> 1.34 | H13: =ROUNDUP($C13*$D13*$E13*$G13,0) -> 0 | I13: =H13 -> 0 | J13: 不要？ | K13: =Results【技術役員スポンサーメディア積算】!BG283 -> 624655701 | L13: =$K13*$G13 -> 8.3703864e+08
B14: ファミリー | C14: {=IF(SUMPRODUCT(--(Results【技術役員スポンサーメディア積算】!F:F="ファミリー") + --(Results【技術役員スポンサーメディア積算】!G:G="ファミリー"))=0, 0, (SUMIFS(Results【技術役員スポンサーメディア積算】!AA:AA, Results【技術役員スポンサーメディア積算】!F:F, "ファミリー") + SUMIFS(Results【技術役員スポンサーメディア積算】!AA:AA, Results【技術役員スポンサーメディア積算】!G:G, "ファミリー")) / SUMPRODUCT(--(Results【技術役員スポンサーメディア積算】!F:F="ファミリー") + --(Results【技術役員スポンサーメディア積算】!G:G="ファミリー")))} -> 0 | D14: 370 | E14: 18 | F14: =E14*C14*D14 -> 0 | G14: ='物価（案3）'!$I$10 -> 1.34 | H14: =ROUNDUP($C14*$D14*$E14*$G14,0) -> 0 | I14: =SUM(H14:H19) -> 2457049000 | K14: =Results【技術役員スポンサーメディア積算】!BH283 -> 300216120 | L14: =$K14*$G14 -> 4.022896e+08
B15: スポンサー | C15: {=IF(SUMPRODUCT(--(Results【技術役員スポンサーメディア積算】!F:F="スポンサー") + --(Results【技術役員スポンサーメディア積算】!G:G="スポンサー"))=0, 0, (SUMIFS(Results【技術役員スポンサーメディア積算】!AA:AA, Results【技術役員スポンサーメディア積算】!F:F, "スポンサー") + SUMIFS(Results【技術役員スポンサーメディア積算】!AA:AA, Results【技術役員スポンサーメディア積算】!G:G, "スポンサー")) / SUMPRODUCT(--(Results【技術役員スポンサーメディア積算】!F:F="スポンサー") + --(Results【技術役員スポンサーメディア積算】!G:G="スポンサー")))} -> 53371.432 | D15: 1560 | E15: 18 | F15: =E15*C15*D15 -> 1.4986698e+09 | G15: ='物価（案3）'!$I$10 -> 1.34 | H15: =ROUNDUP($C15*$D15*$E15*$G15,0) -> 2008217561 | K15: =Results【技術役員スポンサーメディア積算】!#REF! -> #REF! | L15: =$K15*$G15 -> #REF!
B16: NPC本部 | C16: {=IF(SUMPRODUCT(--(Results【技術役員スポンサーメディア積算】!F:F="本部") + --(Results【技術役員スポンサーメディア積算】!G:G="本部"))=0, 0, (SUMIFS(Results【技術役員スポンサーメディア積算】!AA:AA, Results【技術役員スポンサーメディア積算】!F:F, "本部") + SUMIFS(Results【技術役員スポンサーメディア積算】!AA:AA, Results【技術役員スポンサーメディア積算】!G:G, "本部")) / SUMPRODUCT(--(Results【技術役員スポンサーメディア積算】!F:F="本部") + --(Results【技術役員スポンサーメディア積算】!G:G="本部")))} -> 0 | D16: 116 | E16: 19 | F16: =E16*C16*D16 -> 0 | G16: ='物価（案3）'!$I$10 -> 1.34 | H16: =ROUNDUP($C16*$D16*$E16*$G16,0) -> 0 | K16: =Results【技術役員スポンサーメディア積算】!#REF! -> #REF! | L16: =$K16*$G16 -> #REF!
B17: メディア | C17: {=IF(SUMPRODUCT(--(Results【技術役員スポンサーメディア積算】!F:F="メディア") + --(Results【技術役員スポンサーメディア積算】!G:G="メディア"))=0, 0, (SUMIFS(Results【技術役員スポンサーメディア積算】!AA:AA, Results【技術役員スポンサーメディア積算】!F:F, "メディア") + SUMIFS(Results【技術役員スポンサーメディア積算】!AA:AA, Results【技術役員スポンサーメディア積算】!G:G, "メディア")) / SUMPRODUCT(--(Results【技術役員スポンサーメディア積算】!F:F="メディア") + --(Results【技術役員スポンサーメディア積算】!G:G="メディア")))} -> 0 | D17: 1600 | E17: 18 | F17: =E17*C17*D17 -> 0 | G17: ='物価（案3）'!$I$10 -> 1.34 | H17: =ROUNDUP($C17*$D17*$E17*$G17,0) -> 0 | K17: =Results【技術役員スポンサーメディア積算】!#REF! -> #REF! | L17: =$K17*$G17 -> #REF!
B18: 技術役員（競技役員） | C18: {=IF(SUMPRODUCT(--(Results【技術役員スポンサーメディア積算】!F:F="技術役員") + --(Results【技術役員スポンサーメディア積算】!G:G="技術役員"))=0, 0, (SUMIFS(Results【技術役員スポンサーメディア積算】!AA:AA, Results【技術役員スポンサーメディア積算】!F:F, "技術役員") + SUMIFS(Results【技術役員スポンサーメディア積算】!AA:AA, Results【技術役員スポンサーメディア積算】!G:G, "技術役員")) / SUMPRODUCT(--(Results【技術役員スポンサーメディア積算】!F:F="技術役員") + --(Results【技術役員スポンサーメディア積算】!G:G="技術役員")))} -> 22916.587 | D18: 812 | E18: 18 | F18: =E18*C18*D18 -> 3.3494884e+08 | G18: ='物価（案3）'!$I$10 -> 1.34 | H18: =ROUNDUP($C18*$D18*$E18*$G18,0) -> 448831439 | K18: =Results【技術役員スポンサーメディア積算】!#REF! -> #REF! | L18: =$K18*$G18 -> #REF!
B19: 技術役員（DCO) | C19: {=IF(SUMPRODUCT(--(Results【技術役員スポンサーメディア積算】!F:F="DCO") + --(Results【技術役員スポンサーメディア積算】!G:G="DCO"))=0, 0, (SUMIFS(Results【技術役員スポンサーメディア積算】!AA:AA, Results【技術役員スポンサーメディア積算】!F:F, "DCO") + SUMIFS(Results【技術役員スポンサーメディア積算】!AA:AA, Results【技術役員スポンサーメディア積算】!G:G, "DCO")) / SUMPRODUCT(--(Results【技術役員スポンサーメディア積算】!F:F="DCO") + --(Results【技術役員スポンサーメディア積算】!G:G="DCO")))} -> 0 | D19: 122 | E19: 18 | F19: =E19*C19*D19 -> 0 | G19: ='物価（案3）'!$I$10 -> 1.34 | H19: =ROUNDUP($C19*$D19*$E19*$G19,0) -> 0 | K19: =Results【技術役員スポンサーメディア積算】!#REF! -> #REF! | L19: =$K19*$G19 -> #REF!
A20: 合計 | B20: - | C20: - | D20: - | E20: - | F20: =SUBTOTAL(109,F4:F19) -> 9.6782564e+09 | G20: - | H20: =SUBTOTAL(109,H4:H19) -> 12968863540 | I20: =SUBTOTAL(109,I4:I19) -> 12968863540 | K20: =SUBTOTAL(109,K4:K19) -> #REF! | L20: =SUBTOTAL(109,L4:L19) -> #REF!
A22: FR料
B23: ステークホルダー | C23: 1室あたりの 平均単価 | D23: 部屋数 ※施設保有FR数 | E23: 契約日数 | F23: 金額 物価上昇前 （G、H列固定値） | G23: 物価上昇率（宿泊） 2021➡2026 | H23: 金額 物価上昇後 （G、H列固定値） | I23: 総 計 | K23: 【参考値】 金額 物価上昇前 （シミュレーション） | L23: 【参考値】 金額 物価上昇後 （シミュレーション）
A24: アジア | B24: 選手団 | C24: =IF(COUNTIFS(Results【技術役員スポンサーメディア積算】!C:C, "選手15000", Results【技術役員スポンサーメディア積算】!V:V, ">0")=0, 0, SUMIFS(Results【技術役員スポンサーメディア積算】!V:V, Results【技術役員スポンサーメディア積算】!C:C, "選手15000", Results【技術役員スポンサーメディア積算】!V:V, ">0") / COUNTIFS(Results【技術役員スポンサーメディア積算】!C:C, "選手15000", Results【技術役員スポンサーメディア積算】!V:V, ">0")) -> 0 | D24: =IF(COUNTIF(Results【技術役員スポンサーメディア積算】!C:C, "選手15000")=0, 0, SUMIF(Results【技術役員スポンサーメディア積算】!C:C, "選手15000", Results【技術役員スポンサーメディア積算】!I:I)) -> 0 | E24: =$E4+1 -> 33 | F24: =E24*C24*D24 -> 0 | G24: ='物価（案3）'!$I$10 -> 1.34 | H24: =ROUNDUP($C24*$D24*$E24*$G24,0) -> 0 | I24: =H24 -> 0 | K24: =Results【技術役員スポンサーメディア積算】!BI283 -> 691185467 | L24: =$K24*$G24 -> 9.2618853e+08
B25: ファミリー | C25: =IF(COUNTIFS(Results【技術役員スポンサーメディア積算】!D:D, "ファミリー", Results【技術役員スポンサーメディア積算】!V:V, ">0")=0, 0, SUMIFS(Results【技術役員スポンサーメディア積算】!V:V, Results【技術役員スポンサーメディア積算】!D:D, "ファミリー", Results【技術役員スポンサーメディア積算】!V:V, ">0") / COUNTIFS(Results【技術役員スポンサーメディア積算】!D:D, "ファミリー", Results【技術役員スポンサーメディア積算】!V:V, ">0")) -> 0 | D25: =IF(COUNTIF(Results【技術役員スポンサーメディア積算】!D:D, "ファミリー")=0, 0, SUMIF(Results【技術役員スポンサーメディア積算】!D:D, "ファミリー", Results【技術役員スポンサーメディア積算】!I:I)) -> 0 | E25: =$E6+1 -> 33 | F25: =E25*C25*D25 -> 0 | G25: ='物価（案3）'!$I$10 -> 1.34 | H25: =ROUNDUP($C25*$D25*$E25*$G25,0) -> 0 | I25: =SUM(H25:H27) -> 0 | K25: =Results【技術役員スポンサーメディア積算】!BJ283 -> 1898926146 | L25: =$K25*$G25 -> 2.544561e+09
B26: スポンサー | G26: ='物価（案3）'!$I$10 -> 1.34 | H26: =ROUNDUP($C26*$D26*$E26*$G26,0) -> 0 | L26: =$K26*$G26 -> 0
B27: NOC本部 | C27: {=IF(SUMPRODUCT(--(Results【技術役員スポンサーメディア積算】!C:C="本部") + --(Results【技術役員スポンサーメディア積算】!D:D="本部"))=0, 0, (SUMIFS(Results【技術役員スポンサーメディア積算】!V:V, Results【技術役員スポンサーメディア積算】!C:C, "本部") + SUMIFS(Results【技術役員スポンサーメディア積算】!V:V, Results【技術役員スポンサーメディア積算】!D:D, "本部")) / SUMPRODUCT(--(Results【技術役員スポンサーメディア積算】!C:C="本部") + --(Results【技術役員スポンサーメディア積算】!D:D="本部")))} -> 0 | D27: =IF(AND(COUNTIF(Results【技術役員スポンサーメディア積算】!C:C, "本部")=0, COUNTIF(Results【技術役員スポンサーメディア積算】!D:D, "本部")=0), 0, IFERROR(SUMIF(Results【技術役員スポンサーメディア積算】!C:C, "本部", Results【技術役員スポンサーメディア積算】!I:I), 0) + IFERROR(SUMIF(Results【技術役員スポンサーメディア積算】!D:D, "本部", Results【技術役員スポンサーメディア積算】!I:I), 0)) -> 0 | E27: =$E8+1 -> 37 | F27: =E27*C27*D27 -> 0 | G27: ='物価（案3）'!$I$10 -> 1.34 | H27: =ROUNDUP($C27*$D27*$E27*$G27,0) -> 0 | K27: =Results【技術役員スポンサーメディア積算】!BK283 -> 87385650 | L27: =$K27*$G27 -> 117096771
A28: パラ | B28: 選手団 | C28: =IF(COUNTIFS(Results【技術役員スポンサーメディア積算】!F:F, "選手", Results【技術役員スポンサーメディア積算】!V:V, ">0")=0, 0, SUMIFS(Results【技術役員スポンサーメディア積算】!V:V, Results【技術役員スポンサーメディア積算】!F:F, "選手", Results【技術役員スポンサーメディア積算】!V:V, ">0") / COUNTIFS(Results【技術役員スポンサーメディア積算】!F:F, "選手", Results【技術役員スポンサーメディア積算】!V:V, ">0")) -> 0 | D28: =IF(COUNTIF(Results【技術役員スポンサーメディア積算】!F:F, "選手")=0, 0, IFERROR(SUMIF(Results【技術役員スポンサーメディア積算】!F:F, "選手", Results【技術役員スポンサーメディア積算】!I:I), 0)) -> 0 | E28: =$E12+1 -> 19 | F28: =E28*C28*D28 -> 0 | G28: ='物価（案3）'!$I$10 -> 1.34 | H28: =ROUNDUP($C28*$D28*$E28*$G28,0) -> 0 | I28: =H28 -> 0 | K28: =Results【技術役員スポンサーメディア積算】!BL283 -> 321313565 | L28: =$K28*$G28 -> 4.3056018e+08
B29: ファミリー | C29: {=IF(SUMPRODUCT(--(Results【技術役員スポンサーメディア積算】!F:F="ファミリー") + --(Results【技術役員スポンサーメディア積算】!G:G="ファミリー"))=0, 0, (SUMIFS(Results【技術役員スポンサーメディア積算】!V:V, Results【技術役員スポンサーメディア積算】!F:F, "ファミリー") + SUMIFS(Results【技術役員スポンサーメディア積算】!V:V, Results【技術役員スポンサーメディア積算】!G:G, "ファミリー")) / SUMPRODUCT(--(Results【技術役員スポンサーメディア積算】!F:F="ファミリー") + --(Results【技術役員スポンサーメディア積算】!G:G="ファミリー")))} -> 0 | D29: =IF(COUNTIF(Results【技術役員スポンサーメディア積算】!F:F, "ファミリー")=0, 0, IFERROR(SUMIF(Results【技術役員スポンサーメディア積算】!F:F, "ファミリー", Results【技術役員スポンサーメディア積算】!I:I), 0)) -> 0 | E29: =$E14+1 -> 19 | F29: =E29*C29*D29 -> 0 | G29: ='物価（案3）'!$I$10 -> 1.34 | H29: =ROUNDUP($C29*$D29*$E29*$G29,0) -> 0 | I29: =SUM(H29:H30) -> 0 | K29: =Results【技術役員スポンサーメディア積算】!BN283 -> 0 | L29: =$K29*$G29 -> 0
B30: NPC本部 | C30: {=IF(SUMPRODUCT(--(Results【技術役員スポンサーメディア積算】!F:F="本部") + --(Results【技術役員スポンサーメディア積算】!G:G="本部"))=0, 0, (SUMIFS(Results【技術役員スポンサーメディア積算】!V:V, Results【技術役員スポンサーメディア積算】!F:F, "本部") + SUMIFS(Results【技術役員スポンサーメディア積算】!V:V, Results【技術役員スポンサーメディア積算】!G:G, "本部")) / SUMPRODUCT(--(Results【技術役員スポンサーメディア積算】!F:F="本部") + --(Results【技術役員スポンサーメディア積算】!G:G="本部")))} -> 0 | D30: =IF(COUNTIF(Results【技術役員スポンサーメディア積算】!F:F, "本部")=0, 0, IFERROR(SUMIF(Results【技術役員スポンサーメディア積算】!F:F, "本部", Results【技術役員スポンサーメディア積算】!I:I), 0)) -> 0 | E30: =$E16+1 -> 20 | F30: =E30*C30*D30 -> 0 | G30: ='物価（案3）'!$I$10 -> 1.34 | H30: =ROUNDUP($C30*$D30*$E30*$G30,0) -> 0 | K30: =Results【技術役員スポンサーメディア積算】!#REF! -> #REF! | L30: =$K30*$G30 -> #REF!
A31: 合計 | B31: - | C31: - | D31: - | E31: - | F31: =SUBTOTAL(109,F24:F30) -> 0 | G31: - | H31: =SUBTOTAL(109,H24:H30) -> 0 | I31: =SUBTOTAL(109,I24:I30) -> 0 | K31: =SUBTOTAL(109,K24:K30) -> #REF! | L31: =SUBTOTAL(109,L24:L30) -> #REF!
A32: ※契約泊数及び日数についてシミュレーションが流動的であるため最大利用期間で契約見込、その後精査しキャンセル期限までにキャンセルする。
H35: 宿泊料＋FR料
H36: アジア | I36: =I4+I6+I24+I25 -> 10511814540
H37: パラ | I37: =I12+I14+I28+I29 -> 2457049000
H38: 合計 | I38: =I36+I37 -> 12968863540

Sheet 消費者物価平均指数　IMF
A1: Country | B1: Subject Descriptor | C1: Units | D1: Scale | E1: Country/Series-specific Notes | F1: 2018 | G1: 2019 | H1: 2020 | I1: 2021 | J1: 2022 | K1: 2023 | L1: 2024 | M1: 2025 | N1: 2026 | O1: Estimates Start After
A2: Japan | B2: Inflation, average consumer prices | C2: Index | D2: Units | E2: Source: Ministry of Internal Affairs and Communications Latest actual data: 2023 Notes: The CPI basket was constructed by averaging 2019 and 2020 weights. Harmonized prices: No Base year: 2020 Primary domestic currency: Japanese yen Data last updated: 03/2024 | F2: 99.6 | G2: 100.02 | H2: 99.993 | I2: 99.759 | J2: 102.25 | K2: 105.591 | L2: 107.954 | M2: 110.217 | N2: 112.428 | O2: 2023
A3: 2021年基準指標 | F3: =F2/$I$2 -> 0.99840616 | G3: =G2/$I$2 -> 1.0026163 | H3: =H2/$I$2 -> 1.0023457 | I3: =I2/$I$2 -> 1 | J3: =J2/$I$2 -> 1.0249702 | K3: =K2/$I$2 -> 1.0584609 | L3: =L2/$I$2 -> 1.082148 | M3: =M2/$I$2 -> 1.1048326 | N3: =N2/$I$2 -> 1.1269961
A4: International Monetary Fund, World Economic Outlook Database, April 2024 | L4: 予測 | M4: 予測 | N4: 予測
A7: ※「宿泊」ではなく、「総合」

Sheet 物価（案1）
B1: 消費者物価指数（総合） | C1: 宿泊料 | D1: 宿泊料上昇率
A2: 2020実績 | B2: 99.9 | C2: 98.7 | D2: =ROUNDUP(C3/C2,2) -> 1.19
A3: 2021実績 | B3: 100 | C3: 116.9 | E3: =ROUNDUP(C4/C3,2) -> 0.98 | J3: 100 | K3: とすると
A4: 2022実績 | B4: 103.2 | C4: 113.6 | F4: =ROUNDUP(C5/C4,2) -> 1.26
A5: 2023実績 | B5: 106.3 | C5: 142.6 | G5: =ROUNDUP(AVERAGE(D2,E3,F4),2) -> 1.15
A6: 2024見込 | C6: =ROUNDUP(C5*G5,1) -> 164 | H6: =G5 -> 1.15
A7: 2025見込 | C7: =ROUNDUP(C6*H6,1) -> 188.6 | I7: =G5 -> 1.15
A8: 2026見込 | C8: =ROUNDUP(C7*I7,1) -> 216.9 | J8: =ROUNDUP(C8*100/C3,1) -> 185.6 | K8: になる
F10: 2021→2026宿泊物価上昇率 | I10: =ROUNDUP(C8/C3,2) -> 1.86

Sheet 物価（案2）
B1: 消費者物価指数（総合） | C1: 宿泊料 | D1: 宿泊料上昇率
A2: 2020実績 | B2: 99.9 | C2: 98.7 | D2: =ROUNDUP(C3/C2,2) -> 1.19
A3: 2021実績 | B3: 100 | C3: 116.9 | E3: =ROUNDUP(C4/C3,2) -> 0.98 | J3: 100 | K3: とすると
A4: 2022実績 | B4: 103.2 | C4: 113.6 | F4: =ROUNDUP(C5/C4,2) -> 1.26
A5: 2023実績 | B5: 106.3 | C5: 142.6 | G5: =F4 -> 1.26
A6: 2024見込 | C6: =ROUNDUP(C5*G5,1) -> 179.7 | H6: =G5 -> 1.26
A7: 2025見込 | C7: =ROUNDUP(C6*H6,1) -> 226.5 | I7: =G5 -> 1.26
A8: 2026見込 | C8: =ROUNDUP(C7*I7,1) -> 285.4 | J8: =ROUNDUP(C8*100/C3,1) -> 244.2 | K8: になる
F10: 2021→2026宿泊物価上昇率 | I10: =ROUNDUP(C8/C3,2) -> 2.45

Sheet 案3元データ
A1: 類・品目 | B1: 総合 | C1: 食料 | D1: 穀類 | E1: 米類 | F1: うるち米Ａ | G1: うるち米Ｂ | H1: パン | I1: 食パン | J1: あんパン | K1: カレーパン | L1: 麺類 | M1: ゆでうどん | N1: そうめん | O1: スパゲッティ | P1: カップ麺 | Q1: 中華麺 | R1: 他の穀類 | S1: 小麦粉 | T1: もち | U1: シリアル | V1: 魚介類 | W1: 生鮮魚介 | X1: まぐろ | Y1: あじ | Z1: いわし | AA1: かつお | AB1: さけ | AC1: さば | AD1: さんま | AE1: たい | AF1: ぶり | AG1: いか | AH1: たこ | AI1: えび | AJ1: あさり | AK1: かき（貝） | AL1: ほたて貝 | AM1: 塩干魚介 | AN1: 塩さけ | AO1: たらこ | AP1: しらす干し | AQ1: 干しあじ | AR1: 煮干し | AS1: ししゃも | AT1: いくら | AU1: 魚肉練製品 | AV1: 揚げかまぼこ | AW1: ちくわ | AX1: かまぼこ | AY1: 他の魚介加工品 | AZ1: かつお節 | BA1: 魚介漬物 | BB1: 魚介つくだ煮 | BC1: 魚介缶詰 | BD1: 肉類 | BE1: 生鮮肉 | BF1: 牛肉（国産品） | BG1: 牛肉（輸入品） | BH1: 豚肉（国産品） | BI1: 豚肉（輸入品） | BJ1: 鶏肉 | BK1: 加工肉 | BL1: ハム | BM1: ソーセージ | BN1: ベーコン | BO1: 味付け肉 | BP1: 乳卵類 | BQ1: 牛乳・乳製品 | BR1: 牛乳 | BS1: 牛乳 | BT1: 乳製品 | BU1: 粉ミルク | BV1: ヨーグルト | BW1: バター | BX1: チーズ（国産品） | BY1: チーズ（輸入品） | BZ1: 卵 | CA1: 鶏卵 | CB1: 野菜・海藻 | CC1: 生鮮野菜 | CD1: キャベツ | CE1: ほうれんそう | CF1: はくさい | CG1: ねぎ | CH1: レタス | CI1: ブロッコリー | CJ1: もやし | CK1: アスパラガス | CL1: さつまいも | CM1: じゃがいも | CN1: さといも | CO1: だいこん | CP1: にんじん | CQ1: ごぼう | CR1: たまねぎ | CS1: れんこん | CT1: ながいも | CU1: しょうが | CV1: えだまめ | CW1: さやいんげん | CX1: かぼちゃ | CY1: きゅうり | CZ1: なす | DA1: トマト | DB1: ピーマン | DC1: 生しいたけ | DD1: えのきたけ | DE1: しめじ | DF1: カット野菜 | DG1: 乾物・加工品類 | DH1: 乾物・海藻 | DI1: 干ししいたけ | DJ1: 干しのり | DK1: わかめ | DL1: こんぶ | DM1: ひじき | DN1: 大豆加工品 | DO1: 豆腐 | DP1: 油揚げ | DQ1: 納豆 | DR1: 他の野菜・海藻加工品 | DS1: こんにゃく | DT1: 梅干し | DU1: だいこん漬 | DV1: はくさい漬 | DW1: キムチ | DX1: こんぶつくだ煮 | DY1: 野菜缶詰 | DZ1: 果物 | EA1: 生鮮果物 | EB1: りんご | EC1: みかん | ED1: オレンジ | EE1: しらぬひ | EF1: 梨 | EG1: ぶどうＡ | EH1: ぶどうＢ | EI1: 柿 | EJ1: 桃 | EK1: すいか | EL1: メロン | EM1: いちご | EN1: バナナ | EO1: キウイフルーツ | EP1: さくらんぼ | EQ1: アボカド | ER1: 果物加工品 | ES1: ナッツ | ET1: 油脂・調味料 | EU1: 油脂 | EV1: 食用油 | EW1: マーガリン | EX1: 調味料 | EY1: 食塩 | EZ1: しょう油 | FA1: みそ | FB1: 砂糖 | FC1: 酢 | FD1: ソース | FE1: ケチャップ | FF1: マヨネーズ | FG1: ドレッシング | FH1: ジャム | FI1: カレールウ | FJ1: 乾燥スープ | FK1: 風味調味料 | FL1: ふりかけ | FM1: たれ | FN1: つゆ | FO1: 合わせ調味料 | FP1: パスタソース | FQ1: 菓子類 | FR1: ようかん | FS1: まんじゅう | FT1: だいふく餅 | FU1: カステラ | FV1: ケーキ | FW1: ゼリー | FX1: プリン | FY1: シュークリーム | FZ1: ロールケーキ | GA1: せんべい | GB1: ビスケット | GC1: ポテトチップス | GD1: キャンデー | GE1: チョコレート | GF1: アイスクリーム | GG1: 落花生 | GH1: チューインガム | GI1: 調理食品 | GJ1: 主食的調理食品 | GK1: すし（弁当）Ａ | GL1: すし（弁当）Ｂ | GM1: 弁当Ａ | GN1: 弁当Ｂ | GO1: おにぎり | GP1: 調理パン | GQ1: 冷凍米飯 | GR1: 調理パスタ | GS1: 調理ピザ | GT1: 無菌包装米飯 | GU1: 他の調理食品 | GV1: うなぎかば焼き | GW1: サラダ | GX1: コロッケ | GY1: 豚カツ | GZ1: からあげ | HA1: ぎょうざ | HB1: やきとり | HC1: ハンバーグ | HD1: 冷凍調理コロッケ | HE1: 冷凍調理ハンバーグ | HF1: 冷凍ぎょうざ | HG1: 調理カレー | HH1: 混ぜごはんのもと | HI1: 煮豆 | HJ1: 焼き魚 | HK1: きんぴら | HL1: 焼豚 | HM1: サラダチキン | HN1: おでん | HO1: 飲料 | HP1: 茶類 | HQ1: 緑茶 | HR1: 紅茶 | HS1: 茶飲料 | HT1: コーヒー・ココア | HU1: インスタントコーヒー | HV1: コーヒー豆 | HW1: コーヒー飲料Ａ | HX1: コーヒー飲料Ｂ | HY1: 他の飲料 | HZ1: 果実ジュース | IA1: 果汁入り飲料 | IB1: 野菜ジュース | IC1: 炭酸飲料 | ID1: ノンアルコールビール | IE1: 乳酸菌飲料 | IF1: ミネラルウォーター | IG1: 宅配水 | IH1: スポーツドリンク | II1: 豆乳 | IJ1: 酒類 | IK1: 清酒 | IL1: 焼酎 | IM1: ビール | IN1: 発泡酒 | IO1: ウイスキー | IP1: ワイン（国産品） | IQ1: ワイン（輸入品） | IR1: チューハイ | IS1: ビール風アルコール飲料 | IT1: 外食 | IU1: 一般外食 | IV1: うどん（外食） | IW1: 日本そば（外食） | IX1: 中華そば（外食） | IY1: スパゲッティ（外食） | IZ1: すし（外食）Ａ | JA1: すし（外食）Ｂ | JB1: 天丼（外食） | JC1: カレーライス（外食） | JD1: 牛丼（外食） | JE1: 豚カツ定食（外食） | JF1: しょうが焼き定食（外食） | JG1: フライドチキン（外食） | JH1: ぎょうざ（外食） | JI1: ハンバーグ（外食） | JJ1: 焼肉（外食） | JK1: ハンバーガー（外食） | JL1: サンドイッチ（外食） | JM1: ピザ（配達） | JN1: ドーナツ（外食） | JO1: コーヒー（外食）Ａ | JP1: コーヒー（外食）Ｂ | JQ1: ビール（外食） | JR1: やきとり（外食） | JS1: 学校給食 | JT1: 学校給食（小学校） | JU1: 学校給食（中学校） | JV1: 住居 | JW1: 家賃 | JX1: 民営家賃 | JY1: 民営家賃 | JZ1: 公営・都市再生機構・公社家賃 | KA1: 公営家賃 | KB1: 都市再生機構・公社家賃 | KC1: 持家の帰属家賃 | KD1: 持家の帰属家賃 | KE1: 設備修繕・維持 | KF1: 設備材料 | KG1: システムバス | KH1: 温水洗浄便座 | KI1: 給湯器 | KJ1: システムキッチン | KK1: カーポート | KL1: 修繕材料 | KM1: 工事その他のサービス | KN1: 畳替え代 | KO1: 水道工事費 | KP1: 塀工事費 | KQ1: 外壁塗装費 | KR1: 屋根修理費 | KS1: 植木職手間代 | KT1: ふすま張替費 | KU1: 大工手間代 | KV1: 駐車場工事費 | KW1: 壁紙張替費 | KX1: 火災・地震保険料 | KY1: 光熱・水道 | KZ1: 電気代 | LA1: 電気代 | LB1: ガス代 | LC1: 都市ガス代 | LD1: プロパンガス | LE1: 他の光熱 | LF1: 灯油 | LG1: 上下水道料 | LH1: 水道料 | LI1: 下水道料 | LJ1: 家具・家事用品 | LK1: 家庭用耐久財 | LL1: 家事用耐久財 | LM1: 電子レンジ | LN1: 電気炊飯器 | LO1: ガステーブル | LP1: 電気冷蔵庫 | LQ1: 電気掃除機 | LR1: 電気洗濯機（全自動洗濯機） | LS1: 電気洗濯機（洗濯乾燥機） | LT1: 冷暖房用器具 | LU1: ルームエアコン | LV1: 温風ヒーター | LW1: 空気清浄機 | LX1: 一般家具 | LY1: 食堂セット | LZ1: ソファ | MA1: 食器戸棚 | MB1: 室内装備品 | MC1: 照明器具 | MD1: カーペット | ME1: カーテン | MF1: クッション | MG1: 寝具類 | MH1: ベッド | MI1: 布団 | MJ1: 敷布 | MK1: 布団カバー | ML1: 敷きパッド | MM1: 家事雑貨 | MN1: 食器類 | MO1: 茶わん | MP1: 皿 | MQ1: 台所用品 | MR1: 水筒 | MS1: 鍋 | MT1: フライパン | MU1: スポンジたわし | MV1: 他の家事雑貨 | MW1: 電球・ランプ | MX1: タオル | MY1: マット | MZ1: 物干し用ハンガー | NA1: 収納ケース | NB1: 家事用消耗品 | NC1: ティシュ・トイレットペーパー | ND1: ティシュペーパー | NE1: トイレットペーパー | NF1: 洗剤 | NG1: 台所用洗剤 | NH1: 洗濯用洗剤 | NI1: 他の家事用消耗品 | NJ1: ラップ | NK1: ポリ袋 | NL1: 殺虫剤 | NM1: 柔軟仕上剤 | NN1: 芳香・消臭剤 | NO1: キッチンペーパー | NP1: 漂白剤 | NQ1: 家事サービス | NR1: 家事代行料 | NS1: 家事代行料 | NT1: 清掃代 | NU1: リサイクル料金 | NV1: 浄化槽清掃代 | NW1: 他の家事サービス | NX1: モップレンタル料 | NY1: 被服及び履物 | NZ1: 衣料 | OA1: 和服 | OB1: 婦人用着物 | OC1: 婦人用帯 | OD1: 洋服 | OE1: 男子用洋服 | OF1: 背広服（春夏物，中級品） | OG1: 背広服（春夏物，普通品） | OH1: 背広服（秋冬物，中級品） | OI1: 背広服（秋冬物，普通品） | OJ1: 男子用上着 | OK1: 男子用ズボン（春夏物） | OL1: 男子用ズボン（秋冬物） | OM1: 男子用ズボン（ジーンズ） | ON1: 男子用コート | OO1: 男子用学校制服 | OP1: 婦人用洋服 | OQ1: 婦人用スーツ（春夏物，中級品） | OR1: 婦人用スーツ（春夏物，普通品） | OS1: 婦人用スーツ（秋冬物，中級品） | OT1: 婦人用スーツ（秋冬物，普通品） | OU1: ワンピース（春夏物） | OV1: ワンピース（秋冬物） | OW1: 婦人用上着 | OX1: スカート（春夏物） | OY1: スカート（秋冬物） | OZ1: 婦人用スラックス（秋冬物） | PA1: 婦人用スラックス（ジーンズ） | PB1: 婦人用コート | PC1: 女子用学校制服 | PD1: 子供用洋服 | PE1: 子供用ズボン（春夏物） | PF1: 子供用ズボン（秋冬物） | PG1: 乳児服 | PH1: シャツ・セーター・下着類 | PI1: シャツ・セーター類 | PJ1: 男子用シャツ・セーター類 | PK1: ワイシャツ | PL1: 男子用スポーツシャツ（長袖） | PM1: 男子用スポーツシャツ（半袖） | PN1: 男子用セーター | PO1: 婦人用シャツ・セーター類 | PP1: ブラウス（長袖） | PQ1: ブラウス（半袖） | PR1: 婦人用Ｔシャツ（長袖） | PS1: 婦人用Ｔシャツ（半袖） | PT1: 婦人用セーター（長袖） | PU1: 婦人用セーター（半袖） | PV1: 子供用シャツ・セーター類 | PW1: 子供用Ｔシャツ（長袖） | PX1: 子供用Ｔシャツ（半袖） | PY1: 下着類 | PZ1: 男子用下着類 | QA1: 男子用シャツ（半袖） | QB1: 男子用パンツ | QC1: 男子用パジャマ | QD1: 婦人用下着類 | QE1: ブラジャー | QF1: 婦人用ショーツ | QG1: ランジェリー | QH1: 子供用下着類 | QI1: 子供用下着 | QJ1: 履物類 | QK1: 男子靴 | QL1: 婦人靴 | QM1: 子供靴 | QN1: 運動靴 | QO1: サンダル | QP1: スリッパ | QQ1: 他の被服 | QR1: 帽子 | QS1: ネクタイ | QT1: マフラー | QU1: 男子用靴下 | QV1: 婦人用ストッキング | QW1: 婦人用ソックス | QX1: ベルト | QY1: 被服関連サービス | QZ1: クリーニング代Ａ | RA1: クリーニング代Ｂ | RB1: 履物修理代 | RC1: 被服賃借料 | RD1: 保健医療 | RE1: 医薬品・健康保持用摂取品 | RF1: 総合かぜ薬 | RG1: 解熱鎮痛剤 | RH1: 胃腸薬 | RI1: ビタミン剤Ａ | RJ1: ビタミン剤Ｂ | RK1: ドリンク剤 | RL1: 皮膚病薬 | RM1: はり薬 | RN1: 目薬 | RO1: 漢方薬 | RP1: 鼻炎薬 | RQ1: 健康保持用摂取品Ａ | RR1: 健康保持用摂取品Ｂ | RS1: 保健医療用品・器具 | RT1: 紙おむつ（乳幼児用） | RU1: 紙おむつ（大人用） | RV1: 生理用ナプキン | RW1: 入浴剤 | RX1: コンタクトレンズ用剤 | RY1: マスク | RZ1: 軽度失禁用品 | SA1: 眼鏡 | SB1: コンタクトレンズ | SC1: 血圧計 | SD1: 補聴器 | SE1: サポーター | SF1: 保健医療サービス | SG1: 診療代 | SH1: マッサージ料金 | SI1: 人間ドック受診料 | SJ1: 予防接種料 | SK1: 交通・通信 | SL1: 交通 | SM1: 鉄道運賃（ＪＲ） | SN1: 普通運賃（ＪＲ） | SO1: 料金（ＪＲ，在来線） | SP1: 料金（ＪＲ，新幹線） | SQ1: 通学定期（ＪＲ） | SR1: 通勤定期（ＪＲ） | SS1: 鉄道運賃（ＪＲ以外） | ST1: 普通運賃（ＪＲ以外） | SU1: 通学定期（ＪＲ以外） | SV1: 通勤定期（ＪＲ以外） | SW1: 他の交通 | SX1: 一般路線バス代 | SY1: 高速バス代 | SZ1: タクシー代 | TA1: 航空運賃 | TB1: 有料道路料 | TC1: 高速自動車国道料金 | TD1: 都市高速道路料金 | TE1: 自動車等関係費 | TF1: 自動車 | TG1: 軽乗用車 | TH1: 小型乗用車 | TI1: 普通乗用車Ａ | TJ1: 普通乗用車Ｂ | TK1: 自転車 | TL1: 自転車Ａ | TM1: 自転車Ｂ | TN1: 自動車等維持 | TO1: ガソリン | TP1: 自動車タイヤ | TQ1: 自動車バッテリー | TR1: カーナビゲーション | TS1: ドライブレコーダー | TT1: 自動車整備費（定期点検） | TU1: 自動車整備費（パンク修理） | TV1: 自動車オイル交換料 | TW1: 車庫借料 | TX1: 駐車料金 | TY1: 自動車免許手数料 | TZ1: レンタカー料金 | UA1: 洗車代 | UB1: ロードサービス料 | UC1: 自動車保険料（自賠責） | UD1: 自動車保険料（任意） | UE1: 通信 | UF1: はがき | UG1: 封書 | UH1: 通信料（固定電話） | UI1: 通信料（携帯電話） | UJ1: 運送料 | UK1: 携帯電話機 | UL1: 教育 | UM1: 授業料等 | UN1: ＰＴＡ会費（小学校） | UO1: ＰＴＡ会費（中学校） | UP1: 中学校授業料（私立） | UQ1: 高等学校授業料（公立） | UR1: 高等学校授業料（私立） | US1: 大学授業料（国立） | UT1: 大学授業料（私立） | UU1: 短期大学授業料（私立） | UV1: 専修学校授業料（私立） | UW1: 教科書・学習参考教材 | UX1: 教科書 | UY1: 学習参考教材 | UZ1: 補習教育 | VA1: 補習教育（小学校） | VB1: 補習教育（中学校） | VC1: 補習教育（高校・予備校） | VD1: 教養娯楽 | VE1: 教養娯楽用耐久財 | VF1: テレビ | VG1: ビデオレコーダー | VH1: パソコン（デスクトップ型） | VI1: パソコン（ノート型） | VJ1: タブレット端末 | VK1: プリンタ | VL1: カメラ | VM1: ピアノ | VN1: 学習用机 | VO1: 教養娯楽用品 | VP1: 文房具 | VQ1: ボールペン | VR1: ノートブック | VS1: はさみ | VT1: 運動用具類 | VU1: ゴルフクラブ | VV1: グローブ | VW1: テニスラケット | VX1: 釣ざお | VY1: トレーニングパンツ | VZ1: 水着 | WA1: 競技用靴 | WB1: 玩具 | WC1: 家庭用ゲーム機 | WD1: ゲームソフト | WE1: 人形 | WF1: 玩具自動車 | WG1: 組立玩具 | WH1: 切り花 | WI1: 切り花（カーネーション） | WJ1: 切り花（きく） | WK1: 切り花（バラ） | WL1: 他の教養娯楽用品 | WM1: メモリーカード | WN1: コンパクトディスク | WO1: ビデオソフト | WP1: ペットフード（ドッグフード） | WQ1: ペットフード（キャットフード） | WR1: ペットトイレ用品 | WS1: 鉢植え | WT1: 園芸用土 | WU1: 園芸用肥料 | WV1: 電池 | WW1: プリンタ用インク | WX1: 書籍・他の印刷物 | WY1: 新聞代 | WZ1: 新聞代（地方・ブロック紙） | XA1: 新聞代（全国紙） | XB1: 雑誌 | XC1: 月刊誌 | XD1: 週刊誌 | XE1: 書籍 | XF1: 単行本Ａ | XG1: 単行本Ｂ | XH1: 教養娯楽サービス | XI1: 宿泊料 | XJ1: 宿泊料 | XK1: パック旅行費 | XL1: 外国パック旅行費 | XM1: 月謝類 | XN1: 講習料（英会話） | XO1: 講習料（書道） | XP1: 講習料（音楽） | XQ1: 講習料（ダンス） | XR1: 講習料（水泳） | XS1: 講習料（体育） | XT1: 自動車教習料 | XU1: 他の教養娯楽サービス | XV1: 放送受信料 | XW1: 放送受信料（ＮＨＫ） | XX1: 放送受信料（ケーブル） | XY1: 放送受信料（ＮＨＫ・ケーブル以外） | XZ1: 入場・観覧・ゲーム代 | YA1: 映画観覧料 | YB1: 演劇観覧料 | YC1: サッカー観覧料 | YD1: プロ野球観覧料 | YE1: ゴルフ練習料金 | YF1: ゴルフプレー料金 | YG1: ボウリングゲーム代 | YH1: プール使用料 | YI1: フィットネスクラブ使用料 | YJ1: 文化施設入場料 | YK1: テーマパーク入場料 | YL1: カラオケルーム使用料 | YM1: 他の娯楽サービス | YN1: 写真撮影代 | YO1: ビデオソフトレンタル料 | YP1: インターネット接続料 | YQ1: ウェブコンテンツ利用料 | YR1: 獣医代 | YS1: ペット美容院代 | YT1: 諸雑費 | YU1: 理美容サービス | YV1: 入浴料 | YW1: 理髪料 | YX1: パーマネント代 | YY1: カット代 | YZ1: ヘアカラーリング代 | ZA1: エステティック料金 | ZB1: 理美容用品 | ZC1: 理容器具 | ZD1: 電気かみそり | ZE1: 歯ブラシ | ZF1: 石けん類 | ZG1: 手洗い用石けん | ZH1: ボディーソープ | ZI1: 洗顔料 | ZJ1: クレンジング | ZK1: シャンプー | ZL1: ヘアコンディショナー | ZM1: 歯磨き | ZN1: 化粧品 | ZO1: 整髪料 | ZP1: 養毛剤 | ZQ1: 化粧クリームＡ | ZR1: 化粧クリームＢ | ZS1: 化粧水Ａ | ZT1: 化粧水Ｂ | ZU1: 乳液Ａ | ZV1: 乳液Ｂ | ZW1: ファンデーションＡ | ZX1: ファンデーションＢ | ZY1: 口紅Ａ | ZZ1: 口紅Ｂ | AAA1: ヘアカラーリング剤 | AAB1: 美容液 | AAC1: 身の回り用品 | AAD1: かばん類 | AAE1: バッグＡ | AAF1: バッグＢ | AAG1: 通学用かばん | AAH1: 旅行用かばん | AAI1: 腕時計・指輪 | AAJ1: 指輪 | AAK1: 腕時計 | AAL1: 他の身の回り用品 | AAM1: 傘 | AAN1: ハンカチーフ | AAO1: たばこ | AAP1: たばこ（国産品） | AAQ1: たばこ（輸入品） | AAR1: 他の諸雑費 | AAS1: 葬儀料 | AAT1: 傷害保険料 | AAU1: 保育所保育料 | AAV1: 学童保育料 | AAW1: 介護料 | AAX1: 行政証明書手数料 | AAY1: パスポート取得料 | AAZ1: 振込手数料 | ABA1: 警備料 | ABB1: 生鮮食品 | ABC1: 生鮮魚介（再掲） | ABD1: 生鮮野菜（再掲） | ABE1: 生鮮果物（再掲） | ABF1: 生鮮食品を除く総合 | ABG1: 生鮮食品を除く食料 | ABH1: 持家の帰属家賃を除く総合 | ABI1: 持家の帰属家賃を除く住居 | ABJ1: 持家の帰属家賃を除く家賃 | ABK1: 持家の帰属家賃及び生鮮食品を除く総合 | ABL1: エネルギー | ABM1: 生鮮食品及びエネルギーを除く総合 | ABN1: 食料（酒類を除く）及びエネルギーを除く総合 | ABO1: 教育関係費 | ABP1: 教養娯楽関係費 | ABQ1: 情報通信関係費 | ABS1: 消費者物価指数 2020年基準消費者物価指数 長期時系列データ 品目別価格指数 全国 年度平均 | ファイル | 統計データを探す | 政府統計の総合窓口 | ABT1: ←抜粋元
A2: Group/Item | B2: All items | C2: Food | D2: Cereals | E2: Rice | F2: Non-glutinous rice-A | G2: Non-glutinous rice-B | H2: Bread | I2: White bread | J2: Bean-jam buns | K2: Curry buns | L2: Noodles | M2: Boiled “Udon” | N2: “Somen”, fine wheat noodles | O2: Spaghetti | P2: Instant noodles in cups | Q2: Chinese noodles | R2: Other cereals | S2: Wheat flour | T2: “Mochi”, rice-cakes | U2: Cereal | V2: Fish & seafood | W2: Fresh fish & seafood | X2: Tuna fish | Y2: Horse mackerel | Z2: Sardines | AA2: Bonito | AB2: Salmon | AC2: Mackerel | AD2: Saury | AE2: Sea bream | AF2: Yellowtail | AG2: Cuttlefish | AH2: Octopus | AI2: Prawns | AJ2: Short-necked clams | AK2: Oysters | AL2: Scallops | AM2: Salted & dried fish | AN2: Salted salmon | AO2: Salted cod roe | AP2: “Shirasu-boshi”, dried young sardines | AQ2: Dried horse mackerel | AR2: “Niboshi”, dried small sardines | AS2: Capelin | AT2: Salmon roe | AU2: Fish-paste products | AV2: “Agekamaboko”, fried fish-paste patties | AW2: “Chikuwa”, baked fish-paste bars | AX2: “Kamaboko”, steamed fish-paste cakes | AY2: Other processed fish & seafood | AZ2: Dried bonito fillets | BA2: Pickled fish | BB2: Fish prepared in soy sauce | BC2: Canned fish | BD2: Meats | BE2: Raw meats | BF2: Beef (domestic) | BG2: Beef (imported) | BH2: Pork (domestic) | BI2: Pork (imported) | BJ2: Chicken | BK2: Meat products | BL2: Ham | BM2: Sausages | BN2: Bacon | BO2: Seasoned meat | BP2: Dairy products & eggs | BQ2: Fresh milk & dairy products | BR2: Fresh milk | BS2: Fresh milk | BT2: Dairy products | BU2: Powdered milk | BV2: Yogurt | BW2: Butter | BX2: Cheese (domestic) | BY2: Cheese (imported) | BZ2: Eggs | CA2: Hen eggs | CB2: Vegetables & seaweeds | CC2: Fresh vegetables | CD2: Cabbage | CE2: Spinach | CF2: Chinese cabbage | CG2: Welsh onions | CH2: Lettuce | CI2: Broccoli | CJ2: Bean sprouts | CK2: Asparagus | CL2: Sweet potatoes | CM2: White potatoes | CN2: Taros | CO2: Radishes | CP2: Carrots | CQ2: Burdocks | CR2: Onions | CS2: Lotus roots | CT2: “Naga-imo”, yams | CU2: Ginger | CV2: Green soybeans | CW2: Kidney beans | CX2: Pumpkins | CY2: Cucumbers | CZ2: Eggplants | DA2: Tomatoes | DB2: Green peppers | DC2: “Shiitake”, Japanese mushrooms, fresh | DD2: “Enokitake”, mushrooms | DE2: “Shimeji”, mushrooms | DF2: Cut vegetables | DG2: Processed vegetables & seaweeds | DH2: Dried vegetables & seaweeds | DI2: “Shiitake”, Japanese mushrooms, dried | DJ2: Dried laver | DK2: “Wakame”, seaweed | DL2: Dried tangle | DM2: “Hijiki”, edible brown algae | DN2: Soybean products | DO2: “Tofu”, bean curd | DP2: Fried bean curd | DQ2: “Natto”, fermented soybeans | DR2: Other processed vegetables & seaweeds | DS2: “Konnyaku”, devil's-tongue | DT2: “Umeboshi”, pickled plums | DU2: Pickled radishes | DV2: Pickled Chinese cabbage | DW2: “Kimuchi” | DX2: Tangle prepared in soy sauce | DY2: Canned vegetables | DZ2: Fruits | EA2: Fresh fruits | EB2: Apples | EC2: Mandarin oranges | ED2: Oranges | EE2: “Shiranui”, citrus fruits | EF2: Pears | EG2: Grapes-A | EH2: Grapes-B | EI2: Persimmons | EJ2: Peaches | EK2: Watermelons | EL2: Melons | EM2: Strawberries | EN2: Bananas | EO2: Kiwi fruits | EP2: Cherries | EQ2: Avocados | ER2: Processed fruits | ES2: Nuts | ET2: Oils, fats & seasonings | EU2: Oils & fats | EV2: Edible oil | EW2: Margarine | EX2: Seasonings | EY2: Salt | EZ2: Soy sauce | FA2: Soybean paste | FB2: Sugar | FC2: Vinegar | FD2: Worcester sauce | FE2: Ketchup | FF2: Mayonnaise | FG2: Dressing | FH2: Jam | FI2: Instant curry mix | FJ2: Instant dried soup | FK2: Flavor seasonings | FL2: “Furikake”, granular flavor seasonings | FM2: “Tare”, liquid seasonings | FN2: “Tsuyu”, liquid seasonings | FO2: Mixed seasonings | FP2: Prepared pasta sauce | FQ2: Cakes & candies | FR2: “Yokan”, sweet bean jelly | FS2: “Manju”, bean-jam cakes | FT2: “Daifukumochi”, rice cakes stuffed with sweetened bean jam | FU2: “Kasutera”, sponge cakes | FV2: Cakes | FW2: Jelly | FX2: Pudding | FY2: Cream puffs | FZ2: Roll cakes | GA2: “Sembei”, Japanese crackers | GB2: Biscuits | GC2: Potato chips | GD2: Candies | GE2: Chocolate | GF2: Ice cream | GG2: Peanuts | GH2: Chewing gum | GI2: Cooked food | GJ2: Cooked food with rice, bread or noodles | GK2: Sushi (box lunch)-A | GL2: Sushi (box lunch)-B | GM2: Box lunch-A | GN2: Box lunch-B | GO2: Rice balls | GP2: Bread like sandwiches | GQ2: Frozen cooked rice | GR2: Cooked pasta | GS2: Processed pizza | GT2: Aseptic packaged cooked rice | GU2: Other cooked food | GV2: “Kabayaki”, broiled eels | GW2: Salad | GX2: Croquettes | GY2: Pork cutlets | GZ2: Deep fried chicken | HA2: “Gyoza” | HB2: “Yakitori”, grilled chicken | HC2: Hamburg steaks | HD2: Frozen croquettes | HE2: Frozen hamburg steak | HF2: Frozen“Gyoza” | HG2: Cooked curry | HH2: “Mazegohan no moto”, prepared materials to steamed rice with assorted ingredients | HI2: Boiled beans | HJ2: Grilled fish | HK2: “Kimpira” | HL2: Roast pork | HM2: “Salad chicken” | HN2: “Oden”, Japanese stew | HO2: Beverages | HP2: Tea | HQ2: Green tea | HR2: Black tea | HS2: Tea beverages | HT2: Coffee & cocoa | HU2: Instant coffee | HV2: Coffee beans | HW2: Coffee beverages-A | HX2: Coffee beverages-B | HY2: Other beverages | HZ2: Fruit juice | IA2: Beverages containing juice | IB2: Vegetable juice | IC2: Carbonated beverages | ID2: Non-alcoholic beer | IE2: Fermented lactic drinks | IF2: Mineral water | IG2: Home delivery water | IH2: Sports drinks | II2: Soy milk | IJ2: Alcoholic beverages | IK2: “Sake” | IL2: “Shochu”, distilled spirits | IM2: Beer | IN2: Low-malt beer | IO2: Whisky | IP2: Wine (domestic) | IQ2: Wine (imported) | IR2: “Chu-hi”, liquor with soda & fruits | IS2: Beer-flavored alcoholic beverages | IT2: Meals outside the home | IU2: Eating out | IV2: “Udon”, Japanese noodles (eating out) | IW2: “Soba”, Japanese noodles (eating out) | IX2: Chinese noodles (eating out) | IY2: Spaghetti (eating out) | IZ2: Sushi (eating out)-A | JA2: Sushi (eating out)-B | JB2: Tempura bowls (eating out) | JC2: Curry & rice (eating out) | JD2: Beef bowls (eating out) | JE2: Pork cutlet set meals (eating out) | JF2: Ginger pork set meals (eating out) | JG2: Fried chickens (eating out) | JH2: “Gyoza” (eating out) | JI2: Hamburg steaks (eating out) | JJ2: Broiled meat (eating out) | JK2: Hamburgers (eating out) | JL2: Sandwiches (eating out) | JM2: Delivered pizza | JN2: Doughnuts (eating out) | JO2: Coffee (eating out)-A | JP2: Coffee (eating out)-B | JQ2: Beer (eating out) | JR2: “Yakitori”, grilled chicken (eating out) | JS2: School lunch | JT2: (elementary school) | JU2: (junior high school) | JV2: Housing | JW2: Rent | JX2: House rent, private | JY2: House rent, private | JZ2: House rent, public, Urban Renaissance Agency & public corporation | KA2: House rent, public | KB2: House rent, Urban Renaissance Agency & public corporation | KC2: Imputed rent | KD2: Imputed rent | KE2: Repairs & maintenance | KF2: Tools & materials for repairs & maintenance | KG2: Custom bath | KH2: Toilet seat with a hot douche | KI2: Hot-water supply equipment | KJ2: Custom kitchen | KK2: Carports | KL2: Materials for repairs & maintenance | KM2: Service charges for repairs & maintenance | KN2: “Tatami” reupholstering | KO2: Plumbing | KP2: Fence construction | KQ2: External wall coating | KR2: Repairing roofs | KS2: Gardening | KT2: “Fusuma”, sliding doors, reupholstering | KU2: Carpentering | KV2: Parking lot construction | KW2: Wallpaper reupholstering | KX2: Fire & earthquake insurance premium | KY2: Fuel, light & water charges | KZ2: Electricity | LA2: Electricity | LB2: Gas | LC2: Gas, manufactured & piped | LD2: Liquefied propane | LE2: Other fuel & light | LF2: Kerosene | LG2: Water & sewerage charges | LH2: Water charges | LI2: Sewerage charges | LJ2: Furniture & household utensils | LK2: Household durable goods | LL2: Durable goods assisting housework | LM2: Microwave ovens | LN2: Electric rice-cookers | LO2: Gas cooking tables | LP2: Refrigerators | LQ2: Vacuum cleaners | LR2: Washing machines | LS2: Washing & drying machines | LT2: Heating & cooling appliances | LU2: Room air conditioners | LV2: Fan heaters | LW2: Air cleaners | LX2: General furniture | LY2: Dining sets | LZ2: Sofas | MA2: Kitchen cabinets | MB2: Interior furnishings | MC2: Lighting apparatus | MD2: Carpets | ME2: Curtains | MF2: Cushions | MG2: Bedding | MH2: Beds | MI2: Japanese style futon | MJ2: Sheets | MK2: Duvet covers | ML2: Mattress pads | MM2: Domestic utensils | MN2: Tableware | MO2: Bowls | MP2: Dishes | MQ2: Kitchen utensils | MR2: Canteens | MS2: Pans | MT2: Frying pans | MU2: Scrubbing sponges | MV2: Other domestic utensils | MW2: Electric bulbs & lamps | MX2: Towels | MY2: Mattings | MZ2: Clothes drying hangers | NA2: Storage cases | NB2: Domestic non-durable goods | NC2: Facial tissue & rolled toilet paper | ND2: Facial tissue | NE2: Rolled toilet paper | NF2: Detergent | NG2: Liquid detergent, kitchen | NH2: Detergent, laundry | NI2: Other domestic non-durable goods | NJ2: Food wrap | NK2: Plastic bags | NL2: Insecticide | NM2: Fabric softener | NN2: Air fresheners & deodorizer | NO2: Kitchen paper | NP2: Bleach | NQ2: Domestic services | NR2: Domestic help | NS2: Domestic help | NT2: Cleaning fees | NU2: Recycle fees | NV2: Septic tank cleaning fees | NW2: Other domestic services | NX2: Mop-rental fees | NY2: Clothes & footwear | NZ2: Clothes | OA2: Japanese clothing | OB2: Women's“Kimono” | OC2: Women's“Obi” | OD2: Clothing | OE2: Men's clothing | OF2: Men's suits (for spring & summer, medium) | OG2: Men's suits (for spring & summer, ordinary) | OH2: Men's suits (for autumn & winter, medium) | OI2: Men's suits (for autumn & winter, ordinary) | OJ2: Men's jackets | OK2: Men's slacks (for spring & summer) | OL2: Men's slacks (for autumn & winter) | OM2: Men's slacks (jeans) | ON2: Men's coats | OO2: Boys' school uniforms | OP2: Women's clothing | OQ2: Women's suits (for spring & summer, medium) | OR2: Women's suits (for spring & summer, ordinary) | OS2: Women's suits (for autumn & winter, medium) | OT2: Women's suits (for autumn & winter, ordinary) | OU2: One-piece dresses (for spring & summer) | OV2: One-piece dresses (for autumn & winter) | OW2: Women's jackets | OX2: Skirts (for spring & summer) | OY2: Skirts (for autumn & winter) | OZ2: Women's slacks (for autumn & winter) | PA2: Women's slacks (jeans) | PB2: Women's coats | PC2: Girls' school uniforms | PD2: Children's clothing | PE2: Children's trousers (for spring & summer) | PF2: Children's trousers (for autumn & winter) | PG2: Babies' clothes | PH2: Shirts, sweaters & underwear | PI2: Shirts & sweaters | PJ2: Men's shirts & sweaters | PK2: Men's business shirts | PL2: Men's sports shirts (long sleeves) | PM2: Men's sports shirts (short sleeves) | PN2: Men's sweaters | PO2: Women's shirts & sweaters | PP2: Blouses (long sleeves) | PQ2: Blouses (short sleeves) | PR2: Women's T-shirts (long sleeves) | PS2: Women's T-shirts (short sleeves) | PT2: Women's sweaters (long sleeves) | PU2: Women's sweaters (short sleeves) | PV2: Children's shirts & sweaters | PW2: Children's T-shirts (long sleeves) | PX2: Children's T-shirts (short sleeves) | PY2: Underwear | PZ2: Men's underwear | QA2: Men's undershirts | QB2: Men's underpants | QC2: Men's pajamas | QD2: Women's underwear | QE2: Brassieres | QF2: Panties | QG2: Lingeries | QH2: Children's underwear | QI2: Children's underwear | QJ2: Footwear | QK2: Men's shoes | QL2: Women's shoes | QM2: Children's shoes | QN2: Canvas shoes | QO2: Sandals | QP2: Slippers | QQ2: Other clothing | QR2: Hats & caps | QS2: Neckties | QT2: Mufflers | QU2: Men's socks | QV2: Women's stockings | QW2: Women's socks | QX2: Belts | QY2: Services related to clothing | QZ2: Laundry charges-A | RA2: Laundry charges-B | RB2: Footwear repair charges | RC2: Charges for clothing rent | RD2: Medical care | RE2: Medicines & health fortification | RF2: Medicines for cold | RG2: Antipyretic & analgesic medicines | RH2: Gastrointestinal medicines | RI2: Vitamin preparations-A | RJ2: Vitamin preparations-B | RK2: Health drinks | RL2: Dermal medicines | RM2: Plasters | RN2: Eyewashes | RO2: Chinese medicines | RP2: Medicines for rhinitis | RQ2: Health fortification-A | RR2: Health fortification-B | RS2: Medical supplies & appliances | RT2: Disposable diapers (for babies) | RU2: Disposable diapers (for adults) | RV2: Sanitary napkins | RW2: Bath additives | RX2: Contact lenses cleaning solution | RY2: Masks | RZ2: Supplies for slight incontinence | SA2: Spectacles | SB2: Contact lenses | SC2: Sphygmomanometers | SD2: Hearing aids | SE2: Supporters | SF2: Medical services | SG2: Medical treatment | SH2: Charges for massage | SI2: Fees for complete medical checkup | SJ2: Fees for vaccination | SK2: Transportation & communication | SL2: Public transportation | SM2: Railway fares (JR) | SN2: (ordinary fares) | SO2: (special fares, excluding “Shinkansen”) | SP2: (special fares, for “Shinkansen”) | SQ2: (students' season tickets) | SR2: (commuters' season tickets) | SS2: Railway fares (excluding JR) | ST2: (ordinary fares) | SU2: (students' season tickets) | SV2: (commuters' season tickets) | SW2: Other public transportation | SX2: Fixed route bus fares | SY2: Expressway bus fares | SZ2: Taxi fares | TA2: Airplane fares | TB2: Highway tolls | TC2: National expressway tolls | TD2: City expressway tolls | TE2: Private transportation | TF2: Automobiles | TG2: Light motor vehicles (0.66L or less) | TH2: Small motor vehicles | TI2: Motor vehicles-A | TJ2: Motor vehicles-B | TK2: Bicycles | TL2: Bicycles-A | TM2: Bicycles-B | TN2: Automotive maintenance | TO2: Gasoline | TP2: Tires | TQ2: Automobile batteries | TR2: Automobile navigations | TS2: Drive recorders | TT2: Automotive maintenance charges (regular inspections) | TU2: Automotive maintenance charges (puncture repairs) | TV2: Motor oil replacement | TW2: Charges for garage rental | TX2: Charges for parking | TY2: Charges for driving license | TZ2: Charges for rental car | UA2: Car wash fees | UB2: Road services | UC2: Automotive insurance premium (compulsion) | UD2: Automotive insurance premium (option) | UE2: Communication | UF2: Postcards | UG2: Letters | UH2: Telephone charges (fixed-line phone) | UI2: Telephone charges (mobile phone) | UJ2: Forwarding charges | UK2: Mobile phones | UL2: Education | UM2: School fees | UN2: PTA membership fees (elementary school) | UO2: PTA membership fees (junior high school) | UP2: Junior high school fees (private) | UQ2: High school fees (public) | UR2: High school fees (private) | US2: College & university fees (national) | UT2: College & university fees (private) | UU2: Junior college fees (private) | UV2: Special training school fees (private) | UW2: School textbooks & reference books for study | UX2: School textbooks | UY2: Reference books for study | UZ2: Tutorial fees | VA2: (elementary school) | VB2: (junior high school) | VC2: (high school & preparatory school) | VD2: Culture & recreation | VE2: Recreational durable goods | VF2: TV sets | VG2: Video recorders | VH2: Personal computers (desktop) | VI2: Personal computers (notes) | VJ2: Tablet computers | VK2: PC printers | VL2: Cameras | VM2: Pianos | VN2: Desks | VO2: Recreational goods | VP2: Stationery | VQ2: Ball-point pens | VR2: Notebooks | VS2: Scissors | VT2: Sporting goods | VU2: Golf clubs | VV2: Baseball gloves | VW2: Tennis rackets | VX2: Fishing rods | VY2: Pants for exercise | VZ2: Swimming suits | WA2: Athletic shoes | WB2: Toys | WC2: Computer games for domestic use | WD2: Game softwares | WE2: Dolls | WF2: Toy cars | WG2: Building blocks | WH2: Cut flowers | WI2: (Carnations) | WJ2: (Chrysanthemums) | WK2: (Roses) | WL2: Other recreational goods | WM2: Memory cards | WN2: Compact discs | WO2: Video softwares | WP2: Pet foods (dog foods) | WQ2: Pet foods (cat foods) | WR2: Pet toilet supplies | WS2: Potted plants | WT2: Gardening earth | WU2: Horticultural fertilizer | WV2: Batteries | WW2: Ink cartridges for printer | WX2: Books & other reading materials | WY2: Newspapers | WZ2: (regional) | XA2: (national) | XB2: Magazines | XC2: Monthly magazines | XD2: Weekly magazines | XE2: Books | XF2: Books-A | XG2: Books-B | XH2: Recreational services | XI2: Hotel charges | XJ2: Hotel charges | XK2: Charges for package tours | XL2: Charges for package tours to overseas | XM2: Lesson fees | XN2: (English conversation school) | XO2: (calligraphy school) | XP2: (music school) | XQ2: (dancing school) | XR2: (swimming school) | XS2: (physical education school) | XT2: Lesson fees, driving school | XU2: Other recreational services | XV2: Charges for TV license | XW2: Charges for NHK TV license | XX2: Charges for cable TV license | XY2: Charges for other TV licenses | XZ2: Admission & game charges | YA2: Admission to movies | YB2: Admission to theater | YC2: Admission to soccer | YD2: Admission to professional baseball games | YE2: Charges for practicing golf | YF2: Charges for playing golf | YG2: Game charges, bowling | YH2: Swimming pool charges | YI2: Fitness club fees | YJ2: Admission fees to cultural establishments | YK2: Admission fees to theme parks | YL2: “Karaoke” room charges | YM2: Other recreational services | YN2: Photography fees | YO2: Charges for video rental | YP2: Internet connection charges | YQ2: Charges for web content | YR2: Veterinary surgeon fees | YS2: Grooming parlor fees | YT2: Miscellaneous | YU2: Personal care services | YV2: Bathing charges | YW2: Charges for barbers' services | YX2: Permanent wave charges | YY2: Haircut charges | YZ2: Hair dyeing charges | ZA2: Charges for beauty-treatment | ZB2: Toilet articles | ZC2: Toilet utensils | ZD2: Electric shavers | ZE2: Toothbrushes | ZF2: Soap & others | ZG2: Hand soap | ZH2: Body soap | ZI2: Facial wash | ZJ2: Cleansing products | ZK2: Shampoo | ZL2: Hair conditioner | ZM2: Toothpaste | ZN2: Cosmetics | ZO2: Hair styling products | ZP2: Hair tonic | ZQ2: Face cream-A | ZR2: Face cream-B | ZS2: Toilet lotion-A | ZT2: Toilet lotion-B | ZU2: Milky lotion-A | ZV2: Milky lotion-B | ZW2: Foundation-A | ZX2: Foundation-B | ZY2: Lipsticks-A | ZZ2: Lipsticks-B | AAA2: Hair color | AAB2: Face serums | AAC2: Personal effects | AAD2: Bags | AAE2: Bags-A | AAF2: Bags-B | AAG2: School knapsacks | AAH2: Suitcases | AAI2: Watches & rings | AAJ2: Rings | AAK2: Wrist watches | AAL2: Other personal effects | AAM2: Umbrellas | AAN2: Handkerchiefs | AAO2: Tobacco | AAP2: (domestics) | AAQ2: (imported) | AAR2: Other miscellaneous | AAS2: Funeral fees | AAT2: Charges for accident insurance | AAU2: Nursery school fees | AAV2: After-school childcare fees | AAW2: Charges for nursing care | AAX2: Charges for administrative certificates | AAY2: Charges for acquisition of passport | AAZ2: Charges for transfer commission | ABA2: Home security services | ABB2: Fresh food | ABC2: Fresh fish & seafood (reentry) | ABD2: Fresh vegetables (reentry) | ABE2: Fresh fruits (reentry) | ABF2: All items, less fresh food | ABG2: Food, less fresh food | ABH2: All items, less imputed rent | ABI2: Housing, less imputed rent | ABJ2: Rent, less imputed rent | ABK2: All items, less imputed rent & fresh food | ABL2: Energy | ABM2: All items, less fresh food and energy | ABN2: All items, less food (less alcoholic beverages) and energy | ABO2: Expenses for education | ABP2: Expenses for culture & recreation | ABQ2: Expenses for information & communication | ABS2: 2020年基準消費者物価指数 品目別価格指数（1970年度～最新年度）より抜粋
A3: 類・品目符号(Group/Item code) | B3: 0001 | C3: 0002 | D3: 0003 | E3: 0004 | F3: 1001 | G3: 1002 | H3: 0005 | I3: 1021 | J3: 1022 | K3: 1023 | L3: 0006 | M3: 1031 | N3: 1041 | O3: 1042 | P3: 1051 | Q3: 1052 | R3: 0007 | S3: 1071 | T3: 1081 | U3: 1090 | V3: 0008 | W3: 0009 | X3: 1101 | Y3: 1102 | Z3: 1103 | AA3: 1104 | AB3: 1106 | AC3: 1107 | AD3: 1108 | AE3: 1110 | AF3: 1111 | AG3: 1112 | AH3: 1113 | AI3: 1114 | AJ3: 1131 | AK3: 1132 | AL3: 1133 | AM3: 0010 | AN3: 1141 | AO3: 1142 | AP3: 1143 | AQ3: 1144 | AR3: 1146 | AS3: 1150 | AT3: 1167 | AU3: 0011 | AV3: 1151 | AW3: 1152 | AX3: 1153 | AY3: 0012 | AZ3: 1161 | BA3: 1165 | BB3: 1166 | BC3: 1173 | BD3: 0013 | BE3: 0014 | BF3: 1201 | BG3: 1203 | BH3: 1211 | BI3: 1214 | BJ3: 1221 | BK3: 0015 | BL3: 1252 | BM3: 1261 | BN3: 1271 | BO3: 1292 | BP3: 0016 | BQ3: 0017 | BR3: 0018 | BS3: 1303 | BT3: 0019 | BU3: 1311 | BV3: 1333 | BW3: 1321 | BX3: 1331 | BY3: 1332 | BZ3: 0020 | CA3: 1341 | CB3: 0021 | CC3: 0022 | CD3: 1401 | CE3: 1402 | CF3: 1403 | CG3: 1405 | CH3: 1406 | CI3: 1409 | CJ3: 1407 | CK3: 1410 | CL3: 1411 | CM3: 1412 | CN3: 1413 | CO3: 1414 | CP3: 1415 | CQ3: 1416 | CR3: 1417 | CS3: 1419 | CT3: 1420 | CU3: 1421 | CV3: 1430 | CW3: 1432 | CX3: 1433 | CY3: 1434 | CZ3: 1435 | DA3: 1436 | DB3: 1437 | DC3: 1438 | DD3: 1442 | DE3: 1443 | DF3: 1444 | DG3: 0023 | DH3: 0024 | DI3: 1453 | DJ3: 1461 | DK3: 1462 | DL3: 1463 | DM3: 1464 | DN3: 0025 | DO3: 1471 | DP3: 1472 | DQ3: 1473 | DR3: 0026 | DS3: 1481 | DT3: 1482 | DU3: 1483 | DV3: 1486 | DW3: 1487 | DX3: 1485 | DY3: 1491 | DZ3: 0027 | EA3: 0028 | EB3: 1502 | EC3: 1511 | ED3: 1515 | EE3: 1517 | EF3: 1521 | EG3: 1531 | EH3: 1532 | EI3: 1541 | EJ3: 1551 | EK3: 1561 | EL3: 1563 | EM3: 1571 | EN3: 1581 | EO3: 1582 | EP3: 1572 | EQ3: 1583 | ER3: 0029 | ES3: 1594 | ET3: 0030 | EU3: 0031 | EV3: 1601 | EW3: 1602 | EX3: 0032 | EY3: 1611 | EZ3: 1621 | FA3: 1631 | FB3: 1632 | FC3: 1633 | FD3: 1641 | FE3: 1642 | FF3: 1643 | FG3: 1645 | FH3: 1644 | FI3: 1652 | FJ3: 1653 | FK3: 1654 | FL3: 1656 | FM3: 1655 | FN3: 1659 | FO3: 1657 | FP3: 1658 | FQ3: 0033 | FR3: 1701 | FS3: 1702 | FT3: 1703 | FU3: 1711 | FV3: 1712 | FW3: 1784 | FX3: 1714 | FY3: 1713 | FZ3: 1715 | GA3: 1741 | GB3: 1721 | GC3: 1783 | GD3: 1732 | GE3: 1761 | GF3: 1782 | GG3: 1772 | GH3: 1781 | GI3: 0034 | GJ3: 0035 | GK3: 1795 | GL3: 1798 | GM3: 1791 | GN3: 1797 | GO3: 1793 | GP3: 1792 | GQ3: 1794 | GR3: 1796 | GS3: 1799 | GT3: 1790 | GU3: 0036 | GV3: 1801 | GW3: 1811 | GX3: 1821 | GY3: 1831 | GZ3: 1842 | HA3: 1881 | HB3: 1843 | HC3: 1844 | HD3: 1851 | HE3: 1852 | HF3: 1853 | HG3: 1871 | HH3: 1891 | HI3: 1812 | HJ3: 1802 | HK3: 1813 | HL3: 1814 | HM3: 1892 | HN3: 1893 | HO3: 0037 | HP3: 0038 | HQ3: 1902 | HR3: 1911 | HS3: 1914 | HT3: 0039 | HU3: 1921 | HV3: 1922 | HW3: 1923 | HX3: 1924 | HY3: 0040 | HZ3: 1930 | IA3: 1931 | IB3: 1941 | IC3: 1951 | ID3: 1952 | IE3: 1972 | IF3: 1982 | IG3: 1984 | IH3: 1981 | II3: 1983 | IJ3: 0041 | IK3: 2003 | IL3: 2011 | IM3: 2021 | IN3: 2026 | IO3: 2033 | IP3: 2041 | IQ3: 2042 | IR3: 2012 | IS3: 2027 | IT3: 0042 | IU3: 0043 | IV3: 2101 | IW3: 2103 | IX3: 2102 | IY3: 2112 | IZ3: 2123 | JA3: 2121 | JB3: 2132 | JC3: 2133 | JD3: 2136 | JE3: 2142 | JF3: 2146 | JG3: 2164 | JH3: 2134 | JI3: 2141 | JJ3: 2145 | JK3: 2135 | JL3: 2161 | JM3: 2144 | JN3: 2163 | JO3: 2162 | JP3: 2165 | JQ3: 2171 | JR3: 2172 | JS3: 0044 | JT3: 2182 | JU3: 2183 | JV3: 0045 | JW3: 0046 | JX3: 0047 | JY3: 3000 | JZ3: 0048 | KA3: 3016 | KB3: 3017 | KC3: 0050 | KD3: 3030 | KE3: 0051 | KF3: 0052 | KG3: 3101 | KH3: 3103 | KI3: 3104 | KJ3: 3105 | KK3: 3106 | KL3: 3121 | KM3: 0053 | KN3: 3151 | KO3: 3176 | KP3: 3175 | KQ3: 3178 | KR3: 3162 | KS3: 3174 | KT3: 3171 | KU3: 3172 | KV3: 3179 | KW3: 3185 | KX3: 3180 | KY3: 0054 | KZ3: 0056 | LA3: 3500 | LB3: 0057 | LC3: 3600 | LD3: 3612 | LE3: 0058 | LF3: 3701 | LG3: 0059 | LH3: 3810 | LI3: 4610 | LJ3: 0060 | LK3: 0061 | LL3: 0062 | LM3: 4003 | LN3: 4002 | LO3: 4011 | LP3: 4021 | LQ3: 4032 | LR3: 4042 | LS3: 4043 | LT3: 0063 | LU3: 4063 | LV3: 4072 | LW3: 4075 | LX3: 0064 | LY3: 4092 | LZ3: 4093 | MA3: 4083 | MB3: 0066 | MC3: 4115 | MD3: 4121 | ME3: 4141 | MF3: 4142 | MG3: 0070 | MH3: 4201 | MI3: 4211 | MJ3: 4251 | MK3: 4271 | ML3: 4272 | MM3: 0073 | MN3: 0074 | MO3: 4301 | MP3: 4302 | MQ3: 0075 | MR3: 4326 | MS3: 4331 | MT3: 4334 | MU3: 4342 | MV3: 0076 | MW3: 4352 | MX3: 4361 | MY3: 4362 | MZ3: 4372 | NA3: 4373 | NB3: 0077 | NC3: 0078 | ND3: 4412 | NE3: 4413 | NF3: 0079 | NG3: 4431 | NH3: 4441 | NI3: 0080 | NJ3: 4401 | NK3: 4402 | NL3: 4451 | NM3: 4442 | NN3: 4471 | NO3: 4403 | NP3: 4472 | NQ3: 0081 | NR3: 0174 | NS3: 4501 | NT3: 0175 | NU3: 4521 | NV3: 4515 | NW3: 0176 | NX3: 4701 | NY3: 0082 | NZ3: 0083 | OA3: 0084 | OB3: 5011 | OC3: 5041 | OD3: 0085 | OE3: 0086 | OF3: 5101 | OG3: 5103 | OH3: 5102 | OI3: 5104 | OJ3: 5111 | OK3: 5122 | OL3: 5121 | OM3: 5123 | ON3: 5131 | OO3: 5141 | OP3: 0087 | OQ3: 5166 | OR3: 5167 | OS3: 5162 | OT3: 5168 | OU3: 5161 | OV3: 5163 | OW3: 5183 | OX3: 5169 | OY3: 5172 | OZ3: 5181 | PA3: 5179 | PB3: 5182 | PC3: 5184 | PD3: 0088 | PE3: 5195 | PF3: 5196 | PG3: 5193 | PH3: 0089 | PI3: 0090 | PJ3: 0091 | PK3: 5202 | PL3: 5211 | PM3: 5212 | PN3: 5221 | PO3: 0092 | PP3: 5231 | PQ3: 5232 | PR3: 5233 | PS3: 5234 | PT3: 5241 | PU3: 5242 | PV3: 0093 | PW3: 5243 | PX3: 5244 | PY3: 0094 | PZ3: 0095 | QA3: 5301 | QB3: 5311 | QC3: 5331 | QD3: 0096 | QE3: 5341 | QF3: 5351 | QG3: 5361 | QH3: 0097 | QI3: 5372 | QJ3: 0098 | QK3: 5601 | QL3: 5611 | QM3: 5641 | QN3: 5631 | QO3: 5671 | QP3: 5652 | QQ3: 0103 | QR3: 5501 | QS3: 5511 | QT3: 5572 | QU3: 5521 | QV3: 5531 | QW3: 5541 | QX3: 5571 | QY3: 0106 | QZ3: 5711 | RA3: 5712 | RB3: 5721 | RC3: 5731 | RD3: 0107 | RE3: 0108 | RF3: 6001 | RG3: 6002 | RH3: 6012 | RI3: 6021 | RJ3: 6022 | RK3: 6031 | RL3: 6051 | RM3: 6061 | RN3: 6062 | RO3: 6091 | RP3: 6003 | RQ3: 6090 | RR3: 6094 | RS3: 0109 | RT3: 6141 | RU3: 6142 | RV3: 6101 | RW3: 6095 | RX3: 6181 | RY3: 6102 | RZ3: 6182 | SA3: 6121 | SB3: 6161 | SC3: 6171 | SD3: 6172 | SE3: 6173 | SF3: 0110 | SG3: 6200 | SH3: 6221 | SI3: 6222 | SJ3: 6223 | SK3: 0111 | SL3: 0112 | SM3: 0179 | SN3: 7527 | SO3: 7528 | SP3: 7530 | SQ3: 7029 | SR3: 7030 | SS3: 0180 | ST3: 7008 | SU3: 7009 | SV3: 7010 | SW3: 0181 | SX3: 7050 | SY3: 7057 | SZ3: 7060 | TA3: 7070 | TB3: 0182 | TC3: 7363 | TD3: 7364 | TE3: 0113 | TF3: 0114 | TG3: 7105 | TH3: 7106 | TI3: 7113 | TJ3: 7115 | TK3: 0115 | TL3: 7201 | TM3: 7202 | TN3: 0116 | TO3: 7301 | TP3: 7311 | TQ3: 7312 | TR3: 7313 | TS3: 7315 | TT3: 7331 | TU3: 7335 | TV3: 7341 | TW3: 7342 | TX3: 7343 | TY3: 7351 | TZ3: 7344 | UA3: 7347 | UB3: 7350 | UC3: 7370 | UD3: 7390 | UE3: 0117 | UF3: 7401 | UG3: 7402 | UH3: 7410 | UI3: 7430 | UJ3: 7433 | UK3: 7446 | UL3: 0118 | UM3: 0119 | UN3: 8001 | UO3: 8002 | UP3: 8010 | UQ3: 8020 | UR3: 8030 | US3: 8040 | UT3: 8060 | UU3: 8070 | UV3: 8077 | UW3: 0120 | UX3: 8110 | UY3: 8100 | UZ3: 0121 | VA3: 8203 | VB3: 8201 | VC3: 8204 | VD3: 0122 | VE3: 0123 | VF3: 9013 | VG3: 9034 | VH3: 9078 | VI3: 9079 | VJ3: 9080 | VK3: 9081 | VL3: 9043 | VM3: 9051 | VN3: 9061 | VO3: 0128 | VP3: 0129 | VQ3: 9111 | VR3: 9121 | VS3: 9129 | VT3: 0130 | VU3: 9142 | VV3: 9141 | VW3: 9143 | VX3: 9144 | VY3: 9145 | VZ3: 9149 | WA3: 9140 | WB3: 0131 | WC3: 9154 | WD3: 9156 | WE3: 9151 | WF3: 9152 | WG3: 9153 | WH3: 0132 | WI3: 9181 | WJ3: 9182 | WK3: 9183 | WL3: 0133 | WM3: 9199 | WN3: 9172 | WO3: 9174 | WP3: 9193 | WQ3: 9196 | WR3: 9185 | WS3: 9184 | WT3: 9190 | WU3: 9189 | WV3: 9195 | WW3: 9128 | WX3: 0134 | WY3: 0135 | WZ3: 9204 | XA3: 9205 | XB3: 0136 | XC3: 9226 | XD3: 9230 | XE3: 0137 | XF3: 9261 | XG3: 9263 | XH3: 0138 | XI3: 0139 | XJ3: 9300 | XK3: 0177 | XL3: 9305 | XM3: 0140 | XN3: 9328 | XO3: 9329 | XP3: 9326 | XQ3: 9319 | XR3: 9313 | XS3: 9343 | XT3: 9320 | XU3: 0141 | XV3: 0142 | XW3: 9330 | XX3: 9368 | XY3: 9367 | XZ3: 0143 | YA3: 9341 | YB3: 9342 | YC3: 9345 | YD3: 9350 | YE3: 9353 | YF3: 9357 | YG3: 9361 | YH3: 9359 | YI3: 9362 | YJ3: 9374 | YK3: 9372 | YL3: 9395 | YM3: 0144 | YN3: 9381 | YO3: 9391 | YP3: 9397 | YQ3: 9403 | YR3: 9396 | YS3: 9188 | YT3: 0145 | YU3: 0146 | YV3: 9504 | YW3: 9511 | YX3: 9521 | YY3: 9531 | YZ3: 9532 | ZA3: 9505 | ZB3: 0147 | ZC3: 0148 | ZD3: 9602 | ZE3: 9611 | ZF3: 0149 | ZG3: 9621 | ZH3: 9626 | ZI3: 9627 | ZJ3: 9628 | ZK3: 9622 | ZL3: 9624 | ZM3: 9623 | ZN3: 0150 | ZO3: 9631 | ZP3: 9641 | ZQ3: 9650 | ZR3: 9652 | ZS3: 9660 | ZT3: 9661 | ZU3: 9690 | ZV3: 9692 | ZW3: 9670 | ZX3: 9672 | ZY3: 9680 | ZZ3: 9682 | AAA3: 9625 | AAB3: 9693 | AAC3: 0151 | AAD3: 0152 | AAE3: 9721 | AAF3: 9722 | AAG3: 9711 | AAH3: 9731 | AAI3: 0153 | AAJ3: 9741 | AAK3: 9751 | AAL3: 0154 | AAM3: 9701 | AAN3: 9761 | AAO3: 0155 | AAP3: 9799 | AAQ3: 9798 | AAR3: 0156 | AAS3: 9960 | AAT3: 9928 | AAU3: 9921 | AAV3: 9951 | AAW3: 9914 | AAX3: 9901 | AAY3: 9912 | AAZ3: 9920 | ABA3: 9931 | ABB3: 0157 | ABC3: 0158 | ABD3: 0159 | ABE3: 0160 | ABF3: 0161 | ABG3: 0172 | ABH3: 0163 | ABI3: 0164 | ABJ3: 0165 | ABK3: 0166 | ABL3: 0167 | ABM3: 0178 | ABN3: 0168 | ABO3: 0162 | ABP3: 0173 | ABQ3: 0169 | ABS3: 政府統計データ
A4: 含類総連番(Serial number) | B4: 001 | C4: 002 | D4: 003 | E4: 004 | F4: 005 | G4: 006 | H4: 007 | I4: 008 | J4: 009 | K4: 010 | L4: 011 | M4: 012 | N4: 013 | O4: 014 | P4: 015 | Q4: 016 | R4: 017 | S4: 018 | T4: 019 | U4: 020 | V4: 021 | W4: 022 | X4: 023 | Y4: 024 | Z4: 025 | AA4: 026 | AB4: 027 | AC4: 028 | AD4: 029 | AE4: 030 | AF4: 031 | AG4: 032 | AH4: 033 | AI4: 034 | AJ4: 035 | AK4: 036 | AL4: 037 | AM4: 038 | AN4: 039 | AO4: 040 | AP4: 041 | AQ4: 042 | AR4: 043 | AS4: 044 | AT4: 045 | AU4: 046 | AV4: 047 | AW4: 048 | AX4: 049 | AY4: 050 | AZ4: 051 | BA4: 052 | BB4: 053 | BC4: 054 | BD4: 055 | BE4: 056 | BF4: 057 | BG4: 058 | BH4: 059 | BI4: 060 | BJ4: 061 | BK4: 062 | BL4: 063 | BM4: 064 | BN4: 065 | BO4: 066 | BP4: 067 | BQ4: 068 | BR4: 069 | BS4: 070 | BT4: 071 | BU4: 072 | BV4: 073 | BW4: 074 | BX4: 075 | BY4: 076 | BZ4: 077 | CA4: 078 | CB4: 079 | CC4: 080 | CD4: 081 | CE4: 082 | CF4: 083 | CG4: 084 | CH4: 085 | CI4: 086 | CJ4: 087 | CK4: 088 | CL4: 089 | CM4: 090 | CN4: 091 | CO4: 092 | CP4: 093 | CQ4: 094 | CR4: 095 | CS4: 096 | CT4: 097 | CU4: 098 | CV4: 099 | CW4: 100 | CX4: 101 | CY4: 102 | CZ4: 103 | DA4: 104 | DB4: 105 | DC4: 106 | DD4: 107 | DE4: 108 | DF4: 109 | DG4: 110 | DH4: 111 | DI4: 112 | DJ4: 113 | DK4: 114 | DL4: 115 | DM4: 116 | DN4: 117 | DO4: 118 | DP4: 119 | DQ4: 120 | DR4: 121 | DS4: 122 | DT4: 123 | DU4: 124 | DV4: 125 | DW4: 126 | DX4: 127 | DY4: 128 | DZ4: 129 | EA4: 130 | EB4: 131 | EC4: 132 | ED4: 133 | EE4: 134 | EF4: 135 | EG4: 136 | EH4: 137 | EI4: 138 | EJ4: 139 | EK4: 140 | EL4: 141 | EM4: 142 | EN4: 143 | EO4: 144 | EP4: 145 | EQ4: 146 | ER4: 147 | ES4: 148 | ET4: 149 | EU4: 150 | EV4: 151 | EW4: 152 | EX4: 153 | EY4: 154 | EZ4: 155 | FA4: 156 | FB4: 157 | FC4: 158 | FD4: 159 | FE4: 160 | FF4: 161 | FG4: 162 | FH4: 163 | FI4: 164 | FJ4: 165 | FK4: 166 | FL4: 167 | FM4: 168 | FN4: 169 | FO4: 170 | FP4: 171 | FQ4: 172 | FR4: 173 | FS4: 174 | FT4: 175 | FU4: 176 | FV4: 177 | FW4: 178 | FX4: 179 | FY4: 180 | FZ4: 181 | GA4: 182 | GB4: 183 | GC4: 184 | GD4: 185 | GE4: 186 | GF4: 187 | GG4: 188 | GH4: 189 | GI4: 190 | GJ4: 191 | GK4: 192 | GL4: 193 | GM4: 194 | GN4: 195 | GO4: 196 | GP4: 197 | GQ4: 198 | GR4: 199 | GS4: 200 | GT4: 201 | GU4: 202 | GV4: 203 | GW4: 204 | GX4: 205 | GY4: 206 | GZ4: 207 | HA4: 208 | HB4: 209 | HC4: 210 | HD4: 211 | HE4: 212 | HF4: 213 | HG4: 214 | HH4: 215 | HI4: 216 | HJ4: 217 | HK4: 218 | HL4: 219 | HM4: 220 | HN4: 221 | HO4: 222 | HP4: 223 | HQ4: 224 | HR4: 225 | HS4: 226 | HT4: 227 | HU4: 228 | HV4: 229 | HW4: 230 | HX4: 231 | HY4: 232 | HZ4: 233 | IA4: 234 | IB4: 235 | IC4: 236 | ID4: 237 | IE4: 238 | IF4: 239 | IG4: 240 | IH4: 241 | II4: 242 | IJ4: 243 | IK4: 244 | IL4: 245 | IM4: 246 | IN4: 247 | IO4: 248 | IP4: 249 | IQ4: 250 | IR4: 251 | IS4: 252 | IT4: 253 | IU4: 254 | IV4: 255 | IW4: 256 | IX4: 257 | IY4: 258 | IZ4: 259 | JA4: 260 | JB4: 261 | JC4: 262 | JD4: 263 | JE4: 264 | JF4: 265 | JG4: 266 | JH4: 267 | JI4: 268 | JJ4: 269 | JK4: 270 | JL4: 271 | JM4: 272 | JN4: 273 | JO4: 274 | JP4: 275 | JQ4: 276 | JR4: 277 | JS4: 278 | JT4: 279 | JU4: 280 | JV4: 281 | JW4: 282 | JX4: 283 | JY4: 284 | JZ4: 285 | KA4: 286 | KB4: 287 | KC4: 288 | KD4: 289 | KE4: 290 | KF4: 291 | KG4: 292 | KH4: 293 | KI4: 294 | KJ4: 295 | KK4: 296 | KL4: 297 | KM4: 298 | KN4: 299 | KO4: 300 | KP4: 301 | KQ4: 302 | KR4: 303 | KS4: 304 | KT4: 305 | KU4: 306 | KV4: 307 | KW4: 308 | KX4: 309 | KY4: 310 | KZ4: 311 | LA4: 312 | LB4: 313 | LC4: 314 | LD4: 315 | LE4: 316 | LF4: 317 | LG4: 318 | LH4: 319 | LI4: 320 | LJ4: 321 | LK4: 322 | LL4: 323 | LM4: 324 | LN4: 325 | LO4: 326 | LP4: 327 | LQ4: 328 | LR4: 329 | LS4: 330 | LT4: 331 | LU4: 332 | LV4: 333 | LW4: 334 | LX4: 335 | LY4: 336 | LZ4: 337 | MA4: 338 | MB4: 339 | MC4: 340 | MD4: 341 | ME4: 342 | MF4: 343 | MG4: 344 | MH4: 345 | MI4: 346 | MJ4: 347 | MK4: 348 | ML4: 349 | MM4: 350 | MN4: 351 | MO4: 352 | MP4: 353 | MQ4: 354 | MR4: 355 | MS4: 356 | MT4: 357 | MU4: 358 | MV4: 359 | MW4: 360 | MX4: 361 | MY4: 362 | MZ4: 363 | NA4: 364 | NB4: 365 | NC4: 366 | ND4: 367 | NE4: 368 | NF4: 369 | NG4: 370 | NH4: 371 | NI4: 372 | NJ4: 373 | NK4: 374 | NL4: 375 | NM4: 376 | NN4: 377 | NO4: 378 | NP4: 379 | NQ4: 380 | NR4: 381 | NS4: 382 | NT4: 383 | NU4: 384 | NV4: 385 | NW4: 386 | NX4: 387 | NY4: 388 | NZ4: 389 | OA4: 390 | OB4: 391 | OC4: 392 | OD4: 393 | OE4: 394 | OF4: 395 | OG4: 396 | OH4: 397 | OI4: 398 | OJ4: 399 | OK4: 400 | OL4: 401 | OM4: 402 | ON4: 403 | OO4: 404 | OP4: 405 | OQ4: 406 | OR4: 407 | OS4: 408 | OT4: 409 | OU4: 410 | OV4: 411 | OW4: 412 | OX4: 413 | OY4: 414 | OZ4: 415 | PA4: 416 | PB4: 417 | PC4: 418 | PD4: 419 | PE4: 420 | PF4: 421 | PG4: 422 | PH4: 423 | PI4: 424 | PJ4: 425 | PK4: 426 | PL4: 427 | PM4: 428 | PN4: 429 | PO4: 430 | PP4: 431 | PQ4: 432 | PR4: 433 | PS4: 434 | PT4: 435 | PU4: 436 | PV4: 437 | PW4: 438 | PX4: 439 | PY4: 440 | PZ4: 441 | QA4: 442 | QB4: 443 | QC4: 444 | QD4: 445 | QE4: 446 | QF4: 447 | QG4: 448 | QH4: 449 | QI4: 450 | QJ4: 451 | QK4: 452 | QL4: 453 | QM4: 454 | QN4: 455 | QO4: 456 | QP4: 457 | QQ4: 458 | QR4: 459 | QS4: 460 | QT4: 461 | QU4: 462 | QV4: 463 | QW4: 464 | QX4: 465 | QY4: 466 | QZ4: 467 | RA4: 468 | RB4: 469 | RC4: 470 | RD4: 471 | RE4: 472 | RF4: 473 | RG4: 474 | RH4: 475 | RI4: 476 | RJ4: 477 | RK4: 478 | RL4: 479 | RM4: 480 | RN4: 481 | RO4: 482 | RP4: 483 | RQ4: 484 | RR4: 485 | RS4: 486 | RT4: 487 | RU4: 488 | RV4: 489 | RW4: 490 | RX4: 491 | RY4: 492 | RZ4: 493 | SA4: 494 | SB4: 495 | SC4: 496 | SD4: 497 | SE4: 498 | SF4: 499 | SG4: 500 | SH4: 501 | SI4: 502 | SJ4: 503 | SK4: 504 | SL4: 505 | SM4: 506 | SN4: 507 | SO4: 508 | SP4: 509 | SQ4: 510 | SR4: 511 | SS4: 512 | ST4: 513 | SU4: 514 | SV4: 515 | SW4: 516 | SX4: 517 | SY4: 518 | SZ4: 519 | TA4: 520 | TB4: 521 | TC4: 522 | TD4: 523 | TE4: 524 | TF4: 525 | TG4: 526 | TH4: 527 | TI4: 528 | TJ4: 529 | TK4: 530 | TL4: 531 | TM4: 532 | TN4: 533 | TO4: 534 | TP4: 535 | TQ4: 536 | TR4: 537 | TS4: 538 | TT4: 539 | TU4: 540 | TV4: 541 | TW4: 542 | TX4: 543 | TY4: 544 | TZ4: 545 | UA4: 546 | UB4: 547 | UC4: 548 | UD4: 549 | UE4: 550 | UF4: 551 | UG4: 552 | UH4: 553 | UI4: 554 | UJ4: 555 | UK4: 556 | UL4: 557 | UM4: 558 | UN4: 559 | UO4: 560 | UP4: 561 | UQ4: 562 | UR4: 563 | US4: 564 | UT4: 565 | UU4: 566 | UV4: 567 | UW4: 568 | UX4: 569 | UY4: 570 | UZ4: 571 | VA4: 572 | VB4: 573 | VC4: 574 | VD4: 575 | VE4: 576 | VF4: 577 | VG4: 578 | VH4: 579 | VI4: 580 | VJ4: 581 | VK4: 582 | VL4: 583 | VM4: 584 | VN4: 585 | VO4: 586 | VP4: 587 | VQ4: 588 | VR4: 589 | VS4: 590 | VT4: 591 | VU4: 592 | VV4: 593 | VW4: 594 | VX4: 595 | VY4: 596 | VZ4: 597 | WA4: 598 | WB4: 599 | WC4: 600 | WD4: 601 | WE4: 602 | WF4: 603 | WG4: 604 | WH4: 605 | WI4: 606 | WJ4: 607 | WK4: 608 | WL4: 609 | WM4: 610 | WN4: 611 | WO4: 612 | WP4: 613 | WQ4: 614 | WR4: 615 | WS4: 616 | WT4: 617 | WU4: 618 | WV4: 619 | WW4: 620 | WX4: 621 | WY4: 622 | WZ4: 623 | XA4: 624 | XB4: 625 | XC4: 626 | XD4: 627 | XE4: 628 | XF4: 629 | XG4: 630 | XH4: 631 | XI4: 632 | XJ4: 633 | XK4: 634 | XL4: 635 | XM4: 636 | XN4: 637 | XO4: 638 | XP4: 639 | XQ4: 640 | XR4: 641 | XS4: 642 | XT4: 643 | XU4: 644 | XV4: 645 | XW4: 646 | XX4: 647 | XY4: 648 | XZ4: 649 | YA4: 650 | YB4: 651 | YC4: 652 | YD4: 653 | YE4: 654 | YF4: 655 | YG4: 656 | YH4: 657 | YI4: 658 | YJ4: 659 | YK4: 660 | YL4: 661 | YM4: 662 | YN4: 663 | YO4: 664 | YP4: 665 | YQ4: 666 | YR4: 667 | YS4: 668 | YT4: 669 | YU4: 670 | YV4: 671 | YW4: 672 | YX4: 673 | YY4: 674 | YZ4: 675 | ZA4: 676 | ZB4: 677 | ZC4: 678 | ZD4: 679 | ZE4: 680 | ZF4: 681 | ZG4: 682 | ZH4: 683 | ZI4: 684 | ZJ4: 685 | ZK4: 686 | ZL4: 687 | ZM4: 688 | ZN4: 689 | ZO4: 690 | ZP4: 691 | ZQ4: 692 | ZR4: 693 | ZS4: 694 | ZT4: 695 | ZU4: 696 | ZV4: 697 | ZW4: 698 | ZX4: 699 | ZY4: 700 | ZZ4: 701 | AAA4: 702 | AAB4: 703 | AAC4: 704 | AAD4: 705 | AAE4: 706 | AAF4: 707 | AAG4: 708 | AAH4: 709 | AAI4: 710 | AAJ4: 711 | AAK4: 712 | AAL4: 713 | AAM4: 714 | AAN4: 715 | AAO4: 716 | AAP4: 717 | AAQ4: 718 | AAR4: 719 | AAS4: 720 | AAT4: 721 | AAU4: 722 | AAV4: 723 | AAW4: 724 | AAX4: 725 | AAY4: 726 | AAZ4: 727 | ABA4: 728 | ABB4: 729 | ABC4: 730 | ABD4: 731 | ABE4: 732 | ABF4: 733 | ABG4: 734 | ABH4: 735 | ABI4: 736 | ABJ4: 737 | ABK4: 738 | ABL4: 739 | ABM4: 740 | ABN4: 741 | ABO4: 742 | ABP4: 743 | ABQ4: 744
